Workbook

Sheet Modelo de Dominio
A1: Ir a objeto de dominio>>>
A3: #VALUE!

Sheet Objetos de Dominio
A1: <<<Ir al modelo de dominio
A2: Nombre | B2: Descripción | C2: Linea de vida | D2: Muestreo de Datos | E2: Caracterización objeto | F2: EventStorming | G2: Politicas
A3: Pais | B3: Representa el país al que pertenecen las sedes. | C3: 1 | D3: Ver | E3: Ver | F3: Ver | G3: Ver
A4: MetodoPago | B4: Representa las formas en que un cliente puede cancelar una compra (efectivo, tarjeta, transferencia, Nequi, entre otras). | C4: 1 | D4: Ver | E4: Ver | F4: Ver | G4: Ver
A5: Cliente | B5: Representa a la persona que adquiere productos en cualquiera de las sedes del negocio. | C5: 1 | D5: Ver | E5: Ver | F5: Ver | G5: Ver
A6: Marca | B6: Representa al fabricante de los accesorios y repuestos que comercializa el negocio. | C6: 1 | D6: Ver | E6: Ver | F6: Ver | G6: Ver
A7: Motivo | B7: Representa la razón por la que un cliente solicita devolver un producto. | C7: 1 | D7: Ver | E7: Ver | F7: Ver | G7: Ver
A8: TipoDocumento | B8: Representa el tipo de documento de identidad de una persona | C8: 1 | D8: Ver | E8: Ver | F8: Ver | G8: Ver
A9: Categoria | B9: Representa la clasificación a la que pertenece un producto dentro del catálogo. | C9: 1 | D9: Ver | E9: Ver | F9: Ver | G9: Ver
A10: Prefijo | B10: Representa el código de marcado telefónico asociado a un país para el registro de números de contacto | C10: 1 | D10: Ver | E10: Ver | F10: Ver | G10: Ver
A11: Persona | B11: Representa a un individuo en el sistema con sus datos generales de identificación para registrarse en el sistema | C11: 2 | D11: Ver | E11: Ver | F11: Ver | G11: Ver
A12: Producto | B12: Representa un artículo del catálogo general del negocio, independiente de la sede en la que se encuentre. | C12: 2 | D12: Ver | E12: Ver | F12: Ver | G12: Ver
A13: Departamento | B13: Representa el departamento o división administrativa al que pertenece una ciudad dentro de un país. | C13: 2 | D13: Ver | E13: Ver | F13: Ver | G13: Ver
A14: ClienteRegistrado | B14: Representa al cliente cuyos datos de identificación y contacto han sido registrados en el sistema | C14: 2 | D14: Ver | E14: Ver | F14: Ver | G14: Ver
... A34: AplicacionSaldo | B34: Representa el uso de un saldo a favor sobre un pago con saldo, y permite controlar el saldo de un cliente específico. | C34: 10 | D34: Ver | E34: Ver | F34: Ver | G34: Ver

Sheet M-Pais
A1: <<<Ir al modelo de dominio | B1: <<<Ir a objeto de dominio | C1: Ir a la caracterización>>> | D1: Ir al event storming>>> | E1: Ir a las políticas>>>
A2: Nombre: | B2: ='Objetos de Dominio'!A3 -> Pais
A3: Descripción: | B3: ='Objetos de Dominio'!B3 -> Representa el país al que pertenecen las sedes.
A4: Identificador único del país | B4: Nombre oficial del país | C4: Combinación única que indica que no puede existir más de un país con el mismo nombre
A5: ID | B5: Nombre | C5: PaisUnico
A6: 1 | B6: Colombia | C6: =B6 -> Colombia
A7: 2 | B7: Ecuador | C7: =B7 -> Ecuador
A8: 3 | B8: Perú | C8: =B8 -> Perú

Sheet C-Pais
A1: <<<Ir al modelo de dominio | B1: <<<Ir a objeto de dominio | C1: <<<Ir a muestreo del objeto | D1: Ir al event storming>>> | E1: Ir a las políticas>>>
A2: Nombre | B2: ='Objetos de Dominio'!A3 -> Pais
A3: Descripción | B3: ='Objetos de Dominio'!B3 -> Representa el país al que pertenecen las sedes.
A4: Nombre atributo | B4: Descripción atributo | C4: Identificador del objeto de dominio | D4: Tipo de dato | E4: Obligatorio | F4: Longitud mínima (si aplica) | G4: Longitud máxima (si aplica) | H4: Precisión (si aplica) | I4: Redondeo (si aplica) | J4: Rango inicial (si aplica) | K4: Rango final (si aplica) | L4: Formato (si aplica) | M4: Reglas especiales (si aplica) | N4: Dato calculado | O4: Aplica ajuste del dato (si aplica) | P4: Carácter de ajuste (si aplica) | Q4: Quitar espacios en blanco al inicio (si aplica) | R4: Quitar espacios en blanco al fin (si aplica) | S4: Dato sensible (si aplica) | T4: Valor por defecto (si aplica) | U4: Auto generado | V4: =HYPERLINK("#'C-Pais'!A16","buscarPaisPorFiltro") -> buscarPaisPorFiltro
A5: ID | B5: ='M-Pais'!A4 -> Identificador único del país | C5: Si | D5: Identificador único universal | E5: Si | F5: - | G5: - | H5: - | I5: - | J5: - | K5: - | L5: - | M5: Debe ser único y no debe repetirse en los distintos id's de los países | N5: No | O5: No | P5: - | Q5: No | R5: No | S5: - | T5: - | U5: Si | V5: Filtro | W5: No Mostrar
A6: Nombre | B6: ='M-Pais'!B4 -> Nombre oficial del país | C6: No | D6: Texto | E6: Si | F6: 2 | G6: 100 | H6: - | I6: - | J6: - | K6: - | L6: - | M6: Se debe asegurar una sanitización del dato, para garantizar que dentro de su contenido no tenga cualquier tipo de intento de ataque | N6: No | O6: No | P6: - | Q6: Si | R6: Si | S6: - | T6: - | U6: No | V6: Filtro | W6: Mostrar
A9: Nombre combinación única | B9: Descripción | C9: Atributos involucrados
A10: ='M-Pais'!C5 -> PaisUnico | B10: ='M-Pais'!C4 -> Combinación única que indica que no puede existir más de un país con el mismo nombre | C10: Nombre
A14: Responsabilidad | C14: Descripción | G14: Entradas | J14: Salida | O14: Políticas (Reglas de Negocio) | Q14: Excepción
G15: Parámetro | H15: Tipo de dato | I15: Descripción | J15: Tipo de Dato | K15: Descripción | O15: Política | P15: Descripción | Q15: Detalle | R15: ¿Qué hago?
A16: =HYPERLINK("#'C-Pais'!W4","buscarPaisPorFiltro") -> buscarPaisPorFiltro | C16: Permite buscar un país determinado por un criterio específico (nombre, id) | G16: filtro | H16: Pais | I16: Contiene la información de los filtros que servirán como base para llevar a cabo la consulta de la información | J16: Lista<Pais> | K16: Contiene la información de todos los países que cumplen con el filtro de consulta | O16: =HYPERLINK("#'P-Pais'!A5",'P-Pais'!A5) -> P-PAI-001 | P16: ='P-Pais'!B5 -> Asegurar que los datos requeridos sean válidos en tipo de dato, longitud, obligatoriedad y formato | Q16: Informar con un mensaje de error si ocurre un fallo al recuperar el catálogo de países | R16: Detener operación

Sheet E-Pais
A1: <<<Ir al modelo de dominio | B1: <<<Ir a objeto de dominio | C1: <<<Ir a muestreo del objeto | D1: <<<Ir a caracterización | E1: Ir a las políticas>>>
A2: Objeto de Dominio: | B2: ='Objetos de Dominio'!A3 -> Pais
A3: Descripción: | B3: ='Objetos de Dominio'!B3 -> Representa el país al que pertenecen las sedes.
A4: Actor | B4: Action/Command | D4: Entity/Aggregate/ Object domain | E4: Read Model | G4: Business Rule/Policy | I4: External System | J4: Domain Event | K4: Hotspot/questions/Risk
A5: Actor | B5: Acción | C5: Descripción | D5: Objeto de dominio | E5: Información externa | G5: Políticas | I5: Sistema Externo | J5: Evento | K5: Aspectos por solucionar
E6: Información | F6: Descripción | G6: Número | H6: Descripción
A7: Administrador / Vendedor | B7: Buscar país por filtro | C7: Permite buscar un país determinado por un criterio específico (nombre, id) | D7: =$B$2 -> Pais | E7: Filtros de paises | F7: Los parámetros de búsqueda ingresados por el usuario para filtrar el catálogo | G7: =HYPERLINK("#'P-Pais'!A5",'P-Pais'!A5) -> P-PAI-001 | H7: ='P-Pais'!B5 -> Asegurar que los datos requeridos sean válidos en tipo de dato, longitud, obligatoriedad y formato | J7: Paises encontrados

Sheet P-Pais
A1: <<<Ir al modelo de dominio | B1: <<<Ir a objeto de dominio | C1: <<<Ir a muestreo del objeto | D1: <<<Ir a caracterización | E1: <<<Ir al event storming
A2: Objeto de Dominio: | B2: ='Objetos de Dominio'!A3 -> Pais
A3: Descripción: | B3: ='Objetos de Dominio'!B3 -> Representa el país al que pertenecen las sedes.
A4: Número Política | B4: Descripción Política | C4: Objeto Responsable
A5: P-PAI-001 | B5: Asegurar que los datos requeridos sean válidos en tipo de dato, longitud, obligatoriedad y formato | C5: =$B$2 -> Pais

Sheet M-MetodoPago
A1: <<<Ir al modelo de dominio | B1: <<<Ir a objeto de dominio | C1: Ir a la caracterización>>> | D1: Ir al event storming>>> | E1: Ir a las políticas>>>
A2: Nombre: | B2: ='Objetos de Dominio'!A4 -> MetodoPago
A3: Descripción: | B3: ='Objetos de Dominio'!B4 -> Representa las formas en que un cliente puede cancelar una compra (efectivo, tarjeta, transferencia, Nequi, entre otras).
A4: Identificador único del método de pago | B4: Nombre del método de pago disponible en el negocio | C4: Indica si el método de pago está disponible para utilizarse | D4: Combinación única que indica que no puede existir más de un método de pago con el mismo nombre
A5: ID | B5: Nombre | C5: EsActivo | D5: MetodoUnico
A6: 1 | B6: Efectivo | C6: SI | D6: =B6 -> Efectivo
A7: 2 | B7: Tarjeta Débito | C7: SI | D7: =B7 -> Tarjeta Débito
A8: 3 | B8: Tarjeta Crédito | C8: SI | D8: =B8 -> Tarjeta Crédito
A9: 4 | B9: Nequi | C9: SI | D9: =B9 -> Nequi
A10: 5 | B10: Transferencia Bancaria | C10: SI | D10: =B10 -> Transferencia Bancaria
A11: 7 | B11: Wompi | C11: NO | D11: =B11 -> Wompi

Sheet C-MetodoPago
A1: <<<Ir al modelo de dominio | B1: <<<Ir a objeto de dominio | C1: <<<Ir a muestreo del objeto | D1: Ir al event storming>>> | E1: Ir a las políticas>>>
A2: Nombre | B2: ='Objetos de Dominio'!A4 -> MetodoPago
A3: Descripción | B3: ='Objetos de Dominio'!B4 -> Representa las formas en que un cliente puede cancelar una compra (efectivo, tarjeta, transferencia, Nequi, entre otras).
A4: Nombre atributo | B4: Descripción atributo | C4: Identificador del objeto de dominio | D4: Tipo de dato | E4: Obligatorio | F4: Longitud mínima (si aplica) | G4: Longitud máxima (si aplica) | H4: Precisión (si aplica) | I4: Redondeo (si aplica) | J4: Rango inicial (si aplica) | K4: Rango final (si aplica) | L4: Formato (si aplica) | M4: Reglas especiales (si aplica) | N4: Dato calculado | O4: Aplica ajuste del dato (si aplica) | P4: Carácter de ajuste (si aplica) | Q4: Quitar espacios en blanco al inicio (si aplica) | R4: Quitar espacios en blanco al fin (si aplica) | S4: Dato sensible (si aplica) | T4: Valor por defecto (si aplica) | U4: Auto generado | V4: =HYPERLINK("#'C-MetodoPago'!A17","registrarMetodoPago") -> registrarMetodoPago | W4: consultarMetodosPagoPorFiltro
A5: ID | B5: ='M-MetodoPago'!A4 -> Identificador único del método de pago | C5: Si | D5: Identificador único universal | E5: Si | F5: - | G5: - | H5: - | I5: - | J5: - | K5: - | L5: - | M5: Debe ser único y no debe repetirse en los distintos id's de los métodos de pago | N5: No | O5: No | P5: - | Q5: No | R5: No | S5: - | T5: - | U5: Si | V5: Requerido | W5: Filtro | X5: No Mostrar
A6: Nombre | B6: ='M-MetodoPago'!B4 -> Nombre del método de pago disponible en el negocio | C6: No | D6: Texto | E6: Si | F6: 2 | G6: 50 | H6: - | I6: - | J6: - | K6: - | L6: - | M6: Se debe asegurar una sanitización del dato, para garantizar que dentro de su contenido no tenga cualquier tipo de intento de ataque | N6: No | O6: No | P6: - | Q6: Si | R6: Si | S6: - | T6: - | U6: No | V6: Requerido | W6: Filtro | X6: Mostrar
A7: EsActivo | B7: ='M-MetodoPago'!C4 -> Indica si el método de pago está disponible para utilizarse | C7: No | D7: Lógico | E7: Si | F7: - | G7: - | H7: - | I7: - | J7: - | K7: - | L7: - | M7: Solo admite SI o NO y es ingresado por el administrador; al pasar a NO el registro se inhabilita pero se conserva su historial | N7: No | O7: No | P7: - | Q7: No | R7: No | S7: - | T7: - | U7: No | V7: Requerido | W7: Filtro | X7: Mostrar
A10: Nombre combinación única | B10: Descripción | C10: Atributos involucrados
A11: ='M-MetodoPago'!D5 -> MetodoUnico | B11: ='M-MetodoPago'!D4 -> Combinación única que indica que no puede existir más de un método de pago con el mismo nombre | C11: Nombre
A15: Responsabilidad | C15: Descripción | G15: Entradas | J15: Salida | O15: Políticas (Reglas de Negocio) | Q15: Excepción
G16: Parámetro | H16: Tipo de dato | I16: Descripción | J16: Tipo de Dato | K16: Descripción | O16: Política | P16: Descripción | Q16: Detalle | R16: ¿Qué hago?
A17: =HYPERLINK("#'C-MetodoPago'!V4","registrarMetodoPago") -> registrarMetodoPago | C17: Permite agregar una nueva opción al catálogo de métodos de pago del sistema | G17: datos | H17: MetodoPago | I17: Corresponde al nombre y estado del nuevo método de pago | J17: MetodoPago | K17: Objeto del método de pago registrado con su nombre y su estado correspondiente | O17: =HYPERLINK("#'P-MetodoPago'!A5",'P-MetodoPago'!A5) -> P-MDP-001 | P17: ='P-MetodoPago'!B5 -> Asegurar que el id del metodo de pago sea único e irrepetible | Q17: Generar un nuevo identificador hasta garantizar que no exista | R17: Continuar operación
O18: =HYPERLINK("#'P-MetodoPago'!A6",'P-MetodoPago'!A6) -> P-MDP-002 | P18: ='P-MetodoPago'!B6 -> Asegurar que el nombre del método sea único e irrepetible | Q18: Generar una excepción indicando que ya existe un metodo de pago registrado con ese nombre | R18: Detener operación
O19: =HYPERLINK("#'P-MetodoPago'!A7",'P-MetodoPago'!A7) -> P-MDP-003 | P19: ='P-MetodoPago'!B7 -> Asegurar que los datos requeridos sean válidos en tipo de dato, longitud, obligatoriedad y formato | Q19: Informar con un mensaje de error si los parámetros de consulta son inválidos | R19: Detener operación
A20: =HYPERLINK("#'C-MetodoPago'!X4","consultarMetodosPagoPorFiltro") -> consultarMetodosPagoPorFiltro | C20: Permite buscar por filtro y visualizar los métodos de pago habilitados para realizar transacciones | G20: filtro | H20: MetodoPago | I20: Los parámetros de búsqueda ingresados por el usuario para filtrar el catálogo | J20: Lista<MetodoPago> | K20: Contiene la lista de métodos de pago que cumplen con las condiciones del filtro enviado | O20: =HYPERLINK("#'P-MetodoPago'!A7",'P-MetodoPago'!A7) -> P-MDP-003 | P20: ='P-MetodoPago'!B7 -> Asegurar que los datos requeridos sean válidos en tipo de dato, longitud, obligatoriedad y formato | Q20: Informar con un mensaje de error si los parámetros de filtro de consulta son inválidos | R20: Detener operación

Sheet E-MetodoPago
A1: <<<Ir al modelo de dominio | B1: <<<Ir a objeto de dominio | C1: <<<Ir a muestreo del objeto | D1: <<<Ir a caracterización | E1: Ir a las políticas>>>
A2: Objeto de Dominio: | B2: ='Objetos de Dominio'!A4 -> MetodoPago
A3: Descripción: | B3: ='Objetos de Dominio'!B4 -> Representa las formas en que un cliente puede cancelar una compra (efectivo, tarjeta, transferencia, Nequi, entre otras).
A4: Actor | B4: Action/Command | D4: Entity/Aggregate/Object domain | E4: Read Model | G4: Business Rule/Policy | I4: External System | J4: Domain Event | K4: Hotspot/questions/Risk
A5: Actor | B5: Acción | C5: Descripción | D5: Objeto de dominio | E5: Información externa | G5: Políticas | I5: Sistema Externo | J5: Evento | K5: Aspectos por solucionar
E6: Información | F6: Descripción | G6: Número | H6: Descripción
A7: Administrador | B7: Registrar un nuevo método de pago | C7: Permite agregar una nueva opción al catálogo de métodos de pago del sistema | D7: MetodoPago | E7: Datos del método de pago | F7: Corresponde al nombre y estado del nuevo método de pago | G7: =HYPERLINK("#'P-MetodoPago'!A5",'P-MetodoPago'!A5) -> P-MDP-001 | H7: ='P-MetodoPago'!B5 -> Asegurar que el id del metodo de pago sea único e irrepetible | J7: Método de pago registrado
G8: =HYPERLINK("#'P-MetodoPago'!A6",'P-MetodoPago'!A6) -> P-MDP-002 | H8: ='P-MetodoPago'!B6 -> Asegurar que el nombre del método sea único e irrepetible
G9: =HYPERLINK("#'P-MetodoPago'!A7",'P-MetodoPago'!A7) -> P-MDP-003 | H9: ='P-MetodoPago'!B7 -> Asegurar que los datos requeridos sean válidos en tipo de dato, longitud, obligatoriedad y formato
A10: Administrador/Vendedor | B10: Buscar método por criterio | C10: Permite buscar por filtro y visualizar los métodos de pago habilitados para realizar transacciones | D10: MetodoPago | E10: Filtros de los metodos de pago | F10: Los parámetros de búsqueda ingresados por el usuario para filtrar el catálogo | G10: =HYPERLINK("#'P-MetodoPago'!A7",'P-MetodoPago'!A7) -> P-MDP-003 | H10: ='P-MetodoPago'!B7 -> Asegurar que los datos requeridos sean válidos en tipo de dato, longitud, obligatoriedad y formato | J10: Métodos de pago encontrados

Sheet P-MetodoPago
A1: <<<Ir al modelo de dominio | B1: <<<Ir a objeto de dominio | C1: <<<Ir a muestreo del objeto | D1: <<<Ir a caracterización | E1: <<<Ir al event storming
A2: Objeto de Dominio: | B2: ='Objetos de Dominio'!A4 -> MetodoPago
A3: Descripción: | B3: ='Objetos de Dominio'!B4 -> Representa las formas en que un cliente puede cancelar una compra (efectivo, tarjeta, transferencia, Nequi, entre otras).
A4: Número Política | B4: Descripción Política | C4: Objeto Responsable
A5: P-MDP-001 | B5: Asegurar que el id del metodo de pago sea único e irrepetible | C5: MetodoPago
A6: P-MDP-002 | B6: Asegurar que el nombre del método sea único e irrepetible | C6: MetodoPago
A7: P-MDP-003 | B7: Asegurar que los datos requeridos sean válidos en tipo de dato, longitud, obligatoriedad y formato | C7: MetodoPago

Sheet M-Cliente
A1: <<<Ir al modelo de dominio | B1: <<<Ir a objeto de dominio | C1: Ir a la caracterización>>> | D1: Ir al event storming>>> | E1: Ir a las políticas>>>
A2: Nombre: | B2: ='Objetos de Dominio'!A5 -> Cliente
A3: Descripción: | B3: ='Objetos de Dominio'!B5 -> Representa a la persona que adquiere productos en cualquiera de las sedes del negocio.
A4: Identificador único del cliente | B4: Indica si la compra debe asociarse al cliente no registrado cuando el comprador no se desea ser registrado en el sistema.
A5: ID | B5: ClientePorDefecto
A6: 1 | B6: SI
A7: 2 | B7: NO
A8: 3 | B8: NO
A9: 4 | B9: SI
A10: 5 | B10: NO
A11: 6 | B11: SI

Sheet C-Cliente
A1: <<<Ir al modelo de dominio | B1: <<<Ir a objeto de dominio | C1: <<<Ir a muestreo del objeto | D1: Ir al event storming>>> | E1: Ir a las políticas>>>
A2: Nombre | B2: ='Objetos de Dominio'!A5 -> Cliente
A3: Descripción | B3: ='Objetos de Dominio'!B5 -> Representa a la persona que adquiere productos en cualquiera de las sedes del negocio.
A4: Nombre atributo | B4: Descripción atributo | C4: Identificador del objeto de dominio | D4: Tipo de dato | E4: Obligatorio | F4: Longitud mínima (si aplica) | G4: Longitud máxima (si aplica) | H4: Precisión (si aplica) | I4: Redondeo (si aplica) | J4: Rango inicial (si aplica) | K4: Rango final (si aplica) | L4: Formato (si aplica) | M4: Reglas especiales (si aplica) | N4: Dato calculado | O4: Aplica ajuste del dato (si aplica) | P4: Carácter de ajuste (si aplica) | Q4: Quitar espacios en blanco al inicio (si aplica) | R4: Quitar espacios en blanco al fin (si aplica) | S4: Dato sensible (si aplica) | T4: Valor por defecto (si aplica) | U4: Auto generado | V4: =HYPERLINK("#'C-Cliente'!A11","registrarCliente") -> registrarCliente | W4: consultarClientesPorFiltro | Y4: =HYPERLINK("#'C-Cliente'!A14","eliminarCliente") -> eliminarCliente
A5: ID | B5: ='M-Cliente'!A4 -> Identificador único del cliente | C5: Si | D5: Identificador único universal | E5: Si | F5: - | G5: - | H5: - | I5: - | J5: - | K5: - | L5: - | M5: Debe ser único y no debe repetirse en los distintos id's de los clientes | N5: No | O5: No | P5: - | Q5: No | R5: No | S5: - | T5: - | U5: Si | V5: Requerido | W5: Filtro | X5: No mostrar | Y5: Requerido
A6: ClientePorDefecto | B6: ='M-Cliente'!B4 -> Indica si la compra debe asociarse al cliente no registrado cuando el comprador no se desea ser registrado en el sistema. | C6: Si | D6: Lógico | E6: Si | F6: - | G6: - | H6: - | I6: - | J6: - | K6: - | L6: - | M6: Solo admite SI o NO y es ingresado por el administrador; al pasar a NO el registro no se realiza pero se conserva su historial | N6: No | O6: No | P6: - | Q6: No | R6: No | S6: - | T6: - | U6: No | V6: Requerido | W6: Filtro | X6: Mostrar | Y6: No requerido
A9: Responsabilidades | C9: Descripción | G9: Entradas | J9: Salida | O9: Políticas (Reglas de Negocio) | Q9: Excepción
G10: Parámetro | H10: Tipo de dato | I10: Descripción | J10: Tipo de Dato | K10: Descripción | O10: Política | P10: Descripción | Q10: Detalle | R10: ¿Qué hago?
A11: =HYPERLINK("#'C-Cliente'!V4","registrarCliente") -> registrarCliente | C11: Crea el registro base del cliente asignando un ID universal y definiendo si es el cliente por defecto | G11: datos | H11: Cliente | I11: Contiene la información requerida para registrar el cliente | J11: Cliente | K11: Objeto del cliente registrado con su identificador ID asignado y estados por defecto | O11: =HYPERLINK("#'P-Cliente'!A5",'P-Cliente'!A5) -> P-CLI-001 | P11: ='P-Cliente'!B5 -> Asegurar que el id del cliente sea único e irrepetible | Q11: Generar un nuevo identificador hasta garantizar que no exista | R11: Continuar operación
O12: =HYPERLINK("#'P-Cliente'!A6",'P-Cliente'!A6) -> P-CLI-002 | P12: ='P-Cliente'!B6 -> Asegurar que los datos requeridos sean válidos en tipo de dato, longitud, obligatoriedad y formato | Q12: Generar una excepción indicando que los datos requeridos son inválidos o están incompletos | R12: Detener operación
A13: =HYPERLINK("#'C-Cliente'!X4","consultarClientesPorFiltro") -> consultarClientesPorFiltro | C13: Los parámetros de búsqueda ingresados por el usuario para filtrar la lista de clientes | G13: filtro | H13: Cliente | I13: Contiene los parámetros o criterios de consulta enviados para filtrar la búsqueda | J13: Lista<Cliente> | K13: Contiene la lista de clientes que cumplen con las condiciones del filtro enviado | O13: =HYPERLINK("#'P-Cliente'!A6",'P-Cliente'!A6) -> P-CLI-002 | P13: ='P-Cliente'!B6 -> Asegurar que los datos requeridos sean válidos en tipo de dato, longitud, obligatoriedad y formato | Q13: Generar una excepción indicando que los datos requeridos son inválidos o están incompletos | R13: Detener operación
A14: eliminarCliente | C14: Permite eliminar un cliente, borrando todo su historial de compras y de devoluciones, solo si el cliente registrado lo desea | G14: id | H14: UUID | I14: Contiene el identificador único del cliente que se desea eliminar | O14: =HYPERLINK("#'P-Cliente'!A7",'P-Cliente'!A7) -> P-CLI-003 | P14: ='P-Cliente'!B7 -> Asegurar que el cliente no esté siendo utilizado dentro de otro objeto de dominio | Q14: Generar una excepción indicando al usuario que el cliente está siendo usado por otros tipos de cliente (cliente registrado o no registrado) | R14: Detener operación

Sheet E-Cliente
A1: <<<Ir al modelo de dominio | B1: <<<Ir a objeto de dominio | C1: <<<Ir a muestreo del objeto | D1: <<<Ir a caracterización | E1: Ir a las políticas>>>
A2: Objeto de Dominio: | B2: ='Objetos de Dominio'!A5 -> Cliente
A3: Descripción: | B3: ='Objetos de Dominio'!B5 -> Representa a la persona que adquiere productos en cualquiera de las sedes del negocio.
A4: Actor | B4: Action/Command | D4: Entity/Aggregate/Object domain | E4: Read Model | G4: Business Rule/Policy | I4: External System | J4: Domain Event | K4: Hotspot/questions/Risk
A5: Actor | B5: Acción | C5: Descripción | D5: Objeto de dominio | E5: Información externa | G5: Políticas | I5: Sistema Externo | J5: Evento | K5: Aspectos por solucionar
E6: Información | F6: Descripción | G6: Número | H6: Descripción
A7: Administrador/Vendedor | B7: Registrar un nuevo cliente | C7: Crea el registro base del cliente asignando un ID universal y definiendo si es el cliente por defecto | D7: Cliente | E7: Datos del nuevo cliente | F7: Corresponde a la asignación interna del id del cliente y el registro de su tipo | G7: =HYPERLINK("#'P-Cliente'!A5",'P-Cliente'!A5) -> P-CLI-001 | H7: ='P-Cliente'!B5 -> Asegurar que el id del cliente sea único e irrepetible | J7: Cliente registrado
G8: =HYPERLINK("#'P-Cliente'!A6",'P-Cliente'!A6) -> P-CLI-002 | H8: ='P-Cliente'!B6 -> Asegurar que los datos requeridos sean válidos en tipo de dato, longitud, obligatoriedad y formato
A9: Administrador/Vendedor | B9: Buscar cliente por criterio | C9: Permite buscar por filtro y visualizar los clientes disponibles para realizar compras | D9: Cliente | E9: Filtros del id y estados de cliente | F9: Los parámetros de búsqueda ingresados por el usuario para filtrar el cliente | G9: =HYPERLINK("#'P-Cliente'!A6",'P-Cliente'!A6) -> P-CLI-002 | H9: ='P-Cliente'!B6 -> Asegurar que los datos requeridos sean válidos en tipo de dato, longitud, obligatoriedad y formato | J9: Clientes encontrados
A10: Administrador | B10: Eliminar cliente | C10: Permite eliminar el registro de un cliente del catálogo del sistema | D10: Cliente | E10: Datos cliente(id) | F10: Identificador único del cliente que se desea retirar o inactivar | G10: =HYPERLINK("#'P-Cliente'!A6",'P-Cliente'!A6) -> P-CLI-002 | H10: ='P-Cliente'!B6 -> Asegurar que los datos requeridos sean válidos en tipo de dato, longitud, obligatoriedad y formato | J10: Cliente eliminado
G11: =HYPERLINK("#'P-Cliente'!A7",'P-Cliente'!A7) -> P-CLI-003 | H11: ='P-Cliente'!B7 -> Asegurar que el cliente no esté siendo utilizado dentro de otro objeto de dominio

Sheet P-Cliente
A1: <<<Ir al modelo de dominio | B1: <<<Ir a objeto de dominio | C1: <<<Ir a muestreo del objeto | D1: <<<Ir a caracterización | E1: <<<Ir al event storming
A2: Objeto de Dominio: | B2: ='Objetos de Dominio'!A5 -> Cliente
A3: Descripción: | B3: ='Objetos de Dominio'!B5 -> Representa a la persona que adquiere productos en cualquiera de las sedes del negocio.
A4: Número Política | B4: Descripción Política | C4: Objeto Responsable
A5: P-CLI-001 | B5: Asegurar que el id del cliente sea único e irrepetible | C5: Cliente
A6: P-CLI-002 | B6: Asegurar que los datos requeridos sean válidos en tipo de dato, longitud, obligatoriedad y formato | C6: Cliente
A7: P-CLI-003 | B7: Asegurar que el cliente no esté siendo utilizado dentro de otro objeto de dominio | C7: Cliente

Sheet M-Marca
A1: <<<Ir al modelo de dominio | B1: <<<Ir a objeto de dominio | C1: Ir a la caracterización>>> | D1: Ir al event storming>>> | E1: Ir a las políticas>>>
A2: Nombre: | B2: ='Objetos de Dominio'!A6 -> Marca
A3: Descripción: | B3: ='Objetos de Dominio'!B6 -> Representa al fabricante de los accesorios y repuestos que comercializa el negocio.
A4: Identificador único de la marca | B4: Nombre del fabricante de los productos | C4: Variable booleana que define si una marca específica sigue siendo usada en la empresa | D4: Combinación única que indica que no puede existir más de una marca con el mismo nombre
A5: ID | B5: Nombre | C5: EsActivo | D5: MarcaUnica
A6: 1 | B6: Samsung | C6: SI | D6: =B6 -> Samsung
A7: 2 | B7: Apple | C7: SI | D7: =B7 -> Apple
A8: 3 | B8: Xiaomi | C8: SI | D8: =B8 -> Xiaomi
A9: 4 | B9: Saiya | C9: NO | D9: =B9 -> Saiya
A10: 5 | B10: Batri | C10: SI | D10: =B10 -> Batri
A11: 6 | B11: iGoma | C11: SI | D11: =B11 -> iGoma
A12: 7 | B12: SpaceX | C12: NO | D12: =B12 -> SpaceX

Sheet C-Marca
A1: <<<Ir al modelo de dominio | B1: <<<Ir a objeto de dominio | C1: <<<Ir a muestreo del objeto | D1: Ir al event storming>>> | E1: Ir a las políticas>>>
A2: Nombre | B2: ='Objetos de Dominio'!A6 -> Marca
A3: Descripción | B3: ='Objetos de Dominio'!B6 -> Representa al fabricante de los accesorios y repuestos que comercializa el negocio.
A4: Nombre atributo | B4: Descripción atributo | C4: Identificador del objeto de dominio | D4: Tipo de dato | E4: Obligatorio | F4: Longitud mínima (si aplica) | G4: Longitud máxima (si aplica) | H4: Precisión (si aplica) | I4: Redondeo (si aplica) | J4: Rango inicial (si aplica) | K4: Rango final (si aplica) | L4: Formato (si aplica) | M4: Reglas especiales (si aplica) | N4: Dato calculado | O4: Aplica ajuste del dato (si aplica) | P4: Carácter de ajuste (si aplica) | Q4: Quitar espacios en blanco al inicio (si aplica) | R4: Quitar espacios en blanco al fin (si aplica) | S4: Dato sensible (si aplica) | T4: Valor por defecto (si aplica) | U4: Auto generado | V4: registrarMarca | W4: =HYPERLINK("#'C-Marca'!A20","consultarMarcasPorFiltro") -> consultarMarcasPorFiltro
A5: ID | B5: ='M-Marca'!A4 -> Identificador único de la marca | C5: Si | D5: Identificador único universal | E5: Si | F5: - | G5: - | H5: - | I5: - | J5: - | K5: - | L5: - | M5: Debe ser único y no debe repetirse en los distintos id's de las marcas | N5: No | O5: No | P5: - | Q5: No | R5: No | S5: - | T5: - | U5: Si | V5: Requerido | W5: Filtro | X5: No mostrar
A6: Nombre | B6: ='M-Marca'!B4 -> Nombre del fabricante de los productos | C6: No | D6: Alfanumérico | E6: Si | F6: 2 | G6: 50 | H6: - | I6: - | J6: - | K6: - | L6: - | M6: Se debe asegurar una sanitización del dato, para garantizar que dentro de su contenido no tenga cualquier tipo de intento de ataque | N6: No | O6: No | P6: - | Q6: Si | R6: Si | S6: - | T6: - | U6: No | V6: Requerido | W6: Filtro | X6: Mostrar
A7: EsActivo | B7: ='M-Marca'!C4 -> Variable booleana que define si una marca específica sigue siendo usada en la empresa | C7: No | D7: Lógico | E7: Si | F7: - | G7: - | H7: - | I7: - | J7: - | K7: - | L7: - | M7: Solo admite SI o NO y es ingresado por el administrador; al pasar a NO la marca se inhabilita pero se conserva su historial | N7: No | O7: No | P7: - | Q7: No | R7: No | S7: - | T7: No | U7: No | V7: Requerido | W7: Filtro | X7: Mostrar
A10: Nombre combinación única | B10: Descripción | C10: Atributos involucrados
A11: ='M-Marca'!D5 -> MarcaUnica | B11: ='M-Marca'!D4 -> Combinación única que indica que no puede existir más de una marca con el mismo nombre | C11: Nombre
A15: Responsabilidad | C15: Descripción | G15: Entradas | J15: Salida | O15: Políticas (Reglas de Negocio) | Q15: Excepción
G16: Parámetro | H16: Tipo de dato | I16: Descripción | J16: Tipo de Dato | K16: Descripción | O16: Política | P16: Descripción | Q16: Detalle | R16: ¿Qué hago?
A17: =HYPERLINK("#'C-Marca'!V4","registrarMarca") -> registrarMarca | C17: Permite ingresar una nueva marca en el catálogo general del sistema | G17: datos | H17: Marca | I17: Contiene la información requerida para registrar la marca | J17: Marca | K17: Objeto de la marca registrada con su nombre y estado correspondiente | O17: =HYPERLINK("#'P-Marca'!A5",'P-Marca'!A5) -> P-MAR-001 | P17: ='P-Marca'!B5 -> Asegurar que el id de marca sea único e irrepetible | Q17: Generar un nuevo identificador hasta garantizar que no exista | R17: Continuar operación
O18: =HYPERLINK("#'P-Marca'!A6",'P-Marca'!A6) -> P-MAR-002 | P18: ='P-Marca'!B6 -> Asegurar que el nombre de la marca sea único e irrepetible | Q18: Generar una excepción indicando que ya existe una marca con ese nombre | R18: Detener operación
O19: =HYPERLINK("#'P-Marca'!A7",'P-Marca'!A7) -> P-MAR-003 | P19: ='P-Marca'!B7 -> Asegurar que los datos requeridos sean válidos en tipo de dato, longitud, obligatoriedad y formato | Q19: Generar una excepción indicando que los datos requeridos son inválidos o están incompletos | R19: Detener operación
A20: =HYPERLINK("#'C-Marca'!X4","consultarMarcasPorFiltro") -> consultarMarcasPorFiltro | C20: Permite buscar, listar y filtrar el catálogo de marcas por nombre, identificador ID o estado | G20: filtro | H20: Marca | I20: Contiene los parámetros o criterios de búsqueda enviados para filtrar la consulta | J20: Lista<Marca> | K20: Contiene la lista de marcas que cumplen con las condiciones del filtro enviado | O20: =HYPERLINK("#'P-Marca'!A7",'P-Marca'!A7) -> P-MAR-003 | P20: ='P-Marca'!B7 -> Asegurar que los datos requeridos sean válidos en tipo de dato, longitud, obligatoriedad y formato | Q20: Generar una excepción indicando que los datos requeridos son inválidos o están incompletos | R20: Detener operación

Sheet E-Marca
A1: <<<Ir al modelo de dominio | B1: <<<Ir a objeto de dominio | C1: <<<Ir a muestreo del objeto | D1: <<<Ir a caracterización | E1: Ir a las políticas>>>
A2: Objeto de Dominio: | B2: ='Objetos de Dominio'!A6 -> Marca
A3: Descripción: | B3: ='Objetos de Dominio'!B6 -> Representa al fabricante de los accesorios y repuestos que comercializa el negocio.
A4: Actor | B4: Action/Command | D4: Entity/Aggregate/Object domain | E4: Read Model | G4: Business Rule/Policy | I4: External System | J4: Domain Event | K4: Hotspot/questions/Risk
A5: Actor | B5: Acción | C5: Descripción | D5: Objeto de dominio | E5: Información externa | G5: Políticas | I5: Sistema Externo | J5: Evento | K5: Aspectos por solucionar
E6: Información | F6: Descripción | G6: Número | H6: Descripción
A7: Administrador | B7: Registrar una nueva marca | C7: Permite ingresar una nueva marca en el catálogo del sistema | D7: Marca | E7: Datos de la nueva marca | F7: Corresponde al nombre comercial y estado de actividad de la marca | G7: =HYPERLINK("#'P-Marca'!A5",'P-Marca'!A5) -> P-MAR-001 | H7: ='P-Marca'!B5 -> Asegurar que el id de marca sea único e irrepetible | J7: Marca registrada
G8: =HYPERLINK("#'P-Marca'!A6",'P-Marca'!A6) -> P-MAR-002 | H8: ='P-Marca'!B6 -> Asegurar que el nombre de la marca sea único e irrepetible
G9: =HYPERLINK("#'P-Marca'!A7",'P-Marca'!A7) -> P-MAR-003 | H9: ='P-Marca'!B7 -> Asegurar que los datos requeridos sean válidos en tipo de dato, longitud, obligatoriedad y formato
A10: Administrador/Vendedor | B10: Consultar marca por filtro | C10: Permite buscar una marca por un criterio específico | D10: Marca | E10: Datos de la marca(Id, Nombre y esActivo) | F10: Los parámetros de búsqueda ingresados por el usuario para filtrar la marca | G10: =HYPERLINK("#'P-Marca'!A7",'P-Marca'!A7) -> P-MAR-003 | H10: ='P-Marca'!B7 -> Asegurar que los datos requeridos sean válidos en tipo de dato, longitud, obligatoriedad y formato | J10: Marcas encontradas

Sheet P-Marca
A1: <<<Ir al modelo de dominio | B1: <<<Ir a objeto de dominio | C1: <<<Ir a muestreo del objeto | D1: <<<Ir a caracterización | E1: <<<Ir al event storming
A2: Objeto de Dominio: | B2: ='Objetos de Dominio'!A6 -> Marca
A3: Descripción: | B3: ='Objetos de Dominio'!B6 -> Representa al fabricante de los accesorios y repuestos que comercializa el negocio.
A4: Número Política | B4: Descripción Política | C4: Objeto Responsable
A5: P-MAR-001 | B5: Asegurar que el id de marca sea único e irrepetible | C5: Marca
A6: P-MAR-002 | B6: Asegurar que el nombre de la marca sea único e irrepetible | C6: Marca
A7: P-MAR-003 | B7: Asegurar que los datos requeridos sean válidos en tipo de dato, longitud, obligatoriedad y formato | C7: Marca

Sheet M-Motivo
A1: <<<Ir al modelo de dominio | B1: <<<Ir a objeto de dominio | C1: Ir a la caracterización>>> | D1: Ir al event storming>>> | E1: Ir a las políticas>>>
A2: Nombre: | B2: ='Objetos de Dominio'!A7 -> Motivo
A3: Descripción: | B3: ='Objetos de Dominio'!B7 -> Representa la razón por la que un cliente solicita devolver un producto.
A4: Identificador único del motivo | B4: Nombre que representa el motivo de devolución | C4: Combinación única que indica que no puede existir más de una motivo con el mismo nombre
A5: ID | B5: Nombre | C5: MotivoUnico
A6: 1 | B6: Garantía | C6: =B6 -> Garantía
A7: 2 | B7: Cambio de opinión | C7: =B7 -> Cambio de opinión
A8: 3 | B8: Producto incorrecto | C8: =B8 -> Producto incorrecto
A9: 4 | B9: Referencia incorrecta | C9: =B9 -> Referencia incorrecta
A10: 5 | B10: Otro | C10: =B10 -> Otro

Sheet C-Motivo
A1: <<<Ir al modelo de dominio | B1: <<<Ir a objeto de dominio | C1: <<<Ir a muestreo del objeto | D1: Ir al event storming>>> | E1: Ir a las políticas>>>
A2: Nombre | B2: ='Objetos de Dominio'!A7 -> Motivo
A3: Descripción | B3: ='Objetos de Dominio'!B7 -> Representa la razón por la que un cliente solicita devolver un producto.
A4: Nombre atributo | B4: Descripción atributo | C4: Identificador del objeto de dominio | D4: Tipo de dato | E4: Obligatorio | F4: Longitud mínima (si aplica) | G4: Longitud máxima (si aplica) | H4: Precisión (si aplica) | I4: Redondeo (si aplica) | J4: Rango inicial (si aplica) | K4: Rango final (si aplica) | L4: Formato (si aplica) | M4: Reglas especiales (si aplica) | N4: Dato calculado | O4: Aplica ajuste del dato (si aplica) | P4: Carácter de ajuste (si aplica) | Q4: Quitar espacios en blanco al inicio (si aplica) | R4: Quitar espacios en blanco al fin (si aplica) | S4: Dato sensible (si aplica) | T4: Valor por defecto (si aplica) | U4: Auto generado | V4: consultarPorFiltroMotivos
A5: ID | B5: ='M-Motivo'!A4 -> Identificador único del motivo | C5: Si | D5: Identificador único universal | E5: Si | F5: - | G5: - | H5: - | I5: - | J5: - | K5: - | L5: - | M5: Debe ser único y no repetirse en los distintos id's de los motivos | N5: No | O5: No | P5: - | Q5: No | R5: No | S5: - | T5: - | U5: Si | V5: Filtro | W5: No Mostrar
A6: Nombre | B6: ='M-Motivo'!B4 -> Nombre que representa el motivo de devolución | C6: No | D6: Texto | E6: Si | F6: 4 | G6: 40 | H6: - | I6: - | J6: - | K6: - | L6: - | M6: Se debe asegurar una sanitización del dato, para garantizar que dentro de su contenido no tenga cualquier tipo de intento de ataque | N6: No | O6: No | P6: - | Q6: Si | R6: Si | S6: - | T6: - | U6: No | V6: Filtro | W6: Mostrar
A9: Nombre combinación única | B9: Descripción | C9: Atributos involucrados
A10: ='M-Motivo'!C5 -> MotivoUnico | B10: ='M-Motivo'!C4 -> Combinación única que indica que no puede existir más de una motivo con el mismo nombre | C10: Nombre
A14: Responsabilidad | C14: Descripción | G14: Entradas | J14: Salida | O14: Políticas (Reglas de Negocio) | Q14: Excepción
G15: Parámetro | H15: Tipo de dato | I15: Descripción | J15: Tipo de Dato | K15: Descripción | O15: Política | P15: Descripción | Q15: Detalle | R15: ¿Qué hago?
A16: consultarPorFiltroMotivos | C16: Permite consultar la información por un filtro específico de los motivos registrados en el sistema | G16: filtro | H16: Motivo | I16: Contiene los parámetros o criterios de búsqueda enviados para filtrar la consulta | J16: Lista<Motivo> | K16: Contiene la lista de motivos registrados en el sistema que cumplen con las condicioens del filtro enviado | O16: =HYPERLINK("#'P-Motivo'!A7",'P-Motivo'!A5) -> P-MOT-001 | P16: ='P-Motivo'!B5 -> Asegurar que los datos requeridos sean válidos en tipo de dato, longitud, obligatoriedad y formato | Q16: Informar con un mensaje de error si ocurre un fallo al recuperar la información | R16: Detener operación

Sheet E-Motivo
A1: <<<Ir al modelo de dominio | B1: <<<Ir a objeto de dominio | C1: <<<Ir a muestreo del objeto | D1: <<<Ir a caracterización | E1: Ir a las políticas>>>
A2: Objeto de Dominio: | B2: ='Objetos de Dominio'!A7 -> Motivo
A3: Descripción: | B3: ='Objetos de Dominio'!B7 -> Representa la razón por la que un cliente solicita devolver un producto.
A4: Actor | B4: Action/Command | D4: Entity/Aggregate/Object domain | E4: Read Model | G4: Business Rule/Policy | I4: External System | J4: Domain Event | K4: Hotspot/questions/Risk
A5: Actor | B5: Acción | C5: Descripción | D5: Objeto de dominio | E5: Información externa | G5: Políticas | I5: Sistema Externo | J5: Evento | K5: Aspectos por solucionar
E6: Información | F6: Descripción | G6: Número | H6: Descripción
A7: Administrador/Vendedor | B7: Consultar los motivos por filtro | C7: Permite consultar la información los motivos registrados en el sistema mediante un filtro específico | D7: Motivo | E7: Filtros de los motivos | F7: Contiene la lista de motivos registrados en el sistema | G7: =HYPERLINK("#'P-Motivo'!A5",'P-Motivo'!A5) -> P-MOT-001 | H7: ='P-Motivo'!B5 -> Asegurar que los datos requeridos sean válidos en tipo de dato, longitud, obligatoriedad y formato | J7: Motivos encontrados

Sheet P-Motivo
A1: <<<Ir al modelo de dominio | B1: <<<Ir a objeto de dominio | C1: <<<Ir a muestreo del objeto | D1: <<<Ir a caracterización | E1: <<<Ir al event storming
A2: Objeto de Dominio: | B2: ='Objetos de Dominio'!A7 -> Motivo
A3: Descripción: | B3: ='Objetos de Dominio'!B7 -> Representa la razón por la que un cliente solicita devolver un producto.
A4: Número Política | B4: Descripción Política | C4: Objeto Responsable
A5: P-MOT-001 | B5: Asegurar que los datos requeridos sean válidos en tipo de dato, longitud, obligatoriedad y formato | C5: Motivo

Sheet M-TipoDocumento
A1: <<<Ir al modelo de dominio | B1: <<<Ir a objeto de dominio | C1: Ir a la caracterización>>> | D1: Ir al event storming>>> | E1: Ir a las políticas>>>
A2: Nombre: | B2: ='Objetos de Dominio'!A8 -> TipoDocumento
A3: Descripción: | B3: ='Objetos de Dominio'!B8 -> Representa el tipo de documento de identidad de una persona
A4: Identificador único del documento | B4: Representa el nombre del tipo de documento de identidad de una persona | C4: Combinación única que representa que no puede existir un documento con un mismo nombre
A5: ID | B5: Tipo | C5: DocumentoUnico
A6: 1 | B6: Cédula de ciudadanía | C6: =_xlfn.CONCAT(B6) -> Cédula de ciudadanía
A7: 2 | B7: Cédula de extranjería | C7: =_xlfn.CONCAT(B7) -> Cédula de extranjería
A8: 3 | B8: Tarjeta de identidad | C8: =_xlfn.CONCAT(B8) -> Tarjeta de identidad
A9: 4 | B9: Pasaporte | C9: =_xlfn.CONCAT(B9) -> Pasaporte

Sheet C-TipoDocumento
A1: <<<Ir al modelo de dominio | B1: <<<Ir a objeto de dominio | C1: <<<Ir a muestreo del objeto | D1: Ir al event storming>>> | E1: Ir a las políticas>>>
A2: Nombre | B2: ='Objetos de Dominio'!A8 -> TipoDocumento
A3: Descripción | B3: ='Objetos de Dominio'!B8 -> Representa el tipo de documento de identidad de una persona
A4: Nombre atributo | B4: Descripción atributo | C4: Identificador del objeto de dominio | D4: Tipo de dato | E4: Obligatorio | F4: Longitud mínima (si aplica) | G4: Longitud máxima (si aplica) | H4: Precisión (si aplica) | I4: Redondeo (si aplica) | J4: Rango inicial (si aplica) | K4: Rango final (si aplica) | L4: Formato (si aplica) | M4: Reglas especiales (si aplica) | N4: Dato calculado | O4: Aplica ajuste del dato (si aplica) | P4: Carácter de ajuste (si aplica) | Q4: Quitar espacios en blanco al inicio (si aplica) | R4: Quitar espacios en blanco al fin (si aplica) | S4: Dato sensible (si aplica) | T4: Valor por defecto (si aplica) | U4: Auto generado | V4: =HYPERLINK("#'C-TipoDocumento'!a16","consultarDocumentosPorFiltro") -> consultarDocumentosPorFiltro
A5: ID | B5: ='M-TipoDocumento'!A4 -> Identificador único del documento | C5: Si | D5: Identificador único universal | E5: Si | F5: - | G5: - | H5: - | I5: - | J5: - | K5: - | L5: - | M5: Debe ser único y no repetirse en los distintos id's de documentos | N5: No | O5: No | P5: - | Q5: No | R5: No | S5: - | T5: - | U5: Si | V5: Filtro | W5: No mostrar
A6: Tipo | B6: ='M-TipoDocumento'!B4 -> Representa el nombre del tipo de documento de identidad de una persona | C6: No | D6: Alfanumerico | E6: Si | F6: 9 | G6: 50 | H6: - | I6: - | J6: - | K6: - | L6: - | M6: Se debe asegurar una sanitización del dato, para garantizar que dentro de su contenido no tenga cualquier tipo de intento de ataque | N6: No | O6: No | P6: - | Q6: Si | R6: Si | S6: - | T6: - | U6: No | V6: Filtro | W6: Mostrar
A9: Nombre combinación única | B9: Descripción | C9: Atributos involucrados
A10: ='M-TipoDocumento'!C5 -> DocumentoUnico | B10: ='M-TipoDocumento'!C4 -> Combinación única que representa que no puede existir un documento con un mismo nombre | C10: Tipo
A14: Responsabilidad | C14: Descripción | G14: Entradas | J14: Salida | O14: Políticas (Reglas de Negocio) | Q14: Excepción
G15: Parámetro | H15: Tipo de dato | I15: Descripción | J15: Tipo de Dato | K15: Descripción | O15: Política | P15: Descripción | Q15: Detalle | R15: ¿Qué hago?
A16: =HYPERLINK("#'C-TipoDocumento'!v4","consultarDocumentosPorFiltro") -> consultarDocumentosPorFiltro | C16: Permite consultar los clientes que cumplen con los criterios de búsqueda enviados | G16: filtro | H16: Cliente | I16: Contiene los parámetros o criterios de consulta enviados para filtrar la búsqueda | J16: Lista<TipoDocumento> | K16: Contiene la lista de clientes que cumplen con las condiciones del filtro enviado | O16: ='P-TipoDocumento'!A5 -> P-DOC-001 | P16: ='P-TipoDocumento'!B5 -> Asegurar que los datos requeridos sean válidos en tipo de dato, longitud, obligatoriedad y formato | Q16: Generar una excepción indicando que los datos requeridos son inválidos o están incompletos | R16: Detener operación

Sheet E-TipoDocumento
A1: <<<Ir al modelo de dominio | B1: <<<Ir a objeto de dominio | C1: <<<Ir a muestreo del objeto | D1: <<<Ir a caracterización | E1: Ir a las políticas>>>
A2: Objeto de Dominio: | B2: ='Objetos de Dominio'!A8 -> TipoDocumento
A3: Descripción: | B3: ='Objetos de Dominio'!B8 -> Representa el tipo de documento de identidad de una persona
A4: Actor | B4: Action/Command | D4: Entity/Aggregate/Object domain | E4: Read Model | G4: Business Rule/Policy | I4: External System | J4: Domain Event | K4: Hotspot/questions/Risk
A5: Actor | B5: Acción | C5: Descripción | D5: Objeto de dominio | E5: Información externa | G5: Políticas | I5: Sistema Externo | J5: Evento | K5: Aspectos por solucionar
E6: Información | F6: Descripción | G6: Número | H6: Descripción
A7: Administrador/Vendedor | B7: Consultar documentos por filtro | C7: Permite buscar, listar y filtrar los tipos documentos según los criterios de búsqueda enviados | D7: Documento | E7: Filtros de los tipos de documentos | F7: Contiene los parámetros o criterios de búsqueda enviados para filtrar la consulta | G7: =HYPERLINK("#'P-TipoDocumento'!A5",'P-TipoDocumento'!A5) -> P-DOC-001 | H7: ='P-TipoDocumento'!B5 -> Asegurar que los datos requeridos sean válidos en tipo de dato, longitud, obligatoriedad y formato | J7: Documentos encontrados

Sheet P-TipoDocumento
A1: <<<Ir al modelo de dominio | B1: <<<Ir a objeto de dominio | C1: <<<Ir a muestreo del objeto | D1: <<<Ir a caracterización | E1: <<<Ir al event storming
A2: Objeto de Dominio: | B2: ='Objetos de Dominio'!A8 -> TipoDocumento
A3: Descripción: | B3: ='Objetos de Dominio'!B8 -> Representa el tipo de documento de identidad de una persona
A4: Número Política | B4: Descripción Política | C4: Objeto Responsable
A5: P-DOC-001 | B5: Asegurar que los datos requeridos sean válidos en tipo de dato, longitud, obligatoriedad y formato | C5: TipoDocumento

Sheet M-Categoria
A1: <<<Ir al modelo de dominio | B1: <<<Ir a objeto de dominio | C1: Ir a la caracterización>>> | D1: Ir al event storming>>> | E1: Ir a las políticas>>>
A2: Nombre: | B2: ='Objetos de Dominio'!A9 -> Categoria
A3: Descripción: | B3: ='Objetos de Dominio'!B9 -> Representa la clasificación a la que pertenece un producto dentro del catálogo.
A4: Identificador único de la categoría | B4: Nombre de la clasificación de productos | C4: Identifica la categoría principal o superior a la que pertenece la clasificación correspondiente | D4: Indica el nivel de profundidad jerárquica de la categoría dentro de la estructura del catálogo | E4: Combinación única que indica que no puede existir más de una categoría con el mismo nombre y perteneciendo a la misma categoríaPadre
A5: ID | B5: Nombre | C5: CategoriaPadre | D5: Nivel | E5: CategoriaUnica
A6: 1 | B6: Accesorios | D6: 1 | E6: =_xlfn.CONCAT(B6," || ",C6) -> Accesorios ||
A7: 2 | B7: Estuches/Fundas | C7: =B6 -> Accesorios | D7: 2 | E7: =_xlfn.CONCAT(B7," || ",C7) -> Estuches/Fundas || Accesorios
A8: 3 | B8: Estuches Tablets | C8: =B7 -> Estuches/Fundas | D8: 3 | E8: =_xlfn.CONCAT(B8," || ",C8) -> Estuches Tablets || Estuches/Fundas
A9: 4 | B9: Estuches iPad | C9: =B8 -> Estuches Tablets | D9: 4 | E9: =_xlfn.CONCAT(B9," || ",C9) -> Estuches iPad || Estuches Tablets
A10: 5 | B10: Estuches Lenovo | C10: =B8 -> Estuches Tablets | D10: 4 | E10: =_xlfn.CONCAT(B10," || ",C10) -> Estuches Lenovo || Estuches Tablets
A11: 6 | B11: Estuches Samsung | C11: =B8 -> Estuches Tablets | D11: 4 | E11: =_xlfn.CONCAT(B11," || ",C11) -> Estuches Samsung || Estuches Tablets
A12: 7 | B12: Estuches Huawei | C12: =B8 -> Estuches Tablets | D12: 4 | E12: =_xlfn.CONCAT(B12," || ",C12) -> Estuches Huawei || Estuches Tablets
A13: 8 | B13: Estuches Xiaomi | C13: =B8 -> Estuches Tablets | D13: 4 | E13: =_xlfn.CONCAT(B13," || ",C13) -> Estuches Xiaomi || Estuches Tablets
A14: 9 | B14: Estuches Celulares | C14: =B7 -> Estuches/Fundas | D14: 3 | E14: =_xlfn.CONCAT(B14," || ",C14) -> Estuches Celulares || Estuches/Fundas
A15: 10 | B15: Estuches iPhone | C15: =B14 -> Estuches Celulares | D15: 4 | E15: =_xlfn.CONCAT(B15," || ",C15) -> Estuches iPhone || Estuches Celulares
A16: 11 | B16: Estuches Samsung | C16: =B14 -> Estuches Celulares | D16: 4 | E16: =_xlfn.CONCAT(B16," || ",C16) -> Estuches Samsung || Estuches Celulares
A17: 12 | B17: Estuches Xiaomi | C17: =B14 -> Estuches Celulares | D17: 4 | E17: =_xlfn.CONCAT(B17," || ",C17) -> Estuches Xiaomi || Estuches Celulares
A18: 13 | B18: Estuches Huawei | C18: =B14 -> Estuches Celulares | D18: 4 | E18: =_xlfn.CONCAT(B18," || ",C18) -> Estuches Huawei || Estuches Celulares
A19: 14 | B19: Estuches Motorola | C19: =B14 -> Estuches Celulares | D19: 4 | E19: =_xlfn.CONCAT(B19," || ",C19) -> Estuches Motorola || Estuches Celulares
A20: 15 | B20: Estuches Oppo | C20: =B14 -> Estuches Celulares | D20: 4 | E20: =_xlfn.CONCAT(B20," || ",C20) -> Estuches Oppo || Estuches Celulares
A21: 16 | B21: Estuches Tecno | C21: =B14 -> Estuches Celulares | D21: 4 | E21: =_xlfn.CONCAT(B21," || ",C21) -> Estuches Tecno || Estuches Celulares
A22: 17 | B22: Fundas Portatiles | C22: =B7 -> Estuches/Fundas | D22: 3 | E22: =_xlfn.CONCAT(B22," || ",C22) -> Fundas Portatiles || Estuches/Fundas
A23: 18 | B23: Fundas Apple | C23: =B22 -> Fundas Portatiles | D23: 4 | E23: =_xlfn.CONCAT(B23," || ",C23) -> Fundas Apple || Fundas Portatiles
A24: 19 | B24: Fundas Lenovo | C24: =B22 -> Fundas Portatiles | D24: 4 | E24: =_xlfn.CONCAT(B24," || ",C24) -> Fundas Lenovo || Fundas Portatiles
A25: 20 | B25: Fundas HP | C25: =B22 -> Fundas Portatiles | D25: 4 | E25: =_xlfn.CONCAT(B25," || ",C25) -> Fundas HP || Fundas Portatiles
A26: 21 | B26: Fundas Asus | C26: =B22 -> Fundas Portatiles | D26: 4 | E26: =_xlfn.CONCAT(B26," || ",C26) -> Fundas Asus || Fundas Portatiles
A27: 22 | B27: Fundas Dell | C27: =B22 -> Fundas Portatiles | D27: 4 | E27: =_xlfn.CONCAT(B27," || ",C27) -> Fundas Dell || Fundas Portatiles
A28: 23 | B28: Fundas Samsung | C28: =B22 -> Fundas Portatiles | D28: 4 | E28: =_xlfn.CONCAT(B28," || ",C28) -> Fundas Samsung || Fundas Portatiles
A29: 24 | B29: Vidrios Templados | C29: =B6 -> Accesorios | D29: 2 | E29: =_xlfn.CONCAT(B29," || ",C29) -> Vidrios Templados || Accesorios
A30: 25 | B30: Vidrios Tablets | C30: =B29 -> Vidrios Templados | D30: 3 | E30: =_xlfn.CONCAT(B30," || ",C30) -> Vidrios Tablets || Vidrios Templados
A31: 26 | B31: Vidrios iPad | C31: =B30 -> Vidrios Tablets | D31: 4 | E31: =_xlfn.CONCAT(B31," || ",C31) -> Vidrios iPad || Vidrios Tablets
A32: 27 | B32: Vidrios Lenovo | C32: =B30 -> Vidrios Tablets | D32: 4 | E32: =_xlfn.CONCAT(B32," || ",C32) -> Vidrios Lenovo || Vidrios Tablets
A33: 28 | B33: Vidrios Samsung | C33: =B30 -> Vidrios Tablets | D33: 4 | E33: =_xlfn.CONCAT(B33," || ",C33) -> Vidrios Samsung || Vidrios Tablets
A34: 29 | B34: Vidrios Huawei | C34: =B30 -> Vidrios Tablets | D34: 4 | E34: =_xlfn.CONCAT(B34," || ",C34) -> Vidrios Huawei || Vidrios Tablets
A35: 30 | B35: Vidrios Xiaomi | C35: =B30 -> Vidrios Tablets | D35: 4 | E35: =_xlfn.CONCAT(B35," || ",C35) -> Vidrios Xiaomi || Vidrios Tablets
A36: 31 | B36: Vidrios Celulares | C36: =B29 -> Vidrios Templados | D36: 3 | E36: =_xlfn.CONCAT(B36," || ",C36) -> Vidrios Celulares || Vidrios Templados
A37: 32 | B37: Vidrios iPhone | C37: =B36 -> Vidrios Celulares | D37: 4 | E37: =_xlfn.CONCAT(B37," || ",C37) -> Vidrios iPhone || Vidrios Celulares
A38: 33 | B38: Vidrios Samsung | C38: =B36 -> Vidrios Celulares | D38: 4 | E38: =_xlfn.CONCAT(B38," || ",C38) -> Vidrios Samsung || Vidrios Celulares
A39: 34 | B39: Vidrios Xiaomi | C39: =B36 -> Vidrios Celulares | D39: 4 | E39: =_xlfn.CONCAT(B39," || ",C39) -> Vidrios Xiaomi || Vidrios Celulares
A40: 35 | B40: Vidrios Huawei | C40: =B36 -> Vidrios Celulares | D40: 4 | E40: =_xlfn.CONCAT(B40," || ",C40) -> Vidrios Huawei || Vidrios Celulares
A41: 36 | B41: Vidrios Motorola | C41: =B36 -> Vidrios Celulares | D41: 4 | E41: =_xlfn.CONCAT(B41," || ",C41) -> Vidrios Motorola || Vidrios Celulares
A42: 37 | B42: Vidrios Oppo | C42: =B36 -> Vidrios Celulares | D42: 4 | E42: =_xlfn.CONCAT(B42," || ",C42) -> Vidrios Oppo || Vidrios Celulares
A43: 38 | B43: Vidrios Tecno | C43: =B36 -> Vidrios Celulares | D43: 4 | E43: =_xlfn.CONCAT(B43," || ",C43) -> Vidrios Tecno || Vidrios Celulares
A44: 39 | B44: Cables | D44: 1 | E44: =_xlfn.CONCAT(B44," || ",C44) -> Cables ||
A45: 40 | B45: Cables Tipo C-Tipo C | C45: =B44 -> Cables | D45: 2 | E45: =_xlfn.CONCAT(B45," || ",C45) -> Cables Tipo C-Tipo C || Cables
A46: 41 | B46: Cables Tipo C-iPhone | C46: =B44 -> Cables | D46: 2 | E46: =_xlfn.CONCAT(B46," || ",C46) -> Cables Tipo C-iPhone || Cables
A47: 42 | B47: Cables USB- Tipo C | C47: =B44 -> Cables | D47: 2 | E47: =_xlfn.CONCAT(B47," || ",C47) -> Cables USB- Tipo C || Cables
A48: 43 | B48: Cables USB - iPhone | C48: =B44 -> Cables | D48: 2 | E48: =_xlfn.CONCAT(B48," || ",C48) -> Cables USB - iPhone || Cables
A49: 44 | B49: Cargadores | D49: 1 | E49: =_xlfn.CONCAT(B49," || ",C49) -> Cargadores ||
A50: 45 | B50: Cargadores Apple | C50: =B49 -> Cargadores | D50: 2 | E50: =_xlfn.CONCAT(B50," || ",C50) -> Cargadores Apple || Cargadores
A51: 46 | B51: Cargadores Samsung | C51: =B49 -> Cargadores | D51: 2 | E51: =_xlfn.CONCAT(B51," || ",C51) -> Cargadores Samsung || Cargadores
A52: 47 | B52: Cargadores Xiaomi | C52: =B49 -> Cargadores | D52: 2 | E52: =_xlfn.CONCAT(B52," || ",C52) -> Cargadores Xiaomi || Cargadores
A53: 48 | B53: Cargadores Genéricos | C53: =B49 -> Cargadores | D53: 2 | E53: =_xlfn.CONCAT(B53," || ",C53) -> Cargadores Genéricos || Cargadores
A54: 49 | B54: Audífonos | D54: 1 | E54: =_xlfn.CONCAT(B54," || ",C54) -> Audífonos ||
A55: 50 | B55: Audífonos Inalámbricos | C55: =B54 -> Audífonos | D55: 2 | E55: =_xlfn.CONCAT(B55," || ",C55) -> Audífonos Inalámbricos || Audífonos
A56: 51 | B56: Diademas | C56: =B54 -> Audífonos | D56: 2 | E56: =_xlfn.CONCAT(B56," || ",C56) -> Diademas || Audífonos
A57: 52 | B57: Audifonos Cable | C57: =B54 -> Audífonos | D57: 2 | E57: =_xlfn.CONCAT(B57," || ",C57) -> Audifonos Cable || Audífonos
A58: 53 | B58: Audifonos Aux | C58: =B54 -> Audífonos | D58: 2 | E58: =_xlfn.CONCAT(B58," || ",C58) -> Audifonos Aux || Audífonos
A59: 54 | B59: Audifonos Tipo C | C59: =B54 -> Audífonos | D59: 2 | E59: =_xlfn.CONCAT(B59," || ",C59) -> Audifonos Tipo C || Audífonos
A60: 55 | B60: Audifonos iPhone | C60: =B54 -> Audífonos | D60: 2 | E60: =_xlfn.CONCAT(B60," || ",C60) -> Audifonos iPhone || Audífonos
A61: 56 | B61: Power Banks | D61: 1 | E61: =_xlfn.CONCAT(B61," || ",C61) -> Power Banks ||
A62: 57 | B62: Power Banks 5.000 mAh | C62: =B61 -> Power Banks | D62: 2 | E62: =_xlfn.CONCAT(B62," || ",C62) -> Power Banks 5.000 mAh || Power Banks
A63: 58 | B63: Power Banks 10.000 mAh | C63: =B61 -> Power Banks | D63: 2 | E63: =_xlfn.CONCAT(B63," || ",C63) -> Power Banks 10.000 mAh || Power Banks
A64: 59 | B64: Power Banks 20.000 mAh | C64: =B61 -> Power Banks | D64: 2 | E64: =_xlfn.CONCAT(B64," || ",C64) -> Power Banks 20.000 mAh || Power Banks
A65: 60 | B65: Power Banks 30.000 mAh | C65: =B61 -> Power Banks | D65: 2 | E65: =_xlfn.CONCAT(B65," || ",C65) -> Power Banks 30.000 mAh || Power Banks

Sheet C-Categoria
A1: <<<Ir al modelo de dominio | B1: <<<Ir a objeto de dominio | C1: <<<Ir a muestreo del objeto | D1: Ir al event storming>>> | E1: Ir a las políticas>>>
A2: Nombre | B2: ='Objetos de Dominio'!A9 -> Categoria
A3: Descripción | B3: ='Objetos de Dominio'!B9 -> Representa la clasificación a la que pertenece un producto dentro del catálogo.
A4: Nombre atributo | B4: Descripción atributo | C4: Identificador del objeto de dominio | D4: Tipo de dato | E4: Obligatorio | F4: Longitud mínima (si aplica) | G4: Longitud máxima (si aplica) | H4: Precisión (si aplica) | I4: Redondeo (si aplica) | J4: Rango inicial (si aplica) | K4: Rango final (si aplica) | L4: Formato (si aplica) | M4: Reglas especiales (si aplica) | N4: Dato calculado | O4: Aplica ajuste del dato (si aplica) | P4: Carácter de ajuste (si aplica) | Q4: Quitar espacios en blanco al inicio (si aplica) | R4: Quitar espacios en blanco al fin (si aplica) | S4: Dato sensible (si aplica) | T4: Valor por defecto (si aplica) | U4: Auto generado | V4: registrarCategoria | W4: consultarCategoriasPorFiltro | Y4: modificarCategoria | AA4: eliminarCategoria
A5: ID | B5: ='M-Categoria'!A4 -> Identificador único de la categoría | C5: Si | D5: Identificador único universal | E5: Si | F5: - | G5: - | H5: - | I5: - | J5: - | K5: - | L5: - | M5: Debe ser único y no debe repetirse en los distintos id's de las categorías | N5: No | O5: No | P5: - | Q5: No | R5: No | S5: - | T5: - | U5: Si | V5: Requerido | W5: Filtro | X5: No Mostrar | Y5: Requerido | Z5: No modificable | AA5: Requerido
A6: Nombre | B6: ='M-Categoria'!B4 -> Nombre de la clasificación de productos | C6: No | D6: Alfanumérico | E6: Si | F6: 2 | G6: 50 | H6: - | I6: - | J6: - | K6: - | L6: - | M6: Se debe asegurar una sanitización del dato, para garantizar que dentro de su contenido no tenga cualquier tipo de intento de ataque | N6: No | O6: No | P6: - | Q6: Si | R6: Si | S6: - | T6: - | U6: No | V6: Requerido | W6: Filtro | X6: Mostrar | Y6: Requerido | Z6: Modificable | AA6: No Requerido
A7: CategoriaPadre | B7: ='M-Categoria'!C4 -> Identifica la categoría principal o superior a la que pertenece la clasificación correspondiente | C7: No | D7: Alfanumérico | E7: No | F7: 2 | G7: 50 | H7: - | I7: - | J7: - | K7: - | L7: - | M7: Se debe asegurar una sanitización del dato, para garantizar que dentro de su contenido no tenga cualquier tipo de intento de ataque | N7: No | O7: No | P7: - | Q7: Si | R7: Si | S7: - | T7: Vacio | U7: No | V7: No requerido | W7: Filtro | X7: Mostrar | Y7: No requerido | Z7: Modificable | AA7: No Requerido
A8: Nivel | B8: ='M-Categoria'!D4 -> Indica el nivel de profundidad jerárquica de la categoría dentro de la estructura del catálogo | C8: No | D8: Numérico Entero | E8: Si | F8: - | G8: - | H8: - | I8: - | J8: 1 | K8: - | L8: - | M8: Se calcula a partir de la profundidad de CategoriaPadre + 1; el primer nivel es 1 | N8: Si | O8: No | P8: - | Q8: No | R8: No | S8: - | T8: - | U8: No | V8: No requerido | W8: Filtro | X8: No Mostrar | Y8: No Requerido | Z8: No modificable | AA8: No Requerido
A11: Nombre combinación única | B11: Descripción | C11: Atributos involucrados
A12: ='M-Categoria'!E5 -> CategoriaUnica | B12: ='M-Categoria'!E4 -> Combinación única que indica que no puede existir más de una categoría con el mismo nombre y perteneciendo a la misma categoríaPadre | C12: Nombre
C13: CategoriaPadre
A17: Responsabilidad | C17: Descripción | G17: Entradas | J17: Salida | O17: Políticas (Reglas de Negocio) | Q17: Excepción
G18: Parámetro | H18: Tipo de dato | I18: Descripción | J18: Tipo de Dato | K18: Descripción | O18: Política | P18: Descripción | Q18: Detalle | R18: ¿Qué hago?
A19: registrarCategoria | C19: Permite registrar una nueva categoría en el sistema | G19: datos | H19: Categoria | I19: Contiene la información requerida para registrar la categoría | J19: Categoria | K19: Objeto de la categoría registrada con su identificador ID asignado, nombre, su categoría padre y nivel correspondientes | O19: =HYPERLINK("#'P-Categoria'!A5",'P-Categoria'!A5) -> P-CAT-001 | P19: ='P-Categoria'!B5 -> Asegurar que el id de categoría debe ser único e irrepetible | Q19: Generar un nuevo identificador hasta garantizar que no exista | R19: Continuar operación
O20: =HYPERLINK("#'P-Categoria'!A6",'P-Categoria'!A6) -> P-CAT-002 | P20: ='P-Categoria'!B6 -> Asegurar que el campo nombre de categoría debe ser único e irrepetible en su respectivo nivel de categoría padre | Q20: Generar una excepción indicando que ya existe una categoría con ese mismo nombre en ese mismo nivel | R20: Detener operación
O21: =HYPERLINK("#'P-Categoria'!A7",'P-Categoria'!A7) -> P-CAT-003 | P21: ='P-Categoria'!B7 -> Asegurar que los datos requeridos sean válidos en tipo de dato, longitud, obligatoriedad y formato | Q21: Generar una excepción indicando que los datos requeridos son inválidos o están incompletos | R21: Detener operación
A22: consultarCategoriasPorFiltro | C22: Permite buscar, listar y filtrar las categorías según los criterios de búsqueda enviados, ya sea id, nombre, categoriapadre o nivel | G22: filtro | H22: Categoria | I22: Contiene los parámetros o criterios de búsqueda enviados para filtrar la consulta | J22: Lista<Categoria> | K22: Contiene la lista de categorías que cumplen con las condiciones del filtro enviado | O22: =HYPERLINK("#'P-Categoria'!A7",'P-Categoria'!A7) -> P-CAT-003 | P22: ='P-Categoria'!B7 -> Asegurar que los datos requeridos sean válidos en tipo de dato, longitud, obligatoriedad y formato | Q22: Generar una excepción indicando que los datos requeridos son inválidos o están incompletos | R22: Detener operación
A23: modificarCategoria | C23: Permite actualizar la información de una categoría existente | G23: id | H23: UUID | I23: Tiene el identificador único de la categoría a modificar y la nueva información requerida para modificar la categoría existente | J23: Categoria | K23: Objeto de la categoría con su información actualizada | O23: =HYPERLINK("#'P-Categoria'!A6",'P-Categoria'!A6) -> P-CAT-002 | P23: ='P-Categoria'!B6 -> Asegurar que el campo nombre de categoría debe ser único e irrepetible en su respectivo nivel de categoría padre | Q23: Generar una excepción indicando que ya existe una categoría con ese mismo nombre en ese mismo nivel | R23: Detener operación
G24: datos | H24: Categoria | O24: =HYPERLINK("#'P-Categoria'!A7",'P-Categoria'!A7) -> P-CAT-003 | P24: ='P-Categoria'!B7 -> Asegurar que los datos requeridos sean válidos en tipo de dato, longitud, obligatoriedad y formato | Q24: Generar una excepción indicando que los datos requeridos son inválidos o están incompletos | R24: Detener operación
O25: ='P-Categoria'!A8 -> P-CAT-004 | P25: ='P-Categoria'!B8 -> Asegurar que no se asigne como categoría padre a la misma categoría o a cualquier subcategoría que dependa de ella | Q25: Generar una excepción indicando que no se puede asignar como categoría padre a sí misma ni a una de sus subcategorías | R25: Detener operación
A26: eliminarCategoria | C26: Permite eliminar una categoría si no posee ningun objeto de dominio dentro de ella | G26: id | H26: UUID | I26: Contiene el identificador único de la categoría que se desea eliminar | O26: =HYPERLINK("#'P-Categoria'!A7",'P-Categoria'!A7) -> P-CAT-003 | P26: ='P-Categoria'!B7 -> Asegurar que los datos requeridos sean válidos en tipo de dato, longitud, obligatoriedad y formato | Q26: Generar una excepción indicando que los datos requeridos son inválidos o están incompletos | R26: Detener operación
O27: ='P-Categoria'!A9 -> P-CAT-005 | P27: ='P-Categoria'!B9 -> Asegurar que la categoría no tenga ningún producto o categoría dependiendo de ella | Q27: Generar una excepción indicando al usuario que un producto o categoría está presente dentro de la misma | R27: Detener operación

Sheet E-Categoria
A1: <<<Ir al modelo de dominio | B1: <<<Ir a objeto de dominio | C1: <<<Ir a muestreo del objeto | D1: <<<Ir a caracterización | E1: Ir a las políticas>>>
A2: Objeto de Dominio: | B2: ='Objetos de Dominio'!A9 -> Categoria
A3: Descripción: | B3: ='Objetos de Dominio'!B9 -> Representa la clasificación a la que pertenece un producto dentro del catálogo.
A4: Actor | B4: Action/Command | D4: Entity/Aggregate/Object domain | E4: Read Model | G4: Business Rule/Policy | I4: External System | J4: Domain Event | K4: Hotspot/questions/Risk
A5: Actor | B5: Acción | C5: Descripción | D5: Objeto de dominio | E5: Información externa | G5: Políticas | I5: Sistema Externo | J5: Evento | K5: Aspectos por solucionar
E6: Información | F6: Descripción | G6: Número | H6: Descripción
A7: Administrador | B7: Registrar una nueva categoría | C7: Permite registrar una nueva categoría en el sistema | D7: Categoria | E7: Datos de la nueva categoría | F7: Contiene la información requerida para registrar la categoría | G7: =HYPERLINK("#'P-Categoria'!A5",'P-Categoria'!A5) -> P-CAT-001 | H7: ='P-Categoria'!B5 -> Asegurar que el id de categoría debe ser único e irrepetible | J7: Categoria registrada
G8: =HYPERLINK("#'P-Categoria'!A6",'P-Categoria'!A6) -> P-CAT-002 | H8: ='P-Categoria'!B6 -> Asegurar que el campo nombre de categoría debe ser único e irrepetible en su respectivo nivel de categoría padre
G9: =HYPERLINK("#'P-Categoria'!A7",'P-Categoria'!A7) -> P-CAT-003 | H9: ='P-Categoria'!B7 -> Asegurar que los datos requeridos sean válidos en tipo de dato, longitud, obligatoriedad y formato
A10: Administrador/Vendedor | B10: Consultar categorías por filtro | C10: Permite buscar, listar y filtrar las categorías según los criterios de búsqueda enviados | D10: Categoria | E10: Filtros de las categorías | F10: Contiene los parámetros o criterios de búsqueda enviados para filtrar la consulta | G10: =HYPERLINK("#'P-Categoria'!A7",'P-Categoria'!A7) -> P-CAT-003 | H10: ='P-Categoria'!B7 -> Asegurar que los datos requeridos sean válidos en tipo de dato, longitud, obligatoriedad y formato | J10: Categorias encontradas
A11: Administrador | B11: Modificar una categoría | C11: Permite actualizar la información de una categoría existente | D11: Categoria | E11: Datos de la categoría a modificar | F11: Tiene el identificador único de la categoría a modificar y la nueva información | G11: =HYPERLINK("#'P-Categoria'!A6",'P-Categoria'!A6) -> P-CAT-002 | H11: ='P-Categoria'!B6 -> Asegurar que el campo nombre de categoría debe ser único e irrepetible en su respectivo nivel de categoría padre | J11: Categoria modificada
G12: =HYPERLINK("#'P-Categoria'!A7",'P-Categoria'!A7) -> P-CAT-003 | H12: ='P-Categoria'!B7 -> Asegurar que los datos requeridos sean válidos en tipo de dato, longitud, obligatoriedad y formato
G13: =HYPERLINK("#'P-Categoria'!A8",'P-Categoria'!A8) -> P-CAT-004 | H13: ='P-Categoria'!B8 -> Asegurar que no se asigne como categoría padre a la misma categoría o a cualquier subcategoría que dependa de ella
A14: Administrador | B14: Eliminar Categoria | C14: Permite eliminar una categoría del catálogo del sistema | D14: Categoria | E14: Datos categoría(id) | F14: Identificador único de la categoría que se desea retirar o inactivar | G14: =HYPERLINK("#'P-Categoria'!A7",'P-Categoria'!A7) -> P-CAT-003 | H14: ='P-Categoria'!B7 -> Asegurar que los datos requeridos sean válidos en tipo de dato, longitud, obligatoriedad y formato | J14: Categoria eliminada
G15: =HYPERLINK("#'P-Categoria'!A9",'P-Categoria'!A9) -> P-CAT-005 | H15: ='P-Categoria'!B9 -> Asegurar que la categoría no tenga ningún producto o categoría dependiendo de ella

Sheet P-Categoria
A1: <<<Ir al modelo de dominio | B1: <<<Ir a objeto de dominio | C1: <<<Ir a muestreo del objeto | D1: <<<Ir a caracterización | E1: <<<Ir al event storming
A2: Objeto de Dominio: | B2: ='Objetos de Dominio'!A9 -> Categoria
A3: Descripción: | B3: ='Objetos de Dominio'!B9 -> Representa la clasificación a la que pertenece un producto dentro del catálogo.
A4: Número Política | B4: Descripción Política | C4: Objeto Responsable
A5: P-CAT-001 | B5: Asegurar que el id de categoría debe ser único e irrepetible | C5: Categoria
A6: P-CAT-002 | B6: Asegurar que el campo nombre de categoría debe ser único e irrepetible en su respectivo nivel de categoría padre | C6: Categoria
A7: P-CAT-003 | B7: Asegurar que los datos requeridos sean válidos en tipo de dato, longitud, obligatoriedad y formato | C7: Categoria
A8: P-CAT-004 | B8: Asegurar que no se asigne como categoría padre a la misma categoría o a cualquier subcategoría que dependa de ella | C8: Categoria
A9: P-CAT-005 | B9: Asegurar que la categoría no tenga ningún producto o categoría dependiendo de ella | C9: Categoria

Sheet M-Prefijo
A1: <<<Ir al modelo de dominio | B1: <<<Ir a objeto de dominio | C1: Ir a la caracterización>>> | D1: Ir al event storming>>> | E1: Ir a las políticas>>>
A2: Nombre: | B2: ='Objetos de Dominio'!A10 -> Prefijo
A3: Descripción: | B3: ='Objetos de Dominio'!B10 -> Representa el código de marcado telefónico asociado a un país para el registro de números de contacto
A4: Identificador único del Prefijo | B4: Representa el código indicativo internacional de marcado telefónico | C4: Combinación única que representa que no puede existir un código de prefijo igual a otro
A5: ID | B5: Código | C5: PrefijoUnico
A6: 1 | B6: +57 | C6: =_xlfn.CONCAT(B6) -> +57
A7: 2 | B7: +32 | C7: =_xlfn.CONCAT(B7) -> +32
A8: 3 | B8: +1 | C8: =_xlfn.CONCAT(B8) -> +1
A9: 4 | B9: +52 | C9: =_xlfn.CONCAT(B9) -> +52
A10: 5 | B10: +54 | C10: =_xlfn.CONCAT(B10) -> +54

Sheet C-Prefijo
A1: <<<Ir al modelo de dominio | B1: <<<Ir a objeto de dominio | C1: <<<Ir a muestreo del objeto | D1: Ir al event storming>>> | E1: Ir a las políticas>>>
A2: Nombre | B2: ='Objetos de Dominio'!A10 -> Prefijo
A3: Descripción | B3: ='Objetos de Dominio'!B10 -> Representa el código de marcado telefónico asociado a un país para el registro de números de contacto
A4: Nombre atributo | B4: Descripción atributo | C4: Identificador del objeto de dominio | D4: Tipo de dato | E4: Obligatorio | F4: Longitud mínima (si aplica) | G4: Longitud máxima (si aplica) | H4: Precisión (si aplica) | I4: Redondeo (si aplica) | J4: Rango inicial (si aplica) | K4: Rango final (si aplica) | L4: Formato (si aplica) | M4: Reglas especiales (si aplica) | N4: Dato calculado | O4: Aplica ajuste del dato (si aplica) | P4: Carácter de ajuste (si aplica) | Q4: Quitar espacios en blanco al inicio (si aplica) | R4: Quitar espacios en blanco al fin (si aplica) | S4: Dato sensible (si aplica) | T4: Valor por defecto (si aplica) | U4: Auto generado | V4: consultarPrefijosPorFiltro
A5: ID | B5: ='M-Prefijo'!A4 -> Identificador único del Prefijo | C5: Si | D5: Identificador único universal | E5: Si | F5: - | G5: - | H5: - | I5: - | J5: - | K5: - | L5: - | M5: Debe ser único y no repetirse en los distintos id's de de los prefijos | N5: No | O5: No | P5: - | Q5: No | R5: No | S5: - | T5: - | U5: Si | V5: Filtro | W5: No Mostrar
A6: Código | B6: ='M-Prefijo'!B4 -> Representa el código indicativo internacional de marcado telefónico | C6: No | D6: Alfanumerico | E6: Si | F6: 2 | G6: 8 | H6: - | I6: - | J6: - | K6: - | L6: Formato válido de prefijos | M6: Se debe asegurar una sanitización del dato, para garantizar que dentro de su contenido no tenga cualquier tipo de intento de ataque | N6: No | O6: No | P6: - | Q6: Si | R6: Si | S6: - | T6: - | U6: No | V6: Filtro | W6: Mostrar
A9: Nombre combinación única | B9: Descripción | C9: Atributos involucrados
A10: ='M-Prefijo'!C5 -> PrefijoUnico | B10: ='M-Prefijo'!C4 -> Combinación única que representa que no puede existir un código de prefijo igual a otro | C10: Código
A12: Responsabilidad | C12: Descripción | G12: Entradas | J12: Salida | O12: Políticas (Reglas de Negocio) | Q12: Excepción
G13: Parámetro | H13: Tipo de dato | I13: Descripción | J13: Tipo de Dato | K13: Descripción | O13: Política | P13: Descripción | Q13: Detalle | R13: ¿Qué hago?
A14: consultarPrefijosPorFiltro | C14: Permite consultar la información detallada de los prefijos registrados en el sistema | G14: filtro | H14: Prefijo | I14: Contiene los parámetros o criterios de búsqueda enviados para filtrar la consulta | J14: Lista<Prefijo> | K14: Contiene la lista de categorías que cumplen con las condiciones del filtro enviado | O14: ='P-Prefijo'!A5 -> P-PRE-001 | P14: ='P-Prefijo'!B5 -> Asegurar que los datos requeridos sean válidos en tipo de dato, longitud, obligatoriedad y formato | Q14: Generar una excepción indicando que los datos requeridos son inválidos o están incompletos | R14: Detener operación

Sheet E-Prefijo
A1: <<<Ir al modelo de dominio | B1: <<<Ir a objeto de dominio | C1: <<<Ir a muestreo del objeto | D1: <<<Ir a caracterización | E1: Ir a las políticas>>>
A2: Objeto de Dominio: | B2: ='Objetos de Dominio'!A10 -> Prefijo
A3: Descripción: | B3: ='Objetos de Dominio'!B10 -> Representa el código de marcado telefónico asociado a un país para el registro de números de contacto
A4: Actor | B4: Action/Command | D4: Entity/Aggregate/ Object domain | E4: Read Model | G4: Business Rule/Policy | I4: External System | J4: Domain Event | K4: Hotspot/questions/Risk
A5: Actor | B5: Acción | C5: Descripción | D5: Objeto de dominio | E5: Información externa | G5: Políticas | I5: Sistema Externo | J5: Evento | K5: Aspectos por solucionar
E6: Información | F6: Descripción | G6: Número | H6: Descripción
A7: Administrador / Vendedor | B7: Buscar prefijo por filtro | C7: Permite buscar un prefijo determinado por un criterio específico (nombre, id) | D7: Prefijo | E7: Filtros de los prefijos | F7: Los parámetros de búsqueda ingresados por el usuario para filtrar un prefijo | G7: ='P-Prefijo'!A5 -> P-PRE-001 | H7: ='P-Prefijo'!B5 -> Asegurar que los datos requeridos sean válidos en tipo de dato, longitud, obligatoriedad y formato | J7: Prefijos encontrados

Sheet P-Prefijo
A1: <<<Ir al modelo de dominio | B1: <<<Ir a objeto de dominio | C1: <<<Ir a muestreo del objeto | D1: <<<Ir a caracterización | E1: <<<Ir al event storming
A2: Objeto de Dominio: | B2: ='Objetos de Dominio'!A10 -> Prefijo
A3: Descripción: | B3: ='Objetos de Dominio'!B10 -> Representa el código de marcado telefónico asociado a un país para el registro de números de contacto
A4: Número Política | B4: Descripción Política | C4: Objeto Responsable
A5: P-PRE-001 | B5: Asegurar que los datos requeridos sean válidos en tipo de dato, longitud, obligatoriedad y formato | C5: Prefijo

Sheet M-Persona
A1: <<<Ir al modelo de dominio | B1: <<<Ir a objeto de dominio | C1: Ir a la caracterización>>> | D1: Ir al event storming>>> | E1: Ir a las políticas>>>
A2: Nombre: | B2: ='Objetos de Dominio'!A11 -> Persona
A3: Descripción: | B3: ='Objetos de Dominio'!B11 -> Representa a un individuo en el sistema con sus datos generales de identificación para registrarse en el sistema
A4: Identificador único del empleado | B4: Representa el tipo de documento de identidad de la persona | C4: Representa el código indicativo internacional de marcado telefónico asociado al teléfono de la persona | D4: Representa el número del documento de identidad de la persona | E4: Número de contacto de la persona | F4: Representa el nombre de la persona | G4: Representa el apellido de la persona | H4: Correo electrónico de las personas | I4: Variable booleana que define si el teléfono de la persona está confirmado o no | J4: Variable booleana que define si el correo electrónico de la persona está confirmado o no | K4: Combinación única que indica que no puede existir más de un empleado con el mismo número de documento | L4: Combinación única que indica que no puede existir más de un empleado con el mismo teléfono | M4: Combinación única que indica que no puede existir más de un empleado con el mismo correo
A5: ID | B5: ='M-TipoDocumento'!B2 -> TipoDocumento | C5: ='M-Prefijo'!B2 -> Prefijo | D5: NumeroDocumento | E5: Telefono | F5: Nombre | G5: Apellido | H5: Correo | I5: TelefonoConfirmado | J5: CorreoConfirmado | K5: DocumentoPersona | L5: TelefonoPersona | M5: CorreoPersona
A6: 1 | B6: ='M-TipoDocumento'!C6 -> Cédula de ciudadanía | C6: ='M-Prefijo'!B6 -> +57 | D6: 1027661773 | E6: 3001234568 | F6: Carlos Andrés | G6: Riaño | H6: carlos.gomez@gmail.com | I6: SI | J6: NO | K6: =D6 -> 1027661773 | L6: =E6 -> 3001234568 | M6: =H6 -> carlos.gomez@gmail.com
A7: 2 | B7: ='M-TipoDocumento'!C7 -> Cédula de extranjería | C7: ='M-Prefijo'!B7 -> +32 | D7: 123456789 | E7: 3001234569 | F7: Mariana | G7: Jiménez | H7: mariana.lopez@gmail.com | I7: SI | J7: SI | K7: =D7 -> 123456789 | L7: =E7 -> 3001234569 | M7: =H7 -> mariana.lopez@gmail.com
A8: 3 | B8: ='M-TipoDocumento'!C8 -> Tarjeta de identidad | C8: ='M-Prefijo'!B8 -> +1 | D8: 900123456-7 | E8: 3001234571 | F8: Valentina | G8: Vélez | H8: valentina.ruiz@gmail.com | I8: NO | J8: SI | K8: =D8 -> 900123456-7 | L8: =E8 -> 3001234571 | M8: =H8 -> valentina.ruiz@gmail.com

Sheet C-Persona
A1: <<<Ir al modelo de dominio | B1: <<<Ir a objeto de dominio | C1: <<<Ir a muestreo del objeto | D1: Ir al event storming>>> | E1: Ir a las políticas>>> | F1: <<<Ir a crud
A2: Nombre | B2: ='Objetos de Dominio'!A11 -> Persona
A3: Descripción | B3: ='Objetos de Dominio'!B11 -> Representa a un individuo en el sistema con sus datos generales de identificación para registrarse en el sistema
A4: Nombre atributo | B4: Descripción atributo | C4: Identificador del objeto de dominio | D4: Tipo de dato | E4: Obligatorio | F4: Longitud mínima (si aplica) | G4: Longitud máxima (si aplica) | H4: Precisión (si aplica) | I4: Redondeo (si aplica) | J4: Rango inicial (si aplica) | K4: Rango final (si aplica) | L4: Formato (si aplica) | M4: Reglas especiales (si aplica) | N4: Dato calculado | O4: Aplica ajuste del dato (si aplica) | P4: Carácter de ajuste (si aplica) | Q4: Quitar espacios en blanco al inicio (si aplica) | R4: Quitar espacios en blanco al fin (si aplica) | S4: Dato sensible (si aplica) | T4: Valor por defecto (si aplica) | U4: Auto generado | V4: registrarPersona | W4: consultarPersonasPorFiltro | Y4: modificarPersona | AA4: eliminarPersona
A5: ='M-Persona'!A5 -> ID | B5: ='M-Persona'!A4 -> Identificador único del empleado | C5: Si | D5: Identificador único universal | E5: Si | F5: - | G5: - | H5: - | I5: - | J5: - | K5: - | L5: - | M5: Debe ser único y no debe repetirse en los distintos id's de los clientes registrados naturales | N5: No | O5: No | P5: - | Q5: No | R5: No | S5: - | T5: - | U5: Si | V5: Requerido | W5: Filtro | X5: No Mostrar | Y5: Requerido | Z5: No modificable | AA5: Requerido
A6: ='M-Persona'!B5 -> TipoDocumento | B6: ='M-Persona'!B4 -> Representa el tipo de documento de identidad de la persona | C6: No | D6: TipoDocumento | E6: Si | F6: - | G6: - | H6: - | I6: - | J6: - | K6: - | L6: - | M6: Aplican las reglas del objeto referenciado | N6: No | O6: No | P6: - | Q6: No | R6: No | S6: - | T6: - | U6: No | V6: Requerido | W6: Filtro | X6: Mostrar | Y6: No Requerido | Z6: Modificable | AA6: No requerido
A7: ='M-Persona'!C5 -> Prefijo | B7: ='M-Persona'!C4 -> Representa el código indicativo internacional de marcado telefónico asociado al teléfono de la persona | C7: No | D7: Prefijo | E7: Si | F7: - | G7: - | H7: - | I7: - | J7: - | K7: - | L7: - | M7: Aplican las reglas del objeto referenciado | N7: No | O7: No | P7: - | Q7: No | R7: No | S7: - | T7: - | U7: No | V7: Requerido | W7: No filtro | X7: Mostrar | Y7: No Requerido | Z7: Modificable | AA7: No requerido
A8: ='M-Persona'!D5 -> NumeroDocumento | B8: ='M-Persona'!D4 -> Representa el número del documento de identidad de la persona | C8: No | D8: Alfanumérico | E8: Si | F8: 3 | G8: 20 | H8: - | I8: - | J8: - | K8: - | L8: Formato de documento correspondiente válido 1.207.661.773 | M8: Se debe asegurar una sanitización del dato, para garantizar que dentro de su contenido no tenga cualquier tipo de intento de ataque | N8: No | O8: No | P8: - | Q8: Si | R8: Si | S8: Si | T8: - | U8: No | V8: Requerido | W8: Filtro | X8: Mostrar | Y8: No Requerido | Z8: Modificable | AA8: No requerido
A9: ='M-Persona'!E5 -> Telefono | B9: ='M-Persona'!E4 -> Número de contacto de la persona | C9: No | D9: Alfanumérico | E9: Si | F9: 7 | G9: 15 | H9: - | I9: - | J9: - | K9: - | L9: Formato de número telefónico correspondiente válido (+57) 3158185857 | M9: Se debe asegurar una sanitización del dato, para garantizar que dentro de su contenido no tenga cualquier tipo de intento de ataque, solo se aceptan dígitos | N9: No | O9: No | P9: - | Q9: Si | R9: Si | S9: Si | T9: - | U9: No | V9: Requerido | W9: Filtro | X9: Mostrar | Y9: No Requerido | Z9: Modificable | AA9: No requerido
A10: ='M-Persona'!F5 -> Nombre | B10: ='M-Persona'!F4 -> Representa el nombre de la persona | C10: No | D10: Alfanumérico | E10: Si | F10: 2 | G10: 50 | H10: - | I10: - | J10: - | K10: - | L10: - | M10: Se debe asegurar una sanitización del dato, para garantizar que dentro de su contenido no tenga cualquier tipo de intento de ataque | N10: No | O10: No | P10: - | Q10: Si | R10: Si | S10: - | T10: - | U10: No | V10: Requerido | W10: Filtro | X10: Mostrar | Y10: No Requerido | Z10: Modificable | AA10: No requerido
A11: ='M-Persona'!G5 -> Apellido | B11: ='M-Persona'!G4 -> Representa el apellido de la persona | C11: No | D11: Alfanumérico | E11: Si | F11: 2 | G11: 100 | H11: - | I11: - | J11: - | K11: - | L11: - | M11: Se debe asegurar una sanitización del dato, para garantizar que dentro de su contenido no tenga cualquier tipo de intento de ataque | N11: No | O11: No | P11: - | Q11: Si | R11: Si | S11: - | T11: - | U11: No | V11: Requerido | W11: Filtro | X11: Mostrar | Y11: No Requerido | Z11: Modificable | AA11: No requerido
A12: ='M-Persona'!H5 -> Correo | B12: ='M-Persona'!H4 -> Correo electrónico de las personas | C12: No | D12: Alfanumérico | E12: Si | F12: 6 | G12: 254 | H12: - | I12: - | J12: - | K12: - | L12: Formato válido de correo electrónico | M12: Debe contener únicamente números y corresponder a un número telefónico móvil o fijo colombiano válido | N12: No | O12: No | P12: - | Q12: Si | R12: Si | S12: Si | T12: - | U12: No | V12: Requerido | W12: Filtro | X12: Mostrar | Y12: No Requerido | Z12: Modificable | AA12: No requerido
A13: ='M-Persona'!I5 -> TelefonoConfirmado | B13: ='M-Persona'!I4 -> Variable booleana que define si el teléfono de la persona está confirmado o no | C13: No | D13: Lógico | E13: Si | F13: - | G13: - | H13: - | I13: - | J13: - | K13: - | L13: - | M13: Solo admite SI o NO, pasa a SI únicamente tras validar el correo con el cliente o empleado, por medio de un mensaje o un vinculo | N13: No | O13: No | P13: - | Q13: No | R13: No | S13: - | T13: No | U13: Si | V13: No Requerido | W13: No filtro | X13: No Mostrar | Y13: No Requerido | Z13: No modificable | AA13: No requerido
A14: ='M-Persona'!J5 -> CorreoConfirmado | B14: ='M-Persona'!J4 -> Variable booleana que define si el correo electrónico de la persona está confirmado o no | C14: No | D14: Lógico | E14: Si | F14: - | G14: - | H14: - | I14: - | J14: - | K14: - | L14: - | M14: Solo admite SI o NO; pasa a SI únicamente tras validar el teléfono con el cliente o empleado, por medio de un mensaje o un vinculo | N14: No | O14: No | P14: - | Q14: No | R14: No | S14: - | T14: No | U14: Si | V14: No Requerido | W14: No filtro | X14: No Mostrar | Y14: No requerido | Z14: No modificable | AA14: No requerido
A17: Nombre combinación única | B17: Descripción | C17: Atributos involucrados
A18: ='M-Persona'!K5 -> DocumentoPersona | B18: ='M-Persona'!K4 -> Combinación única que indica que no puede existir más de un empleado con el mismo número de documento | C18: NumeroDocumento
A19: ='M-Persona'!L5 -> TelefonoPersona | B19: ='M-Persona'!L4 -> Combinación única que indica que no puede existir más de un empleado con el mismo teléfono | C19: Telefono
A20: ='M-Persona'!M5 -> CorreoPersona | B20: ='M-Persona'!M4 -> Combinación única que indica que no puede existir más de un empleado con el mismo correo | C20: Correo
A24: Responsabilidad | C24: Descripción | G24: Entradas | J24: Salida | O24: Políticas (Reglas de Negocio) | Q24: Excepción
G25: Parámetro | H25: Tipo de dato | I25: Descripción | J25: Tipo de Dato | K25: Descripción | O25: Política | P25: Descripción | Q25: Detalle | R25: ¿Qué hago?
A26: registrarPersona | C26: Permite registrar una nueva persona en el sistema | G26: datos | H26: Persona | I26: Contiene la información requerida para registrar la persona correspondiente | J26: Persona | K26: Objeto de la persona con su identificador ID asignado, nombre, apellido, teléfono y demás atributos | O26: ='P-Persona'!A5 -> P-PER-001 | P26: ='P-Persona'!B5 -> Asegurar que el id de la persona sea único e irrepetible | Q26: Generar un nuevo identificador hasta garantizar que no exista | R26: Continuar operación
O27: ='P-Persona'!A6 -> P-PER-002 | P27: ='P-Persona'!B6 -> Asegurar que el campo NumeroDocumento de la persona sea único e irrepetible | Q27: Generar una excepción indicando que ya existe una persona con ese mismo Documento | R27: Detener operación
O28: ='P-Persona'!A7 -> P-PER-003 | P28: ='P-Persona'!B7 -> Asegurar que el campo Telefono de la persona sea único e irrepetible | Q28: Generar una excepción indicando que ya existe una persona con ese mismo Telefono | R28: Detener operación
O29: ='P-Persona'!A8 -> P-PER-004 | P29: ='P-Persona'!B8 -> Asegurar que el campo Correo de la persona sea único e irrepetible | Q29: Generar una excepción indicando que ya existe una persona con ese mismo Correo | R29: Detener operación
O30: ='P-Persona'!A9 -> P-PER-005 | P30: ='P-Persona'!B9 -> Asegurar que los datos requeridos de la persona sean válidos en tipo de dato, longitud, obligatoriedad y formato | Q30: Generar una excepción indicando que los datos requeridos son inválidos o están incompletos | R30: Detener operación
O31: ='P-Persona'!A11 -> P-PER-007 | P31: ='P-Persona'!B11 -> Asegurar que la persona tiene la opcion de escoger cualquier tipo de documento a excepción del NIT | Q31: Generar una excepción indicando que el nit no está disponible para registrar persona natural | R31: Detener operación
A32: consultarPersonasPorFiltro | C32: Permite buscar, listar y filtrar las personas según los criterios de búsqueda enviados | G32: filtro | H32: Persona | I32: Contiene los parámetros o criterios de búsqueda enviados para filtrar la consulta | J32: Lista<Persona> | K32: Contiene la lista de las personas que cumplen con las condiciones del filtro enviado | O32: ='P-Persona'!A9 -> P-PER-005 | P32: ='P-Persona'!B9 -> Asegurar que los datos requeridos de la persona sean válidos en tipo de dato, longitud, obligatoriedad y formato | Q32: Generar una excepción indicando que los datos requeridos son inválidos o están incompletos | R32: Detener operación
A33: modificarPersona | C33: Permite actualizar la información de una persona existente | G33: id | H33: UUID | I33: Tiene el identificador único de una persona a modificar y la nueva información correspondiente | J33: Persona | K33: Objeto de la persona con su información actualizada | O33: ='P-Persona'!A6 -> P-PER-002 | P33: ='P-Persona'!B6 -> Asegurar que el campo NumeroDocumento de la persona sea único e irrepetible | Q33: Generar una excepción indicando que ya existe una persona con ese mismo Documento | R33: Detener operación
O34: ='P-Persona'!A7 -> P-PER-003 | P34: ='P-Persona'!B7 -> Asegurar que el campo Telefono de la persona sea único e irrepetible | Q34: Generar una excepción indicando que ya existe una persona con ese mismo Telefono | R34: Detener operación
G35: datos | H35: Persona | O35: ='P-Persona'!A8 -> P-PER-004 | P35: ='P-Persona'!B8 -> Asegurar que el campo Correo de la persona sea único e irrepetible | Q35: Generar una excepción indicando que ya existe una persona con ese mismo Correo | R35: Detener operación
O36: ='P-Persona'!A9 -> P-PER-005 | P36: ='P-Persona'!B9 -> Asegurar que los datos requeridos de la persona sean válidos en tipo de dato, longitud, obligatoriedad y formato | Q36: Generar una excepción indicando que los datos requeridos son inválidos o están incompletos | R36: Detener operación
A37: eliminarPersona | C37: Permite eliminar una persona eliminando la trazabilidad de su historial | G37: id | H37: UUID | I37: Contiene el identificador único de la persona que se desea eliminar | O37: ='P-Persona'!A9 -> P-PER-005 | P37: ='P-Persona'!B9 -> Asegurar que los datos requeridos de la persona sean válidos en tipo de dato, longitud, obligatoriedad y formato | Q37: Generar una excepción indicando que los datos requeridos son inválidos o están incompletos | R37: Detener operación
O38: ='P-Persona'!A10 -> P-PER-006 | P38: ='P-Persona'!B10 -> Asegurar que persona no esté siendo utilizado dentro de otro objeto de dominio | Q38: Generar una excepción indicando al usuario que el objeto de dominio está presente dentro de otro objeto | R38: Detener operación

Sheet E-Persona
A1: <<<Ir al modelo de dominio | B1: <<<Ir a objeto de dominio | C1: <<<Ir a muestreo del objeto | D1: <<<Ir a caracterización | E1: Ir a las políticas>>> | F1: <<<Ir a crud
A2: Objeto de Dominio: | B2: ='Objetos de Dominio'!A11 -> Persona
A3: Descripción: | B3: ='Objetos de Dominio'!B11 -> Representa a un individuo en el sistema con sus datos generales de identificación para registrarse en el sistema
A4: Actor | B4: Action/Command | D4: Entity/Aggregate/Object domain | E4: Read Model | G4: Business Rule/Policy | I4: External System | J4: Domain Event | K4: Hotspot/questions/Risk
A5: Actor | B5: Acción | C5: Descripción | D5: Objeto de dominio | E5: Información externa | G5: Políticas | I5: Sistema Externo | J5: Evento | K5: Aspectos por solucionar
E6: Información | F6: Descripción | G6: Número | H6: Descripción
A7: Administrador/Vendedor | B7: Registrar una nueva persona | C7: Permite registrar una nueva persona en el sistema | D7: Persona | E7: Datos de la nueva persona | F7: Contiene la información requerida para registrar la persona | G7: =HYPERLINK("#'P-Persona'!A5",'P-Persona'!A5) -> P-PER-001 | H7: ='P-Persona'!B5 -> Asegurar que el id de la persona sea único e irrepetible | J7: Persona registrada
G8: =HYPERLINK("#'P-Persona'!A6",'P-Persona'!A6) -> P-PER-002 | H8: ='P-Persona'!B6 -> Asegurar que el campo NumeroDocumento de la persona sea único e irrepetible
G9: =HYPERLINK("#'P-Persona'!A7",'P-Persona'!A7) -> P-PER-003 | H9: ='P-Persona'!B7 -> Asegurar que el campo Telefono de la persona sea único e irrepetible
G10: =HYPERLINK("#'P-Persona'!A8",'P-Persona'!A8) -> P-PER-004 | H10: ='P-Persona'!B8 -> Asegurar que el campo Correo de la persona sea único e irrepetible
G11: =HYPERLINK("#'P-Persona'!A9",'P-Persona'!A9) -> P-PER-005 | H11: ='P-Persona'!B9 -> Asegurar que los datos requeridos de la persona sean válidos en tipo de dato, longitud, obligatoriedad y formato
G12: =HYPERLINK("#'P-Persona'!A11",'P-Persona'!A11) -> P-PER-007 | H12: ='P-Persona'!B11 -> Asegurar que la persona tiene la opcion de escoger cualquier tipo de documento a excepción del NIT
A13: Administrador/Vendedor | B13: Consultar personas por filtro | C13: Permite buscar, listar y filtrar las personas según los criterios de búsqueda enviados | D13: Persona | E13: Filtros de Persona | F13: Contiene los parámetros o criterios de búsqueda enviados para filtrar la consulta | G13: =HYPERLINK("#'P-Persona'!A9",'P-Persona'!A9) -> P-PER-005 | H13: ='P-Persona'!B9 -> Asegurar que los datos requeridos de la persona sean válidos en tipo de dato, longitud, obligatoriedad y formato | J13: Personas encontradas
A14: Administrador | B14: Modificar una persona | C14: Permite actualizar la información de una persona existente | D14: Persona | E14: Datos de la persona a modificar | F14: Tiene el identificador único de la persona a modificar y la nueva información | G14: =HYPERLINK("#'P-Persona'!A6",'P-Persona'!A6) -> P-PER-002 | H14: ='P-Persona'!B6 -> Asegurar que el campo NumeroDocumento de la persona sea único e irrepetible | J14: Persona modificada
G15: =HYPERLINK("#'P-Persona'!A7",'P-Persona'!A7) -> P-PER-003 | H15: ='P-Persona'!B7 -> Asegurar que el campo Telefono de la persona sea único e irrepetible
G16: =HYPERLINK("#'P-Persona'!A8",'P-Persona'!A8) -> P-PER-004 | H16: ='P-Persona'!B8 -> Asegurar que el campo Correo de la persona sea único e irrepetible
G17: =HYPERLINK("#'P-Persona'!A9",'P-Persona'!A9) -> P-PER-005 | H17: ='P-Persona'!B9 -> Asegurar que los datos requeridos de la persona sean válidos en tipo de dato, longitud, obligatoriedad y formato
A18: Administrador | B18: Eliminar una persona | C18: Permite eliminar una persona eliminando la trazabilidad de su historial | D18: Persona | E18: Identificador de la persona a eliminar | F18: Contiene el identificador único de la persona que se desea eliminar | G18: =HYPERLINK("#'P-Persona'!A9",'P-Persona'!A9) -> P-PER-005 | H18: ='P-Persona'!B9 -> Asegurar que los datos requeridos de la persona sean válidos en tipo de dato, longitud, obligatoriedad y formato | J18: Persona eliminada
G19: ='P-Persona'!A10 -> P-PER-006 | H19: ='P-Persona'!B10 -> Asegurar que persona no esté siendo utilizado dentro de otro objeto de dominio

Sheet P-Persona
A1: <<<Ir al modelo de dominio | B1: <<<Ir a objeto de dominio | C1: <<<Ir a muestreo del objeto | D1: <<<Ir a caracterización | E1: <<<Ir al event storming | F1: <<<Ir a crud
A2: Objeto de Dominio: | B2: ='Objetos de Dominio'!A11 -> Persona
A3: Descripción: | B3: ='Objetos de Dominio'!B11 -> Representa a un individuo en el sistema con sus datos generales de identificación para registrarse en el sistema
A4: Número Política | B4: Descripción Política | C4: Objeto Responsable
A5: P-PER-001 | B5: Asegurar que el id de la persona sea único e irrepetible | C5: Persona
A6: P-PER-002 | B6: Asegurar que el campo NumeroDocumento de la persona sea único e irrepetible | C6: Persona
A7: P-PER-003 | B7: Asegurar que el campo Telefono de la persona sea único e irrepetible | C7: Persona
A8: P-PER-004 | B8: Asegurar que el campo Correo de la persona sea único e irrepetible | C8: Persona
A9: P-PER-005 | B9: Asegurar que los datos requeridos de la persona sean válidos en tipo de dato, longitud, obligatoriedad y formato | C9: Persona
A10: P-PER-006 | B10: Asegurar que persona no esté siendo utilizado dentro de otro objeto de dominio | C10: Persona
A11: P-PER-007 | B11: Asegurar que la persona tiene la opcion de escoger cualquier tipo de documento a excepción del NIT | C11: Persona

Sheet M-Producto
A1: <<<Ir al modelo de dominio | B1: <<<Ir a objeto de dominio | C1: Ir a la caracterización>>> | D1: Ir al event storming>>> | E1: Ir a las políticas>>>
A2: Nombre: | B2: ='Objetos de Dominio'!A12 -> Producto
A3: Descripción: | B3: ='Objetos de Dominio'!B12 -> Representa un artículo del catálogo general del negocio, independiente de la sede en la que se encuentre.
A4: Identificador único del producto | B4: Marca a la que pertenece el producto | C4: Categoría a la que pertenece el producto | D4: Modelo o referencia única del producto | E4: Nombre del accesorio dentro del catálogo general | F4: Descripción general del accesorio | G4: Combinación única que indica que no puede existir más de un producto con el mismo modelo
A5: ID | B5: =HYPERLINK("#'M-Marca'!A1",'M-Marca'!B2) -> Marca | C5: =HYPERLINK("#'M-Categoria'!A1",'M-Categoria'!B2) -> Categoria | D5: Modelo | E5: Nombre | F5: Descripción | G5: ModeloUnico
A6: 1 | B6: =HYPERLINK("#'M-Marca'!C7",'M-Marca'!D7) -> Apple | C6: =HYPERLINK("#'M-Categoria'!E15",'M-Categoria'!E15) -> Estuches iPhone || Estuches Celulares | D6: LWFIP14 | E6: Funda Silicona iPhone 14 | F6: Funda de silicona suave con acabado mate | G6: =D6 -> LWFIP14
A7: 2 | B7: =HYPERLINK("#'M-Marca'!C7",'M-Marca'!D7) -> Apple | C7: =HYPERLINK("#'M-Categoria'!E37",'M-Categoria'!E37) -> Vidrios iPhone || Vidrios Celulares | D7: VDIP13 | E7: Vidrio Templado iPhone 13 | F7: Protector de pantalla de vidrio templado antiespías | G7: =D7 -> VDIP13
A8: 3 | B8: =HYPERLINK("#'M-Marca'!C7",'M-Marca'!D7) -> Apple | C8: =HYPERLINK("#'M-Categoria'!E50",'M-Categoria'!E50) -> Cargadores Apple || Cargadores | D8: TPCIP35w | E8: Cargador Rápido 35W USB-C | F8: Cargador con cable carga rápida | G8: =D8 -> TPCIP35w
A9: 4 | B9: =HYPERLINK("#'M-Marca'!C8",'M-Marca'!D8) -> Xiaomi | C9: =HYPERLINK("#'M-Categoria'!E55",'M-Categoria'!E55) -> Audífonos Inalámbricos || Audífonos | D9: AirDots 2 | E9: Audífonos Bluetooth Buds | F9: Audífonos inalámbricos con estuche de carga | G9: =D9 -> AirDots 2
A10: 5 | B10: =HYPERLINK("#'M-Marca'!C6",'M-Marca'!D6) -> Samsung | C10: =HYPERLINK("#'M-Categoria'!E38",'M-Categoria'!E38) -> Vidrios Samsung || Vidrios Celulares | D10: VDA12 | E10: Vidrio Templado Samsung A12 | F10: Protector de pantalla de vidrio templado | G10: =D10 -> VDA12
A11: 6 | B11: =HYPERLINK("#'M-Marca'!C10",'M-Marca'!D10) -> Batri | C11: =HYPERLINK("#'M-Categoria'!E45",'M-Categoria'!E45) -> Cables Tipo C-Tipo C || Cables | D11: CU16 | E11: Cable USB-C a USB-C 1m | F11: Cable de carga y transferencia de datos | G11: =D11 -> CU16
A12: 7 | B12: =HYPERLINK("#'M-Marca'!C11",'M-Marca'!D11) -> iGoma | C12: =HYPERLINK("#'M-Categoria'!E63",'M-Categoria'!E63) -> Power Banks 10.000 mAh || Power Banks | D12: IG-029 | E12: Power Bank 10000mAh | F12: Batería portátil de carga rápida | G12: =D12 -> IG-029

Sheet C-Producto
A1: <<<Ir al modelo de dominio | B1: <<<Ir a objeto de dominio | C1: <<<Ir a muestreo del objeto | D1: Ir al event storming>>> | E1: Ir a las políticas>>>
A2: Nombre | B2: ='Objetos de Dominio'!A12 -> Producto
A3: Descripción | B3: ='Objetos de Dominio'!B12 -> Representa un artículo del catálogo general del negocio, independiente de la sede en la que se encuentre.
A4: Nombre atributo | B4: Descripción atributo | C4: Identificador del objeto de dominio | D4: Tipo de dato | E4: Obligatorio | F4: Longitud mínima (si aplica) | G4: Longitud máxima (si aplica) | H4: Precisión (si aplica) | I4: Redondeo (si aplica) | J4: Rango inicial (si aplica) | K4: Rango final (si aplica) | L4: Formato (si aplica) | M4: Reglas especiales (si aplica) | N4: Dato calculado | O4: Aplica ajuste del dato (si aplica) | P4: Carácter de ajuste (si aplica) | Q4: Quitar espacios en blanco al inicio (si aplica) | R4: Quitar espacios en blanco al fin (si aplica) | S4: Dato sensible (si aplica) | T4: Valor por defecto (si aplica) | U4: Auto generado | V4: registrarProducto | W4: consultarProductosPorFiltro | Y4: modificarProducto
A5: ID | B5: ='M-Producto'!A4 -> Identificador único del producto | C5: Si | D5: Identificador único universal | E5: Si | F5: - | G5: - | H5: - | I5: - | J5: - | K5: - | L5: - | M5: Debe ser único y no debe repetirse en los distintos id's de los productos | N5: No | O5: No | P5: - | Q5: No | R5: No | S5: - | T5: - | U5: Si | V5: Requerido | W5: Filtro | X5: No Mostrar | Y5: Requerido | Z5: No modificable
A6: Marca | B6: ='M-Producto'!B4 -> Marca a la que pertenece el producto | C6: No | D6: Marca | E6: Si | F6: - | G6: - | H6: - | I6: - | J6: - | K6: - | L6: - | M6: Aplican las reglas del objeto referenciado | N6: No | O6: No | P6: - | Q6: No | R6: No | S6: - | T6: - | U6: No | V6: Requerido | W6: Filtro | X6: Mostrar | Y6: No Requerido | Z6: No Modificable
A7: Categoria | B7: ='M-Producto'!C4 -> Categoría a la que pertenece el producto | C7: No | D7: Categoria | E7: Si | F7: - | G7: - | H7: - | I7: - | J7: - | K7: - | L7: - | M7: Aplican las reglas del objeto referenciado | N7: No | O7: No | P7: - | Q7: No | R7: No | S7: - | T7: - | U7: No | V7: Requerido | W7: Filtro | X7: Mostrar | Y7: No Requerido | Z7: Modificable
A8: Modelo | B8: ='M-Producto'!D4 -> Modelo o referencia única del producto | C8: No | D8: Alfanumérico | E8: Si | F8: 2 | G8: 50 | H8: - | I8: - | J8: - | K8: - | L8: - | M8: Se debe asegurar una sanitización del dato, para garantizar que dentro de su contenido no tenga cualquier tipo de intento de ataque | N8: No | O8: No | P8: - | Q8: Si | R8: Si | S8: - | T8: - | U8: No | V8: Requerido | W8: Filtro | X8: Mostrar | Y8: No Requerido | Z8: Modificable
A9: Nombre | B9: ='M-Producto'!E4 -> Nombre del accesorio dentro del catálogo general | C9: No | D9: Alfanumérico | E9: Si | F9: 2 | G9: 60 | H9: - | I9: - | J9: - | K9: - | L9: - | M9: Se debe asegurar una sanitización del dato, para garantizar que dentro de su contenido no tenga cualquier tipo de intento de ataque | N9: No | O9: No | P9: - | Q9: Si | R9: Si | S9: - | T9: - | U9: No | V9: Requerido | W9: Filtro | X9: Mostrar | Y9: No Requerido | Z9: Modificable
A10: Descripción | B10: ='M-Producto'!F4 -> Descripción general del accesorio | C10: No | D10: Alfanumérico | E10: Si | F10: 10 | G10: 500 | H10: - | I10: - | J10: - | K10: - | L10: - | M10: Se debe asegurar una sanitización del dato, para garantizar que dentro de su contenido no tenga cualquier tipo de intento de ataque | N10: No | O10: No | P10: - | Q10: Si | R10: Si | S10: - | T10: - | U10: No | V10: Requerido | W10: No filtro | X10: No Mostrar | Y10: No Requerido | Z10: Modificable
A13: Nombre combinación única | B13: Descripción | C13: Atributos involucrados
A14: ='M-Producto'!G5 -> ModeloUnico | B14: ='M-Producto'!G4 -> Combinación única que indica que no puede existir más de un producto con el mismo modelo | C14: Modelo
A18: Responsabilidad | C18: Descripción | G18: Entradas | J18: Salida | O18: Políticas (Reglas de Negocio) | Q18: Excepción
G19: Parámetro | H19: Tipo de dato | I19: Descripción | J19: Tipo de Dato | K19: Descripción | O19: Política | P19: Descripción | Q19: Detalle | R19: ¿Qué hago?
A20: registrarProducto | C20: Permite registrar un nuevo producto en el sistema | G20: datos | H20: Producto | I20: Contiene la información requerida para registrar el producto | J20: Producto | K20: Objeto del producto registrado con su identificador ID asignado y demas atributos correspondientes | O20: ='P-Producto'!A5 -> P-PRO-001 | P20: ='P-Producto'!B5 -> Asegurar que el id de producto debe ser único e irrepetible | Q20: Generar un nuevo identificador hasta garantizar que no exista | R20: Continuar operación
O21: ='P-Producto'!A6 -> P-PRO-002 | P21: ='P-Producto'!B6 -> Asegurar que el campo Modelo de producto debe ser único e irrepetible | Q21: Generar una excepción indicando que ya existe un producto con ese mismo Modelo | R21: Detener operación
O22: ='P-Producto'!A7 -> P-PRO-003 | P22: ='P-Producto'!B7 -> Asegurar que los datos requeridos sean válidos en tipo de dato, longitud, obligatoriedad y formato | Q22: Generar una excepción indicando que los datos requeridos son inválidos o están incompletos | R22: Detener operación
A23: consultarProductosPorFiltro | C23: Permite buscar, listar y filtrar los productos según los criterios de búsqueda enviados | G23: filtro | H23: Producto | I23: Contiene los parámetros o criterios de búsqueda enviados para filtrar la consulta | J23: Lista<Producto> | K23: Contiene la lista de productos que cumplen con las condiciones del filtro enviado | O23: ='P-Producto'!A7 -> P-PRO-003 | P23: ='P-Producto'!B7 -> Asegurar que los datos requeridos sean válidos en tipo de dato, longitud, obligatoriedad y formato | Q23: Generar una excepción indicando que los datos requeridos son inválidos o están incompletos | R23: Detener operación
A24: modificarProducto | C24: Permite actualizar la información de un producto existente | G24: id | H24: UUID | I24: Tiene el identificador único del producto a modificar y la nueva información | J24: Producto | K24: Objeto del producto con su información actualizada | O24: ='P-Producto'!A6 -> P-PRO-002 | P24: ='P-Producto'!B6 -> Asegurar que el campo Modelo de producto debe ser único e irrepetible | Q24: Generar una excepción indicando que ya existe un producto con ese mismo Modelo | R24: Detener operación
G25: datos | H25: Producto | O25: ='P-Producto'!A7 -> P-PRO-003 | P25: ='P-Producto'!B7 -> Asegurar que los datos requeridos sean válidos en tipo de dato, longitud, obligatoriedad y formato | Q25: Generar una excepción indicando que los datos requeridos son inválidos o están incompletos | R25: Detener operación

Sheet E-Producto
A1: <<<Ir al modelo de dominio | B1: <<<Ir a objeto de dominio | C1: <<<Ir a muestreo del objeto | D1: <<<Ir a caracterización | E1: Ir a las políticas>>>
A2: Objeto de Dominio: | B2: ='Objetos de Dominio'!A12 -> Producto
A3: Descripción: | B3: ='Objetos de Dominio'!B12 -> Representa un artículo del catálogo general del negocio, independiente de la sede en la que se encuentre.
A4: Actor | B4: Action/Command | D4: Entity/Aggregate/Object domain | E4: Read Model | G4: Business Rule/Policy | I4: External System | J4: Domain Event | K4: Hotspot/questions/Risk
A5: Actor | B5: Acción | C5: Descripción | D5: Objeto de dominio | E5: Información externa | G5: Políticas | I5: Sistema Externo | J5: Evento | K5: Aspectos por solucionar
E6: Información | F6: Descripción | G6: Número | H6: Descripción
A7: Administrador | B7: Registrar un nuevo producto | C7: Permite registrar un nuevo producto en el sistema | D7: Producto | E7: Datos del nuevo producto | F7: Contiene la información requerida para registrar el producto | G7: ='P-Producto'!A5 -> P-PRO-001 | H7: ='P-Producto'!B5 -> Asegurar que el id de producto debe ser único e irrepetible | J7: Producto registrado
G8: ='P-Producto'!A6 -> P-PRO-002 | H8: ='P-Producto'!B6 -> Asegurar que el campo Modelo de producto debe ser único e irrepetible
G9: ='P-Producto'!A7 -> P-PRO-003 | H9: ='P-Producto'!B7 -> Asegurar que los datos requeridos sean válidos en tipo de dato, longitud, obligatoriedad y formato
A10: Administrador/Vendedor | B10: Consultar productos por filtro | C10: Permite buscar, listar y filtrar los productos según los criterios de búsqueda enviados | D10: Producto | E10: Filtros de los productos | F10: Contiene los parámetros o criterios de búsqueda enviados para filtrar la consulta | G10: ='P-Producto'!A7 -> P-PRO-003 | H10: ='P-Producto'!B7 -> Asegurar que los datos requeridos sean válidos en tipo de dato, longitud, obligatoriedad y formato | J10: Productos encontrados
A11: Administrador | B11: Modificar un producto | C11: Permite actualizar la información de un producto existente | D11: Producto | E11: Datos del producto a modificar | F11: Tiene el identificador único del producto a modificar y la nueva información | G11: ='P-Producto'!A6 -> P-PRO-002 | H11: ='P-Producto'!B6 -> Asegurar que el campo Modelo de producto debe ser único e irrepetible | J11: Producto modificado
G12: ='P-Producto'!A7 -> P-PRO-003 | H12: ='P-Producto'!B7 -> Asegurar que los datos requeridos sean válidos en tipo de dato, longitud, obligatoriedad y formato

Sheet P-Producto
A1: <<<Ir al modelo de dominio | B1: <<<Ir a objeto de dominio | C1: <<<Ir a muestreo del objeto | D1: <<<Ir a caracterización | E1: <<<Ir al event storming
A2: Objeto de Dominio: | B2: ='Objetos de Dominio'!A12 -> Producto
A3: Descripción: | B3: ='Objetos de Dominio'!B12 -> Representa un artículo del catálogo general del negocio, independiente de la sede en la que se encuentre.
A4: Número Política | B4: Descripción Política | C4: Objeto Responsable
A5: P-PRO-001 | B5: Asegurar que el id de producto debe ser único e irrepetible | C5: Producto
A6: P-PRO-002 | B6: Asegurar que el campo Modelo de producto debe ser único e irrepetible | C6: Producto
A7: P-PRO-003 | B7: Asegurar que los datos requeridos sean válidos en tipo de dato, longitud, obligatoriedad y formato | C7: Producto

Sheet M-Departamento
A1: <<<Ir al modelo de dominio | B1: <<<Ir a objeto de dominio | C1: Ir a la caracterización>>> | D1: Ir al event storming>>> | E1: Ir a las políticas>>>
A2: Nombre: | B2: ='Objetos de Dominio'!A13 -> Departamento
A3: Descripción: | B3: ='Objetos de Dominio'!B13 -> Representa el departamento o división administrativa al que pertenece una ciudad dentro de un país.
A4: Identificador único del departamento | B4: País al que pertenece el departamento | C4: Nombre oficial del departamento que contiene las distintas sedes del negocio | D4: Combinación única que indica que no puede existir más de un departamento con el mismo nombre en un mismo país
A5: ID | B5: ='Objetos de Dominio'!A3 -> Pais | C5: Nombre | D5: PaisDepartamento
A6: 1 | B6: ='M-Pais'!B6 -> Colombia | C6: Antioquia | D6: =_xlfn.CONCAT(B6, " + ", C6) -> Colombia + Antioquia
A7: 2 | B7: ='M-Pais'!B6 -> Colombia | C7: Cundinamarca | D7: =_xlfn.CONCAT(B7, " + ", C7) -> Colombia + Cundinamarca
A8: 3 | B8: ='M-Pais'!B7 -> Ecuador | C8: Pichincha | D8: =_xlfn.CONCAT(B8, " + ", C8) -> Ecuador + Pichincha

Sheet C-Departamento
A1: <<<Ir al modelo de dominio | B1: <<<Ir a objeto de dominio | C1: <<<Ir a muestreo del objeto | D1: Ir al event storming>>> | E1: Ir a las políticas>>>
A2: Nombre | B2: ='Objetos de Dominio'!A13 -> Departamento
A3: Descripción | B3: ='Objetos de Dominio'!B13 -> Representa el departamento o división administrativa al que pertenece una ciudad dentro de un país.
A4: Nombre atributo | B4: Descripción atributo | C4: Identificador del objeto de dominio | D4: Tipo de dato | E4: Obligatorio | F4: Longitud mínima (si aplica) | G4: Longitud máxima (si aplica) | H4: Precisión (si aplica) | I4: Redondeo (si aplica) | J4: Rango inicial (si aplica) | K4: Rango final (si aplica) | L4: Formato (si aplica) | M4: Reglas especiales (si aplica) | N4: Dato calculado | O4: Aplica ajuste del dato (si aplica) | P4: Carácter de ajuste (si aplica) | Q4: Quitar espacios en blanco al inicio (si aplica) | R4: Quitar espacios en blanco al fin (si aplica) | S4: Dato sensible (si aplica) | T4: Valor por defecto (si aplica) | U4: Auto generado | V4: consultarDepartamentosPorFiltro
A5: ID | B5: ='M-Departamento'!A4 -> Identificador único del departamento | C5: Si | D5: Identificador único universal | E5: Si | F5: - | G5: - | H5: - | I5: - | J5: - | K5: - | L5: - | M5: Debe ser único y no debe repetirse en los distintos id's de los departamentos | N5: No | O5: No | P5: - | Q5: No | R5: No | S5: - | T5: - | U5: Si | V5: Filtro | W5: No Mostrar
A6: Pais | B6: ='M-Departamento'!B4 -> País al que pertenece el departamento | C6: No | D6: Pais | E6: Si | F6: - | G6: - | H6: - | I6: - | J6: - | K6: - | L6: - | M6: Aplican las reglas del objeto referenciado | N6: No | O6: No | P6: - | Q6: No | R6: No | S6: - | T6: - | U6: No | V6: Filtro | W6: Mostrar
A7: Nombre | B7: ='M-Departamento'!C4 -> Nombre oficial del departamento que contiene las distintas sedes del negocio | C7: No | D7: Alfanumérico | E7: Si | F7: 2 | G7: 100 | H7: - | I7: - | J7: - | K7: - | L7: - | M7: Se debe asegurar una sanitización del dato, para garantizar que dentro de su contenido no tenga cualquier tipo de intento de ataque | N7: No | O7: No | P7: - | Q7: Si | R7: Si | S7: - | T7: - | U7: No | V7: Filtro | W7: Mostrar
A10: Nombre combinación única | B10: Descripción | C10: Atributos involucrados
A11: ='M-Departamento'!D5 -> PaisDepartamento | B11: ='M-Departamento'!D4 -> Combinación única que indica que no puede existir más de un departamento con el mismo nombre en un mismo país | C11: Pais
C12: Nombre
A15: Responsabilidad | C15: Descripción | G15: Entradas | J15: Salida | O15: Políticas (Reglas de Negocio) | Q15: Excepción
G16: Parámetro | H16: Tipo de dato | I16: Descripción | J16: Tipo de Dato | K16: Descripción | O16: Política | P16: Descripción | Q16: Detalle | R16: ¿Qué hago?
A17: consultarDepartamentosPorFiltro | C17: Permite buscar, listar y filtrar los departamentos según los criterios de búsqueda enviados | G17: filtro | H17: Departamento | I17: Contiene los parámetros o criterios de búsqueda enviados para filtrar la consulta | J17: Lista<Departamento> | K17: Contiene la lista de departamentos que cumplen con las condiciones del filtro enviado | O17: =HYPERLINK("#'P-Departamento'!A5",'P-Departamento'!A5) -> P-DEP-001 | P17: ='P-Departamento'!B5 -> Asegurar que los datos requeridos sean válidos en tipo de dato, longitud, obligatoriedad y formato | Q17: Generar una excepción indicando que los datos requeridos son inválidos o están incompletos | R17: Detener operación

Sheet E-Departamento
A1: <<<Ir al modelo de dominio | B1: <<<Ir a objeto de dominio | C1: <<<Ir a muestreo del objeto | D1: <<<Ir a caracterización | E1: Ir a las políticas>>>
A2: Objeto de Dominio: | B2: ='Objetos de Dominio'!A13 -> Departamento
A3: Descripción: | B3: ='Objetos de Dominio'!B13 -> Representa el departamento o división administrativa al que pertenece una ciudad dentro de un país.
A4: Actor | B4: Action/Command | D4: Entity/Aggregate/Object domain | E4: Read Model | G4: Business Rule/Policy | I4: External System | J4: Domain Event | K4: Hotspot/questions/Risk
A5: Actor | B5: Acción | C5: Descripción | D5: Objeto de dominio | E5: Información externa | G5: Políticas | I5: Sistema Externo | J5: Evento | K5: Aspectos por solucionar
E6: Información | F6: Descripción | G6: Número | H6: Descripción
A7: Administrador/Vendedor | B7: Consultar departamentos por filtro | C7: Permite buscar, listar y filtrar los departamentos según los criterios de búsqueda enviados | D7: Departamento | E7: Filtros de los departamentos | F7: Contiene los parámetros o criterios de búsqueda enviados para filtrar la consulta | G7: =HYPERLINK("#'P-Departamento'!A6",'P-Departamento'!A5) -> P-DEP-001 | H7: ='P-Departamento'!B5 -> Asegurar que los datos requeridos sean válidos en tipo de dato, longitud, obligatoriedad y formato | J7: Departamentos encontrados

Sheet P-Departamento
A1: <<<Ir al modelo de dominio | B1: <<<Ir a objeto de dominio | C1: <<<Ir a muestreo del objeto | D1: <<<Ir a caracterización | E1: <<<Ir al event storming
A2: Objeto de Dominio: | B2: ='Objetos de Dominio'!A13 -> Departamento
A3: Descripción: | B3: ='Objetos de Dominio'!B13 -> Representa el departamento o división administrativa al que pertenece una ciudad dentro de un país.
A4: Número Política | B4: Descripción Política | C4: Objeto Responsable
A5: P-DEP-001 | B5: Asegurar que los datos requeridos sean válidos en tipo de dato, longitud, obligatoriedad y formato | C5: Departamento

Sheet M-ClienteRegistrado
A1: <<<Ir al modelo de dominio | B1: <<<Ir a objeto de dominio | C1: Ir al event storming>>> | D1: Ir a las políticas>>>
A2: Nombre: | B2: ='Objetos de Dominio'!A14 -> ClienteRegistrado
A3: Descripción: | B3: ='Objetos de Dominio'!B14 -> Representa al cliente cuyos datos de identificación y contacto han sido registrados en el sistema
A4: Identificador único del cliente registrado | B4: Representa a la persona cuyos datos de identificación y contacto van a ser registrados en el sistema como cliente | C4: Combinación única que indica que no puede existir más de un cliente registrado que pueda ser el mismo cliente
A5: ID | B5: Cliente | C5: ClienteRegistradoUnico
A6: 1 | B6: ='M-Cliente'!A6 -> 1 | C6: =B6 -> 1
A7: 2 | B7: ='M-Cliente'!A7 -> 2 | C7: =B7 -> 2
A8: 3 | B8: ='M-Cliente'!A8 -> 3 | C8: =B8 -> 3

Sheet C-ClienteRegistrado
A1: <<<Ir al modelo de dominio | B1: <<<Ir a objeto de dominio | C1: <<<Ir a muestreo del objeto | D1: Ir al event storming>>> | E1: Ir a las políticas>>>
A2: Nombre: | B2: ='Objetos de Dominio'!A14 -> ClienteRegistrado
A3: Descripción: | B3: ='Objetos de Dominio'!B14 -> Representa al cliente cuyos datos de identificación y contacto han sido registrados en el sistema
A4: Nombre atributo | B4: Descripción atributo | C4: Identificador del objeto de dominio | D4: Tipo de dato | E4: Obligatorio | F4: Longitud mínima (si aplica) | G4: Longitud máxima (si aplica) | H4: Precisión (si aplica) | I4: Redondeo (si aplica) | J4: Rango inicial (si aplica) | K4: Rango final (si aplica) | L4: Formato (si aplica) | M4: Reglas especiales (si aplica) | N4: Dato calculado | O4: Aplica ajuste del dato (si aplica) | P4: Carácter de ajuste (si aplica) | Q4: Quitar espacios en blanco al inicio (si aplica) | R4: Quitar espacios en blanco al fin (si aplica) | S4: Dato sensible (si aplica) | T4: Valor por defecto (si aplica) | U4: Auto generado | V4: registrarClienteRegistrado | W4: consultarClientesRegistradosPorFiltro | Y4: eliminarClienteRegistrado
A5: ID | B5: ='M-ClienteRegistrado'!A4 -> Identificador único del cliente registrado | C5: Si | D5: Identificador único universal | E5: Si | F5: - | G5: - | H5: - | I5: - | J5: - | K5: - | L5: - | M5: Debe ser único y no debe repetirse en los distintos id's de los clientes registrados | N5: No | O5: No | P5: - | Q5: No | R5: No | S5: - | T5: - | U5: Si | V5: Requerido | W5: Filtro | X5: No Mostrar | Y5: Requerido
A6: Cliente | B6: ='M-ClienteRegistrado'!B4 -> Representa a la persona cuyos datos de identificación y contacto van a ser registrados en el sistema como cliente | C6: No | D6: Cliente | E6: Si | F6: - | G6: - | H6: - | I6: - | J6: - | K6: - | L6: - | M6: Aplican las reglas del objeto referenciado | N6: No | O6: No | P6: - | Q6: No | R6: No | S6: - | T6: - | U6: No | V6: Requerido | W6: Filtro | X6: Mostrar | Y6: No requerido
A9: Nombre combinación única | B9: Descripción | C9: Atributos involucrados
A10: ='M-ClienteRegistrado'!C5 -> ClienteRegistradoUnico | B10: ='M-ClienteRegistrado'!C4 -> Combinación única que indica que no puede existir más de un cliente registrado que pueda ser el mismo cliente | C10: Cliente
A13: Responsabilidad | C13: Descripción | G13: Entradas | J13: Salida | O13: Políticas (Reglas de Negocio) | Q13: Excepción
G14: Parámetro | H14: Tipo de dato | I14: Descripción | J14: Tipo de Dato | K14: Descripción | O14: Política | P14: Descripción | Q14: Detalle | R14: ¿Qué hago?
A15: registrarClienteRegistrado | C15: Permite registrar un nuevo cliente registrado en el sistema | G15: datos | H15: ClienteRegistrado | I15: Contiene la información requerida para registrar el cliente registrado | J15: ClienteRegistrado | K15: Objeto del cliente registrado con su identificador ID asignado y el cliente correspondiente | O15: ='P-ClienteRegistrado'!A5 -> P-CLR-001 | P15: ='P-ClienteRegistrado'!B5 -> Asegurar que el id de cliente registrado debe ser único e irrepetible | Q15: Generar un nuevo identificador hasta garantizar que no exista | R15: Continuar operación
O16: ='P-ClienteRegistrado'!A6 -> P-CLR-002 | P16: ='P-ClienteRegistrado'!B6 -> Garantizar que el cliente a registrar no este asociado a más de un ClienteRegistrado ni a un ClienteNoRegistrado para evitar duplicación de clientes | Q16: Generar una excepción indicando que ese cliente ya se ha registrado en algún momento en el sistema | R16: Detener operación
O17: ='P-ClienteRegistrado'!A7 -> P-CLR-003 | P17: ='P-ClienteRegistrado'!B7 -> Asegurar que los datos requeridos sean válidos en tipo de dato, longitud, obligatoriedad y formato | Q17: Generar una excepción indicando que los datos requeridos son inválidos o están incompletos | R17: Detener operación
A18: consultarClientesRegistradosPorFiltro | C18: Permite buscar, listar y filtrar los clientes registrados según los criterios de búsqueda enviados | G18: filtro | H18: ClienteRegistrado | I18: Contiene los parámetros o criterios de búsqueda enviados para filtrar la consulta | J18: Lista<ClienteRegistrado> | K18: Contiene la lista de clientes registrados que cumplen con las condiciones del filtro enviado | O18: ='P-ClienteRegistrado'!A7 -> P-CLR-003 | P18: ='P-ClienteRegistrado'!B7 -> Asegurar que los datos requeridos sean válidos en tipo de dato, longitud, obligatoriedad y formato | Q18: Generar una excepción indicando que los datos requeridos son inválidos o están incompletos | R18: Detener operación
A19: eliminarClienteRegistrado | C19: Permite eliminar un cliente eliminando todo su historial de compras y de devoluciones, solo si el cliente registrado lo desea | G19: id | H19: UUID | I19: Contiene el identificador único del cliente que se desea eliminar | O19: =HYPERLINK("#'P-ClienteRegistrado'!A7",'P-ClienteRegistrado'!A7) -> P-CLR-003 | P19: ='P-ClienteRegistrado'!B7 -> Asegurar que los datos requeridos sean válidos en tipo de dato, longitud, obligatoriedad y formato | Q19: Generar una excepción indicando que los datos requeridos son inválidos o están incompletos | R19: Detener operación
O20: =HYPERLINK("#'P-ClienteRegistrado'!A8",'P-ClienteRegistrado'!A8) -> P-CLR-004 | P20: ='P-ClienteRegistrado'!B8 -> Asegurar que el cliente registrado no esté siendo utilizado dentro de ningún otro objeto de dominio | Q20: Generar una excepción indicando al usuario que el cliente registrado está siendo usado por otros tipos de clientes registrados | R20: Detener operación

Sheet E-ClienteRegistrado
A1: <<<Ir al modelo de dominio | B1: <<<Ir a objeto de dominio | C1: <<<Ir a muestreo del objeto | D1: <<<Ir a caracterización | E1: Ir a las políticas>>>
A2: Objeto de Dominio: | B2: ='Objetos de Dominio'!A14 -> ClienteRegistrado
A3: Descripción: | B3: ='Objetos de Dominio'!B14 -> Representa al cliente cuyos datos de identificación y contacto han sido registrados en el sistema
A4: Actor | B4: Action/Command | D4: Entity/Aggregate/Object domain | E4: Read Model | G4: Business Rule/Policy | I4: External System | J4: Domain Event | K4: Hotspot/questions/Risk
A5: Actor | B5: Acción | C5: Descripción | D5: Objeto de dominio | E5: Información externa | G5: Políticas | I5: Sistema Externo | J5: Evento | K5: Aspectos por solucionar
E6: Información | F6: Descripción | G6: Número | H6: Descripción
A7: Administrador/Vendedor | B7: Registrar un nuevo cliente registrado | C7: Permite registrar un nuevo cliente registrado en el sistema | D7: ClienteRegistrado | E7: Datos del nuevo cliente registrado | F7: Contiene la información requerida para registrar el cliente registrado | G7: =HYPERLINK("#'P-ClienteRegistrado'!A5",'P-ClienteRegistrado'!A5) -> P-CLR-001 | H7: ='P-ClienteRegistrado'!B5 -> Asegurar que el id de cliente registrado debe ser único e irrepetible | J7: Cliente registrado creado
G8: =HYPERLINK("#'P-ClienteRegistrado'!A6",'P-ClienteRegistrado'!A6) -> P-CLR-002 | H8: ='P-ClienteRegistrado'!B6 -> Garantizar que el cliente a registrar no este asociado a más de un ClienteRegistrado ni a un ClienteNoRegistrado para evitar duplicación de clientes
G9: =HYPERLINK("#'P-ClienteRegistrado'!A7",'P-ClienteRegistrado'!A7) -> P-CLR-003 | H9: ='P-ClienteRegistrado'!B7 -> Asegurar que los datos requeridos sean válidos en tipo de dato, longitud, obligatoriedad y formato
A10: Administrador/Vendedor | B10: Consultar clientes registrados por filtro | C10: Permite buscar, listar y filtrar los clientes registrados según los criterios de búsqueda enviados | D10: ClienteRegistrado | E10: Filtros del cliente registrado | F10: Contiene los parámetros o criterios de búsqueda enviados para filtrar la consulta | G10: =HYPERLINK("#'P-ClienteRegistrado'!A7",'P-ClienteRegistrado'!A7) -> P-CLR-003 | H10: ='P-ClienteRegistrado'!B7 -> Asegurar que los datos requeridos sean válidos en tipo de dato, longitud, obligatoriedad y formato | J10: Clientes registrados encontrados
A11: Administrador | B11: Eliminar un cliente registrado | C11: Permite eliminar un cliente registrado eliminando la trazabilidad de su historial | D11: ClienteRegistrado | E11: Identificador del cliente registrado | F11: Contiene el identificador único del cliente registrado que se desea eliminar | G11: =HYPERLINK("#'P-ClienteRegistrado'!A7",'P-ClienteRegistrado'!A7) -> P-CLR-003 | H11: ='P-ClienteRegistrado'!B7 -> Asegurar que los datos requeridos sean válidos en tipo de dato, longitud, obligatoriedad y formato | J11: Cliente registrado eliminado
G12: =HYPERLINK("#'P-ClienteRegistrado'!A8",'P-ClienteRegistrado'!A8) -> P-CLR-004 | H12: ='P-ClienteRegistrado'!B8 -> Asegurar que el cliente registrado no esté siendo utilizado dentro de ningún otro objeto de dominio

Sheet P-ClienteRegistrado
A1: <<<Ir al modelo de dominio | B1: <<<Ir a objeto de dominio | C1: <<<Ir a muestreo del objeto | D1: <<<Ir a caracterización | E1: <<<Ir al event storming
A2: Objeto de Dominio: | B2: ='Objetos de Dominio'!A14 -> ClienteRegistrado
A3: Descripción: | B3: ='Objetos de Dominio'!B14 -> Representa al cliente cuyos datos de identificación y contacto han sido registrados en el sistema
A4: Número Política | B4: Descripción Política | C4: Objeto Responsable
A5: P-CLR-001 | B5: Asegurar que el id de cliente registrado debe ser único e irrepetible | C5: ClienteRegistrado
A6: P-CLR-002 | B6: Garantizar que el cliente a registrar no este asociado a más de un ClienteRegistrado ni a un ClienteNoRegistrado para evitar duplicación de clientes | C6: ClienteRegistrado
A7: P-CLR-003 | B7: Asegurar que los datos requeridos sean válidos en tipo de dato, longitud, obligatoriedad y formato | C7: ClienteRegistrado
A8: P-CLR-004 | B8: Asegurar que el cliente registrado no esté siendo utilizado dentro de ningún otro objeto de dominio | C8: ClienteRegistrado

Sheet M-ClienteNoRegistrado
A1: <<<Ir al modelo de dominio | B1: <<<Ir a objeto de dominio | C1: Ir a la caracterización>>> | D1: Ir al event storming>>> | E1: Ir a las políticas>>>
A2: Nombre: | B2: ='Objetos de Dominio'!A15 -> ClienteNoRegistrado
A3: Descripción: | B3: ='Objetos de Dominio'!B15 -> Representa a la persona que realiza una compra sin contar con un registro previo en el sistema
A4: Identificador único del cliente no registrado | B4: Representa a la persona que no se desea registrar en el sistema | C4: Combinación única que indica que no puede existir más de un cliente no registrado que pueda ser el mismo cliente
A5: ID | B5: Cliente | C5: ClienteNoRegistradoUnico
A6: 1 | B6: ='M-Cliente'!A6 -> 1 | C6: =B6 -> 1
A7: 2 | B7: ='M-Cliente'!A9 -> 4 | C7: =B7 -> 4
A8: 3 | B8: ='M-Cliente'!A11 -> 6 | C8: =B8 -> 6

Sheet C-ClienteNoRegistrado
A1: <<<Ir al modelo de dominio | B1: <<<Ir a objeto de dominio | C1: <<<Ir a muestreo del objeto | D1: Ir al event storming>>> | E1: Ir a las políticas>>>
A2: Nombre | B2: ='Objetos de Dominio'!A15 -> ClienteNoRegistrado
A3: Descripción | B3: ='Objetos de Dominio'!B15 -> Representa a la persona que realiza una compra sin contar con un registro previo en el sistema
A4: Nombre atributo | B4: Descripción atributo | C4: Identificador del objeto de dominio | D4: Tipo de dato | E4: Obligatorio | F4: Longitud mínima (si aplica) | G4: Longitud máxima (si aplica) | H4: Precisión (si aplica) | I4: Redondeo (si aplica) | J4: Rango inicial (si aplica) | K4: Rango final (si aplica) | L4: Formato (si aplica) | M4: Reglas especiales (si aplica) | N4: Dato calculado | O4: Aplica ajuste del dato (si aplica) | P4: Carácter de ajuste (si aplica) | Q4: Quitar espacios en blanco al inicio (si aplica) | R4: Quitar espacios en blanco al fin (si aplica) | S4: Dato sensible (si aplica) | T4: Valor por defecto (si aplica) | U4: Auto generado | V4: registrarClienteNoRegistrado | W4: consultarClientesNoRegistradosPorFiltro
A5: ID | B5: ='M-ClienteNoRegistrado'!A4 -> Identificador único del cliente no registrado | C5: Si | D5: Identificador único universal | E5: Si | F5: - | G5: - | H5: - | I5: - | J5: - | K5: - | L5: - | M5: Debe ser único y no debe repetirse en los distintos id's de los clientes no registrados | N5: No | O5: No | P5: - | Q5: No | R5: No | S5: - | T5: - | U5: Si | V5: Requerido | W5: Filtro | X5: No Mostrar
A6: Cliente | B6: ='M-ClienteNoRegistrado'!B4 -> Representa a la persona que no se desea registrar en el sistema | C6: No | D6: Cliente | E6: Si | F6: - | G6: - | H6: - | I6: - | J6: - | K6: - | L6: - | M6: Aplican las reglas del objeto referenciado | N6: No | O6: No | P6: - | Q6: No | R6: No | S6: - | T6: - | U6: No | V6: Requerido | W6: Filtro | X6: Mostrar
A9: Nombre combinación única | B9: Descripción | C9: Atributos involucrados
A10: ='M-ClienteNoRegistrado'!C5 -> ClienteNoRegistradoUnico | B10: ='M-ClienteNoRegistrado'!C4 -> Combinación única que indica que no puede existir más de un cliente no registrado que pueda ser el mismo cliente | C10: Cliente
A14: Responsabilidad | C14: Descripción | G14: Entradas | J14: Salida | O14: Políticas (Reglas de Negocio) | Q14: Excepción
G15: Parámetro | H15: Tipo de dato | I15: Descripción | J15: Tipo de Dato | K15: Descripción | O15: Política | P15: Descripción | Q15: Detalle | R15: ¿Qué hago?
A16: registrarClienteNoRegistrado | C16: Permite registrar un nuevo cliente no registrado en el sistema | G16: datos | H16: ClienteNoRegistrado | I16: Contiene la información requerida para registrar el cliente no registrado | J16: ClienteNoRegistrado | K16: Objeto del cliente no registrado con su identificador ID asignado y su cliente correspondiente | O16: =HYPERLINK("#'P-ClienteNoRegistrado'!A5",'P-ClienteNoRegistrado'!A5) -> P-CNR-001 | P16: ='P-ClienteNoRegistrado'!B5 -> Asegurar que el id de cliente no registrado debe ser único e irrepetible | Q16: Generar un nuevo identificador hasta garantizar que no exista | R16: Continuar operación
O17: =HYPERLINK("#'P-ClienteNoRegistrado'!A6",'P-ClienteNoRegistrado'!A6) -> P-CNR-002 | P17: ='P-ClienteNoRegistrado'!B6 -> Garantizar que el cliente a registrar no este asociado a más de un ClienteRegistrado ni a un ClienteNoRegistrado para evitar duplicación de clientes | Q17: Generar una excepción indicando que ese cliente ya se ha registrado en algún momento en el sistema | R17: Detener operación
O18: =HYPERLINK("#'P-ClienteNoRegistrado'!A7",'P-ClienteNoRegistrado'!A7) -> P-CNR-003 | P18: ='P-ClienteNoRegistrado'!B7 -> Asegurar que los datos requeridos sean válidos en tipo de dato, longitud, obligatoriedad y formato | Q18: Generar una excepción indicando que los datos requeridos son inválidos o están incompletos | R18: Detener operación
A19: consultarClientesNoRegistradosPorFiltro | C19: Permite buscar, listar y filtrar los clientes no registrados según los criterios de búsqueda enviados | G19: filtro | H19: ClienteNoRegistrado | I19: Contiene los parámetros o criterios de búsqueda enviados para filtrar la consulta | J19: Lista<ClienteNoRegistrado> | K19: Contiene la lista de clientes no registrados que cumplen con las condiciones del filtro enviado | O19: =HYPERLINK("#'P-ClienteNoRegistrado'!A7",'P-ClienteNoRegistrado'!A7) -> P-CNR-003 | P19: ='P-ClienteNoRegistrado'!B7 -> Asegurar que los datos requeridos sean válidos en tipo de dato, longitud, obligatoriedad y formato | Q19: Generar una excepción indicando que los datos requeridos son inválidos o están incompletos | R19: Detener operación

Sheet E-ClienteNoRegistrado
A1: <<<Ir al modelo de dominio | B1: <<<Ir a objeto de dominio | C1: <<<Ir a muestreo del objeto | D1: <<<Ir a caracterización | E1: Ir a las políticas>>>
A2: Objeto de Dominio: | B2: ='Objetos de Dominio'!A15 -> ClienteNoRegistrado
A3: Descripción: | B3: ='Objetos de Dominio'!B15 -> Representa a la persona que realiza una compra sin contar con un registro previo en el sistema
A4: Actor | B4: Action/Command | D4: Entity/Aggregate/Object domain | E4: Read Model | G4: Business Rule/Policy | I4: External System | J4: Domain Event | K4: Hotspot/questions/Risk
A5: Actor | B5: Acción | C5: Descripción | D5: Objeto de dominio | E5: Información externa | G5: Políticas | I5: Sistema Externo | J5: Evento | K5: Aspectos por solucionar
E6: Información | F6: Descripción | G6: Número | H6: Descripción
A7: Administrador/Vendedor | B7: Registrar un nuevo cliente no registrado | C7: Permite registrar un nuevo cliente no registrado en el sistema | D7: ClienteNoRegistrado | E7: Datos del nuevo cliente no registrado | F7: Contiene la información requerida para registrar el cliente no registrado | G7: =HYPERLINK("#'P-ClienteNoRegistrado'!A5",'P-ClienteNoRegistrado'!A5) -> P-CNR-001 | H7: ='P-ClienteNoRegistrado'!B5 -> Asegurar que el id de cliente no registrado debe ser único e irrepetible | J7: Cliente no registrado creado
G8: =HYPERLINK("#'P-ClienteNoRegistrado'!A6",'P-ClienteNoRegistrado'!A6) -> P-CNR-002 | H8: ='P-ClienteNoRegistrado'!B6 -> Garantizar que el cliente a registrar no este asociado a más de un ClienteRegistrado ni a un ClienteNoRegistrado para evitar duplicación de clientes
G9: =HYPERLINK("#'P-ClienteNoRegistrado'!A7",'P-ClienteNoRegistrado'!A7) -> P-CNR-003 | H9: ='P-ClienteNoRegistrado'!B7 -> Asegurar que los datos requeridos sean válidos en tipo de dato, longitud, obligatoriedad y formato
A10: Administrador/Vendedor | B10: Consultar clientes no registrados por filtro | C10: Permite buscar, listar y filtrar los clientes no registrados según los criterios de búsqueda enviados | D10: ClienteNoRegistrado | E10: Filtros del cliente no registrado | F10: Contiene los parámetros o criterios de búsqueda enviados para filtrar la consulta | G10: =HYPERLINK("#'P-ClienteNoRegistrado'!A7",'P-ClienteNoRegistrado'!A7) -> P-CNR-003 | H10: ='P-ClienteNoRegistrado'!B7 -> Asegurar que los datos requeridos sean válidos en tipo de dato, longitud, obligatoriedad y formato | J10: Clientes no registrados encontrados

Sheet P-ClienteNoRegistrado
A1: <<<Ir al modelo de dominio | B1: <<<Ir a objeto de dominio | C1: <<<Ir a muestreo del objeto | D1: <<<Ir a caracterización | E1: <<<Ir al event storming
A2: Objeto de Dominio: | B2: ='Objetos de Dominio'!A15 -> ClienteNoRegistrado
A3: Descripción: | B3: ='Objetos de Dominio'!B15 -> Representa a la persona que realiza una compra sin contar con un registro previo en el sistema
A4: Número Política | B4: Descripción Política | C4: Objeto Responsable
A5: P-CNR-001 | B5: Asegurar que el id de cliente no registrado debe ser único e irrepetible | C5: ClienteNoRegistrado
A6: P-CNR-002 | B6: Garantizar que el cliente a registrar no este asociado a más de un ClienteRegistrado ni a un ClienteNoRegistrado para evitar duplicación de clientes | C6: ClienteNoRegistrado
A7: P-CNR-003 | B7: Asegurar que los datos requeridos sean válidos en tipo de dato, longitud, obligatoriedad y formato | C7: ClienteNoRegistrado

Sheet M-ClienteRegistradoN
A1: <<<Ir al modelo de dominio | B1: <<<Ir a objeto de dominio | C1: Ir a la caracterización>>> | D1: Ir al event storming>>> | E1: Ir a las políticas>>>
A2: Nombre: | B2: ='Objetos de Dominio'!A16 -> ClienteRegistradoN
A3: Descripción: | B3: ='Objetos de Dominio'!B16 -> Representa al cliente registrado natural en el sistema con sus datos básicos de identificación y contacto
A4: Identificador único del cliente registrado natural | B4: Referencia al cliente registrado asociado al cliente registrado natural | C4: Nombre completo de la persona asociada al cliente registrado natural | D4: Combinación única que garantiza que un mismo ClienteRegistrado no se puede asociar más de una vez a un cliente registrado natural | E4: Combinación única que representa que una misma persona no se puede asociar a más de un cliente registrado natura
A5: ID | B5: ClienteRegistrado | C5: Persona | D5: ClienteNaturalUnico | E5: PersonaNaturalUnica
A6: 1 | B6: ='M-ClienteRegistrado'!A6 -> 1 | C6: ='M-Persona'!A6 -> 1 | D6: =B6 -> 1 | E6: =C6 -> 1
A7: 2 | B7: ='M-ClienteRegistrado'!A7 -> 2 | C7: ='M-Persona'!A7 -> 2 | D7: =B7 -> 2 | E7: =C7 -> 2
A8: 3 | B8: ='M-ClienteRegistrado'!A8 -> 3 | C8: ='M-Persona'!A8 -> 3 | D8: =B8 -> 3 | E8: =C8 -> 3

Sheet C-ClienteRegistradoN
A1: <<<Ir al modelo de dominio | B1: <<<Ir a objeto de dominio | C1: <<<Ir a muestreo del objeto | D1: Ir al event storming>>> | E1: Ir a las políticas>>> | F1: <<<Ir a crud
A2: Nombre | B2: ='Objetos de Dominio'!A16 -> ClienteRegistradoN
A3: Descripción | B3: ='Objetos de Dominio'!B16 -> Representa al cliente registrado natural en el sistema con sus datos básicos de identificación y contacto
A4: Nombre atributo | B4: Descripción atributo | C4: Identificador del objeto de dominio | D4: Tipo de dato | E4: Obligatorio | F4: Longitud mínima (si aplica) | G4: Longitud máxima (si aplica) | H4: Precisión (si aplica) | I4: Redondeo (si aplica) | J4: Rango inicial (si aplica) | K4: Rango final (si aplica) | L4: Formato (si aplica) | M4: Reglas especiales (si aplica) | N4: Dato calculado | O4: Aplica ajuste del dato (si aplica) | P4: Carácter de ajuste (si aplica) | Q4: Quitar espacios en blanco al inicio (si aplica) | R4: Quitar espacios en blanco al fin (si aplica) | S4: Dato sensible (si aplica) | T4: Valor por defecto (si aplica) | U4: Auto generado | V4: registrarClienteRegistradoNatural | W4: consultarClientesRegistradosNaturalesPorFiltro | Y4: =HYPERLINK("#'C-ClienteRegistradoN'!A26","eliminarClienteRegistradoNatural") -> eliminarClienteRegistradoNatural
A5: ='M-ClienteRegistradoN'!A5 -> ID | B5: ='M-ClienteRegistradoN'!A4 -> Identificador único del cliente registrado natural | C5: Si | D5: Identificador único universal | E5: Si | F5: - | G5: - | H5: - | I5: - | J5: - | K5: - | L5: - | M5: Debe ser único y no debe repetirse en los distintos id's de los clientes registrados naturales | N5: No | O5: No | P5: - | Q5: No | R5: No | S5: - | T5: - | U5: Si | V5: Requerido | W5: Filtro | X5: No Mostrar | Y5: Requerido
A6: ='M-ClienteRegistradoN'!B5 -> ClienteRegistrado | B6: ='M-ClienteRegistradoN'!B4 -> Referencia al cliente registrado asociado al cliente registrado natural | C6: No | D6: ClienteRegistrado | E6: Si | F6: - | G6: - | H6: - | I6: - | J6: - | K6: - | L6: - | M6: Aplican las reglas del objeto referenciado | N6: No | O6: No | P6: - | Q6: No | R6: No | S6: - | T6: - | U6: No | V6: Requerido | W6: Filtro | X6: Mostrar | Y6: No requerido
A7: ='M-ClienteRegistradoN'!C5 -> Persona | B7: ='M-ClienteRegistradoN'!C4 -> Nombre completo de la persona asociada al cliente registrado natural | C7: No | D7: Persona | E7: Si | F7: - | G7: - | H7: - | I7: - | J7: - | K7: - | L7: - | M7: Aplican las reglas del objeto referenciado | N7: No | O7: No | P7: - | Q7: No | R7: No | S7: - | T7: - | U7: No | V7: Requerido | W7: Filtro | X7: Mostrar | Y7: No requerido
A10: Nombre combinación única | B10: Descripción | C10: Atributos involucrados
A11: ='M-ClienteRegistradoN'!D5 -> ClienteNaturalUnico | B11: ='M-ClienteRegistradoN'!D4 -> Combinación única que garantiza que un mismo ClienteRegistrado no se puede asociar más de una vez a un cliente registrado natural | C11: ClienteRegistrado
A12: ='M-ClienteRegistradoN'!E5 -> PersonaNaturalUnica | B12: ='M-ClienteRegistradoN'!E4 -> Combinación única que representa que una misma persona no se puede asociar a más de un cliente registrado natura | C12: Persona
A16: Responsabilidad | C16: Descripción | G16: Entradas | J16: Salida | O16: Políticas (Reglas de Negocio) | Q16: Excepción
G17: Parámetro | H17: Tipo de dato | I17: Descripción | J17: Tipo de Dato | K17: Descripción | O17: Política | P17: Descripción | Q17: Detalle | R17: ¿Qué hago?
A18: registrarClienteRegistradoNatural | C18: Permite registrar un nuevo cliente registrado natural en el sistema | G18: datos | H18: ClienteRegistradoNatural | I18: Contiene la información requerida para registrar el cliente registrado natural correspondiente | J18: ClienteRegistradoNatural | K18: Objeto del cliente registrado natural con su identificador ID y las referencias a ClienteRegistrado y Persona | O18: =HYPERLINK("#'P-ClienteRegistradoN'!A5",'P-ClienteRegistradoN'!A5) -> P-CRN-001 | P18: ='P-ClienteRegistradoN'!B5 -> Asegurar que el id del cliente registrado natural sea único e irrepetible | Q18: Generar un nuevo identificador hasta garantizar que no exista | R18: Continuar operación
O19: =HYPERLINK("#'P-ClienteRegistradoN'!A6",'P-ClienteRegistradoN'!A6) -> P-CRN-002 | P19: ='P-ClienteRegistradoN'!B6 -> El sistema debe garantizar que un mismo cliente registrado no este asociado a más de un ClienteRegistradoNatural ni a un ClienteRegistradoJuridico para evitar duplicación de clientes registrados | Q19: Generar una excepción indicando que ya existe un cliente registrado natural o jurídico que se ha asociado a ese mismo ClienteRegistrado | R19: Detener operación
O20: P-CRN-003 | P20: ='P-ClienteRegistradoN'!B7 -> El sistema debe garantizar que una misma persona no esté asociada a más de un ClienteRegistradoNatural ni un empleado para evitar duplicación de personas | Q20: Generar una excepción indicando que la persona ya se encuentra asociada a otro cliente registrado natural o empleado | R20: Detener operación
O21: =HYPERLINK("#'P-ClienteRegistradoN'!A8",'P-ClienteRegistradoN'!A8) -> P-CRN-004 | P21: ='P-ClienteRegistradoN'!B8 -> Asegurar que los datos requeridos sean válidos en tipo de dato, longitud, obligatoriedad y formato | Q21: Generar una excepción indicando que los datos requeridos son inválidos o están incompletos | R21: Detener operación
A22: consultarClientesRegistradosNaturalesPorFiltro | C22: Permite buscar, listar y filtrar los clientes registrados naturales según los criterios de búsqueda enviados | G22: filtro | H22: ClienteRegistradoNatural | I22: Contiene los parámetros o criterios de búsqueda enviados para filtrar la consulta | J22: Lista<ClienteRegistradoNatural> | K22: Contiene la lista de los clientes registrados naturales que cumplen con las condiciones del filtro enviado | O22: =HYPERLINK("#'P-ClienteRegistradoN'!A8",'P-ClienteRegistradoN'!A8) -> P-CRN-004 | P22: ='P-ClienteRegistradoN'!B8 -> Asegurar que los datos requeridos sean válidos en tipo de dato, longitud, obligatoriedad y formato | Q22: Generar una excepción indicando que los datos requeridos son inválidos o están incompletos | R22: Detener operación
A23: eliminarClienteRegistradoNatural | C23: Permite eliminar un cliente registrado natural eliminando la trazabilidad de su historial, solo si el cliente lo desea | G23: id | H23: UUID | I23: Contiene el identificador único del cliente registrado natural que se desea eliminar | O23: =HYPERLINK("#'P-ClienteRegistradoN'!A8",'P-ClienteRegistradoN'!A8) -> P-CRN-004 | P23: ='P-ClienteRegistradoN'!B8 -> Asegurar que los datos requeridos sean válidos en tipo de dato, longitud, obligatoriedad y formato | Q23: Generar una excepción indicando que los datos requeridos son inválidos o están incompletos | R23: Detener operación
O24: ='P-ClienteRegistradoN'!A9 -> P-CRN-005 | P24: ='P-ClienteRegistradoN'!B9 -> Asegurar que cliente no este realizando algún proceso o transacción de compra en el momento de la eliminación | Q24: Generar una exepción indicando que el cliente se encuentra realizando una transacción importante en el momento, por lo que es imposible eliminarlo instantáneamente | R24: Detener operación

Sheet E-ClienteRegistradoN
A1: <<<Ir al modelo de dominio | B1: <<<Ir a objeto de dominio | C1: <<<Ir a muestreo del objeto | D1: <<<Ir a caracterización | E1: Ir a las políticas>>>
A2: Objeto de Dominio: | B2: ClienteRegistradoN
A3: Descripción: | B3: Representa al cliente registrado natural en el sistema con sus datos básicos de identificación y contacto
A4: Actor | B4: Action/Command | D4: Entity/Aggregate/Object domain | E4: Read Model | G4: Business Rule/Policy | I4: External System | J4: Domain Event | K4: Hotspot/questions/Risk
A5: Actor | B5: Acción | C5: Descripción | D5: Objeto de dominio | E5: Información externa | G5: Políticas | I5: Sistema Externo | J5: Evento | K5: Aspectos por solucionar
E6: Información | F6: Descripción | G6: Número | H6: Descripción
A7: Administrador/Vendedor | B7: Registrar un nuevo cliente registrado natural | C7: Permite registrar un nuevo cliente registrado natural en el sistema | D7: ClienteRegistradoNatural | E7: Datos del nuevo cliente registrado natural | F7: Contiene la información requerida para registrar un nuevo cliente registrado natural en el sistema | G7: ='P-ClienteRegistradoN'!A5 -> P-CRN-001 | H7: ='P-ClienteRegistradoN'!B5 -> Asegurar que el id del cliente registrado natural sea único e irrepetible | J7: Cliente registrado natural creado
G8: ='P-ClienteRegistradoN'!A6 -> P-CRN-002 | H8: ='P-ClienteRegistradoN'!B6 -> El sistema debe garantizar que un mismo cliente registrado no este asociado a más de un ClienteRegistradoNatural ni a un ClienteRegistradoJuridico para evitar duplicación de clientes registrados
G9: ='P-ClienteRegistradoN'!A7 -> P-CRN-003 | H9: ='P-ClienteRegistradoN'!B7 -> El sistema debe garantizar que una misma persona no esté asociada a más de un ClienteRegistradoNatural ni un empleado para evitar duplicación de personas
G10: ='P-ClienteRegistradoN'!A8 -> P-CRN-004 | H10: ='P-ClienteRegistradoN'!B8 -> Asegurar que los datos requeridos sean válidos en tipo de dato, longitud, obligatoriedad y formato
A11: Administrador/Vendedor | B11: Consultar clientes registrados naturales por filtro | C11: Permite buscar, listar y filtrar los clientes registrados naturales según los criterios de búsqueda enviados | D11: ClienteRegistradoNatural | E11: Filtros de cliente registrado natural | F11: Contiene los parámetros o criterios de búsqueda enviados para filtrar la consulta | G11: ='P-ClienteRegistradoN'!A8 -> P-CRN-004 | H11: ='P-ClienteRegistradoN'!B8 -> Asegurar que los datos requeridos sean válidos en tipo de dato, longitud, obligatoriedad y formato | J11: Clientes registrados naturales encontrados
A12: Administrador | B12: Eliminar un cliente registrado natural | C12: Permite eliminar un cliente registrado natural eliminando la trazabilidad de su historial, solo si el cliente lo desea | D12: ClienteRegistradoNatural | E12: Identificador del cliente registrado natural a eliminar | F12: Contiene el identificador único del cliente registrado natural que se desea eliminar | G12: ='P-ClienteRegistradoN'!A8 -> P-CRN-004 | H12: ='P-ClienteRegistradoN'!B8 -> Asegurar que los datos requeridos sean válidos en tipo de dato, longitud, obligatoriedad y formato | J12: Cliente registrado natural eliminado
G13: ='P-ClienteRegistradoN'!A9 -> P-CRN-005 | H13: ='P-ClienteRegistradoN'!B9 -> Asegurar que cliente no este realizando algún proceso o transacción de compra en el momento de la eliminación

Sheet P-ClienteRegistradoN
A1: <<<Ir al modelo de dominio | B1: <<<Ir a objeto de dominio | C1: <<<Ir a muestreo del objeto | D1: <<<Ir a caracterización | E1: <<<Ir al event storming | F1: <<<Ir a crud
A2: Objeto de Dominio: | B2: ='Objetos de Dominio'!A16 -> ClienteRegistradoN
A3: Descripción: | B3: ='Objetos de Dominio'!B16 -> Representa al cliente registrado natural en el sistema con sus datos básicos de identificación y contacto
A4: Número Política | B4: Descripción Política | C4: Objeto Responsable
A5: P-CRN-001 | B5: Asegurar que el id del cliente registrado natural sea único e irrepetible | C5: ClienteRegistradoNatural
A6: P-CRN-002 | B6: El sistema debe garantizar que un mismo cliente registrado no este asociado a más de un ClienteRegistradoNatural ni a un ClienteRegistradoJuridico para evitar duplicación de clientes registrados | C6: ClienteRegistradoNatural
A7: P-CRN-003 | B7: El sistema debe garantizar que una misma persona no esté asociada a más de un ClienteRegistradoNatural ni un empleado para evitar duplicación de personas | C7: ClienteRegistradoNatural
A8: P-CRN-004 | B8: Asegurar que los datos requeridos sean válidos en tipo de dato, longitud, obligatoriedad y formato | C8: ClienteRegistradoNatural
A9: P-CRN-005 | B9: Asegurar que cliente no este realizando algún proceso o transacción de compra en el momento de la eliminación | C9: ClienteRegistradoNatural

Sheet M-ClienteRegistradoJ
A1: <<<Ir al modelo de dominio | B1: <<<Ir a objeto de dominio | C1: Ir a la caracterización>>> | D1: Ir al event storming>>> | E1: Ir a las políticas>>>
A2: Nombre: | B2: ='Objetos de Dominio'!A17 -> ClienteRegistradoJ
A3: Descripción: | B3: ='Objetos de Dominio'!B17 -> Representa al cliente registrado Jurídico en el sistema con sus datos básicos de identificación y contacto
A4: Identificador único del cliente registrado jurídico | B4: Representa al cliente registrado asociado al cliente registrado jurídico | C4: Representa el código indicativo internacional de marcado telefónico | D4: Número de contacto de un cliente registrado jurídico | E4: Representa el número del documento de un cliente registrado jurídico | F4: Representa el nombre de un cliente registrado jurídico | G4: Correo electrónico de un cliente registrado jurídico | H4: Variable booleana que define si el teléfono de un cliente registrado jurídico específico está confirmado o no | I4: Variable booleana que define si un correo de un cliente registrado jurídico específico está confirmado o no | J4: Combinación única que indica que no puede existir más de un cliente registrado jurídico con el mismo teléfono | K4: Combinación única que indica que no puede existir más de un cliente registrado jurídico con el mismo NIT | L4: Combinación única que indica que no puede exisitir más de un cliente registrado jurídico con la misma razón social | M4: Combinación única que indica que no puede existir más de un cliente registrado jurídico con el mismo correo | N4: Combinación única que garantiza que un mismo ClienteRegistrado no se puede asociar más de una vez a un cliente registrado jurídico
A5: ID | B5: ClienteRegistrado | C5: Prefijo | D5: Telefono | E5: NIT | F5: RazónSocial | G5: Correo | H5: TelefonoConfirmado | I5: CorreoConfirmado | J5: TelefonoJuridicoUnico | K5: NitJuridicoUnico | L5: RazonSocialUnica | M5: CorreoJuridicoUnico | N5: ClienteJuridicoUnico
A6: 1 | B6: ='M-ClienteRegistrado'!A6 -> 1 | C6: ='M-Prefijo'!C6 -> +57 | D6: 3001234568 | E6: 988456256-8 | F6: Agricultura SAS | G6: agriculturasas@gmail.com | H6: SI | I6: NO | J6: =D6 -> 3001234568 | K6: =E6 -> 988456256-8 | L6: =F6 -> Agricultura SAS | M6: =G6 -> agriculturasas@gmail.com | N6: =L6 -> Agricultura SAS
A7: 2 | B7: ='M-ClienteRegistrado'!A7 -> 2 | C7: ='M-Prefijo'!C7 -> +32 | D7: 3001234569 | E7: 904154456-7 | F7: Sayonara SAS | G7: Sayonarasas@gmail.com | H7: SI | I7: SI | J7: =D7 -> 3001234569 | K7: =E7 -> 904154456-7 | L7: =F7 -> Sayonara SAS | M7: =G7 -> Sayonarasas@gmail.com | N7: =L7 -> Sayonara SAS
A8: 3 | B8: ='M-ClienteRegistrado'!A8 -> 3 | C8: ='M-Prefijo'!C8 -> +1 | D8: 3001234571 | E8: 900123456-9 | F8: Telcel SOS | G8: Telcelsos@gmail.com | H8: NO | I8: SI | J8: =D8 -> 3001234571 | K8: =E8 -> 900123456-9 | L8: =F8 -> Telcel SOS | M8: =G8 -> Telcelsos@gmail.com | N8: =L8 -> Telcel SOS

Sheet C-ClienteRegistradoJ
A1: <<<Ir al modelo de dominio | B1: <<<Ir a objeto de dominio | C1: <<<Ir a muestreo del objeto | D1: Ir al event storming>>> | E1: Ir a las políticas>>> | G1: <<<Ir a crud
A2: Nombre | B2: ='Objetos de Dominio'!A17 -> ClienteRegistradoJ
A3: Descripción | B3: ='Objetos de Dominio'!B17 -> Representa al cliente registrado Jurídico en el sistema con sus datos básicos de identificación y contacto
A4: Nombre atributo | B4: Descripción atributo | C4: Identificador del objeto de dominio | D4: Tipo de dato | E4: Obligatorio | F4: Longitud mínima (si aplica) | G4: Longitud mínima (si aplica) | H4: Longitud máxima (si aplica) | I4: Precisión (si aplica) | J4: Redondeo (si aplica) | K4: Rango inicial (si aplica) | L4: Rango final (si aplica) | M4: Formato (si aplica) | N4: Reglas especiales (si aplica) | O4: Dato calculado | P4: Aplica ajuste del dato (si aplica) | Q4: Carácter de ajuste (si aplica) | R4: Quitar espacios en blanco al inicio (si aplica) | S4: Quitar espacios en blanco al fin (si aplica) | T4: Dato sensible (si aplica) | U4: Valor por defecto (si aplica) | V4: Auto generado | W4: =HYPERLINK("#'C-ClienteRegistradoJ'!A27","registrarClienteRegistradoJuridico") -> registrarClienteRegistradoJuridico | X4: =HYPERLINK("#'C-ClienteRegistradoJ'!A34","consultarClientesRegistradosJuridicosPorFiltro") -> consultarClientesRegistradosJuridicosPorFiltro | Z4: =HYPERLINK("#'C-ClienteRegistradoJ'!A37","modificarClienteRegistradoJuridico") -> modificarClienteRegistradoJuridico | AB4: =HYPERLINK("#'C-ClienteRegistradoJ'!A40","eliminarClienteRegistradoJuridico") -> eliminarClienteRegistradoJuridico
A5: ='M-ClienteRegistradoJ'!A5 -> ID | B5: ='M-ClienteRegistradoJ'!A4 -> Identificador único del cliente registrado jurídico | C5: Si | D5: Identificador único universal | E5: Si | F5: - | G5: - | H5: - | I5: - | J5: - | K5: - | L5: - | M5: - | N5: Debe ser único y no debe repetirse en los distintos id's de los clientes registrados jurídicos | O5: No | P5: No | Q5: - | R5: No | S5: No | T5: - | U5: - | V5: Si | W5: Requerido | X5: Filtro | Y5: No Mostrar | Z5: Requerido | AA5: No modificable | AB5: Requerido
A6: ='M-ClienteRegistradoN'!B5 -> ClienteRegistrado | B6: ='M-ClienteRegistradoJ'!B4 -> Representa al cliente registrado asociado al cliente registrado jurídico | C6: No | D6: ClienteRegistrado | E6: Si | F6: - | G6: - | H6: - | I6: - | J6: - | K6: - | L6: - | M6: - | N6: Aplican las reglas del objeto referenciado | O6: No | P6: No | Q6: - | R6: No | S6: No | T6: - | U6: - | V6: No | W6: Requerido | X6: Filtro | Y6: Mostrar | Z6: No Requerido | AA6: No modificable | AB6: No requerido
A7: Prefijo | B7: ='M-ClienteRegistradoJ'!D4 -> Número de contacto de un cliente registrado jurídico | C7: No | D7: Prefijo | E7: Si | F7: - | G7: - | H7: - | I7: - | J7: - | K7: - | L7: - | M7: - | N7: Aplican las reglas del objeto referenciado | O7: No | P7: No | Q7: - | R7: No | S7: No | T7: - | U7: - | V7: No | W7: Requerido | X7: No filtro | Y7: Mostrar | Z7: No requerido | AA7: Modificable | AB7: No requerido
A8: ='M-ClienteRegistradoJ'!D5 -> Telefono | B8: ='M-ClienteRegistradoJ'!D4 -> Número de contacto de un cliente registrado jurídico | C8: No | D8: Alfanumérico | E8: Si | F8: 7 | G8: 7 | H8: 15 | I8: - | J8: - | K8: - | L8: - | M8: Formato de número telefónico correspondiente válido (+57) 3158185857 | N8: Se debe asegurar una sanitización del dato, para garantizar que dentro de su contenido no tenga cualquier tipo de intento de ataque, solo se aceptan dígitos | O8: No | P8: No | Q8: - | R8: Si | S8: Si | T8: Si | U8: - | V8: No | W8: Requerido | X8: Filtro | Y8: Mostrar | Z8: No requerido | AA8: Modificable | AB8: No requerido
A9: ='M-ClienteRegistradoJ'!E5 -> NIT | B9: ='M-ClienteRegistradoJ'!E4 -> Representa el número del documento de un cliente registrado jurídico | C9: No | D9: Alfanumérico | E9: Si | F9: 6 | G9: 3 | H9: 20 | I9: - | J9: - | K9: - | L9: - | M9: Formato de NIT correspondiente válido 903276582-1 | N9: Se debe asegurar una sanitización del dato, para garantizar que dentro de su contenido no tenga cualquier tipo de intento de ataque | O9: No | P9: No | Q9: - | R9: Si | S9: Si | T9: - | U9: - | V9: No | W9: Requerido | X9: Filtro | Y9: Mostrar | Z9: No requerido | AA9: No Modificable | AB9: No requerido
A10: ='M-ClienteRegistradoJ'!F5 -> RazónSocial | B10: ='M-ClienteRegistradoJ'!F4 -> Representa el nombre de un cliente registrado jurídico | C10: No | D10: Alfanumérico | E10: Si | F10: 2 | G10: 7 | H10: 50 | I10: - | J10: - | K10: - | L10: - | M10: - | N10: Se debe asegurar una sanitización del dato, para garantizar que dentro de su contenido no tenga cualquier tipo de intento de ataque, debe corresponder a la razón social del nit respectivo del cliente jurídico | O10: No | P10: No | Q10: - | R10: Si | S10: Si | T10: - | U10: - | V10: No | W10: Requerido | X10: Filtro | Y10: Mostrar | Z10: No requerido | AA10: Modificable | AB10: No requerido
A11: ='M-ClienteRegistradoJ'!G5 -> Correo | B11: ='M-ClienteRegistradoJ'!G4 -> Correo electrónico de un cliente registrado jurídico | C11: No | D11: Alfanumérico | E11: Si | F11: 6 | G11: 2 | H11: 254 | I11: - | J11: - | K11: - | L11: - | M11: Formato valido de correo electrónico Saraitelsas@gmail.com | N11: Se debe asegurar una sanitización del dato, para garantizar que dentro de su contenido no tenga cualquier tipo de intento de ataque | O11: No | P11: No | Q11: - | R11: Si | S11: Si | T11: Si | U11: - | V11: No | W11: Requerido | X11: Filtro | Y11: Mostrar | Z11: No requerido | AA11: Modificable | AB11: No requerido
A12: CorreoConfirmado | B12: ='M-ClienteRegistradoJ'!I4 -> Variable booleana que define si un correo de un cliente registrado jurídico específico está confirmado o no | C12: No | D12: Lógico | E12: Si | F12: - | G12: - | H12: - | I12: - | J12: - | K12: - | L12: - | M12: - | N12: Solo admite SI o NO, pasa a SI únicamente tras validar el correo con el cliente o empleado, por medio de un mensaje o un vinculo | O12: No | P12: No | Q12: - | R12: No | S12: No | T12: - | U12: No | V12: Si | W12: No Requerido | X12: No filtro | Y12: No Mostrar | Z12: No requerido | AA12: No modificable | AB12: No requerido
A13: TelefonoConfirmado | B13: ='M-ClienteRegistradoJ'!J4 -> Combinación única que indica que no puede existir más de un cliente registrado jurídico con el mismo teléfono | C13: No | D13: Lógico | E13: Si | F13: - | G13: - | H13: - | I13: - | J13: - | K13: - | L13: - | M13: - | N13: Solo admite SI o NO; pasa a SI únicamente tras validar el teléfono con el cliente o empleado, por medio de un mensaje o un vinculo | O13: No | P13: No | Q13: - | R13: No | S13: No | T13: - | U13: No | V13: Si | W13: No Requerido | X13: No Filtro | Y13: No Mostrar | Z13: No requerido | AA13: No modificable | AB13: No requerido
A16: Nombre combinación única | B16: Descripción | C16: Atributos involucrados
A17: ='M-ClienteRegistradoJ'!J5 -> TelefonoJuridicoUnico | B17: ='M-ClienteRegistradoJ'!J4 -> Combinación única que indica que no puede existir más de un cliente registrado jurídico con el mismo teléfono | C17: =A8 -> Telefono
A18: ='M-ClienteRegistradoJ'!K5 -> NitJuridicoUnico | B18: ='M-ClienteRegistradoJ'!K4 -> Combinación única que indica que no puede existir más de un cliente registrado jurídico con el mismo NIT | C18: =A9 -> NIT
A19: ='M-ClienteRegistradoJ'!L5 -> RazonSocialUnica | B19: ='M-ClienteRegistradoJ'!L4 -> Combinación única que indica que no puede exisitir más de un cliente registrado jurídico con la misma razón social | C19: =A10 -> RazónSocial
A20: ='M-ClienteRegistradoJ'!M5 -> CorreoJuridicoUnico | B20: ='M-ClienteRegistradoJ'!M4 -> Combinación única que indica que no puede existir más de un cliente registrado jurídico con el mismo correo | C20: =A11 -> Correo
A21: ='M-ClienteRegistradoJ'!N5 -> ClienteJuridicoUnico | B21: ='M-ClienteRegistradoJ'!N4 -> Combinación única que garantiza que un mismo ClienteRegistrado no se puede asociar más de una vez a un cliente registrado jurídico | C21: ClienteRegistrado
A25: Responsabilidad | C25: Descripción | H25: Entradas | K25: Salida | P25: Políticas (Reglas de Negocio) | R25: Excepción
H26: Parámetro | I26: Tipo de dato | J26: Descripción | K26: Tipo de Dato | L26: Descripción | P26: Política | Q26: Descripción | R26: Detalle | S26: ¿Qué hago?
A27: =HYPERLINK("#'C-ClienteRegistradoJ'!W4","registrarClienteRegistradoJuridico") -> registrarClienteRegistradoJuridico | C27: Permite registrar un nuevo cliente registrado jurídico en el sistema | H27: datos | I27: ClienteRegistradoJuridico | J27: Contiene la información requerida para registrar el cliente registrado jurídico correspondiente | K27: ClienteRegistradoJuridico | L27: Objeto del cliente registrado jurídico con su identificador ID asignado, nombre, apellido, teléfono y demás atributos | P27: =HYPERLINK("#'P-ClienteRegistradoJ'!A5",'P-ClienteRegistradoJ'!A5) -> P-CRJ-001 | Q27: ='P-ClienteRegistradoJ'!B5 -> Asegurar que el id del cliente registrado jurídico sea único e irrepetible | R27: Generar un nuevo identificador hasta garantizar que no exista | S27: Continuar operación
P28: =HYPERLINK("#'P-ClienteRegistradoJ'!A6",'P-ClienteRegistradoJ'!A6) -> P-CRJ-002 | Q28: ='P-ClienteRegistradoJ'!B6 -> Asegurar que el campo NIT del cliente registrado jurídico sea único e irrepetible | R28: Generar una excepción indicando que ya existe un cliente registrado con ese mismo Documento | S28: Detener operación
P29: =HYPERLINK("#'P-ClienteRegistradoJ'!A7",'P-ClienteRegistradoJ'!A7) -> P-CRJ-003 | Q29: ='P-ClienteRegistradoJ'!B7 -> Asegurar que el campo Telefono del cliente registrado jurídico sea único e irrepetible | R29: Generar una excepción indicando que ya existe un cliente registrado con ese mismo Telefono | S29: Detener operación
P30: =HYPERLINK("#'P-ClienteRegistradoJ'!A8",'P-ClienteRegistradoJ'!A8) -> P-CRJ-004 | Q30: ='P-ClienteRegistradoJ'!B8 -> Asegurar que el campo Correo del cliente registrado jurídico sea único e irrepetible | R30: Generar una excepción indicando que ya existe un cliente registrado con ese mismo Correo | S30: Detener operación
P31: =HYPERLINK("#'P-ClienteRegistradoJ'!A9",'P-ClienteRegistradoJ'!A9) -> P-CRJ-005 | Q31: ='P-ClienteRegistradoJ'!B9 -> Asegurar que el campo RazonSocial del cliente registrado jurídico sea único e irrepetible | R31: Generar una excepción indicando que ya existe un cliente registrado con esa misma Razon social | S31: Detener operación
P32: =HYPERLINK("#'P-ClienteRegistradoJ'!A10",'P-ClienteRegistradoJ'!A10) -> P-CRJ-006 | Q32: ='P-ClienteRegistradoJ'!B10 -> Garantizar que el sistema debe validar que un mismo cliente registrado no esté asociado a más de un ClienteRegistradoNatural ni a un ClienteRegistradoJuridico | R32: Generar una excepción indicando que ya existe un cliente registrado natural o jurídico que se ha asociado a ese mismo ClienteRegistrado | S32: Detener operación
P33: =HYPERLINK("#'P-ClienteRegistradoJ'!A11",'P-ClienteRegistradoJ'!A11) -> P-CRJ-007 | Q33: ='P-ClienteRegistradoJ'!B11 -> Asegurar que los datos requeridos sean válidos en tipo de dato, longitud, obligatoriedad y formato | R33: Generar una excepción indicando que los datos requeridos son inválidos o están incompletos | S33: Detener operación
A34: =HYPERLINK("#'C-ClienteRegistradoJ'!X4","consultarClientesRegistradosJuridicosPorFiltro") -> consultarClientesRegistradosJuridicosPorFiltro | C34: Permite buscar, listar y filtrar los clientes registrados jurídicos según los criterios de búsqueda enviados | H34: filtro | I34: ClienteRegistradoJuridico | J34: Contiene los parámetros o criterios de búsqueda enviados para filtrar la consulta | K34: Lista<ClienteRegistradoJuridico> | L34: Contiene la lista de los clientes registrados jurídicos que cumplen con las condiciones del filtro enviado | P34: =HYPERLINK("#'P-ClienteRegistradoJ'!A11",'P-ClienteRegistradoJ'!A11) -> P-CRJ-007 | Q34: ='P-ClienteRegistradoJ'!B11 -> Asegurar que los datos requeridos sean válidos en tipo de dato, longitud, obligatoriedad y formato | R34: Generar una excepción indicando que los datos requeridos son inválidos o están incompletos | S34: Detener operación
A35: modificarClienteRegistradoJuridico | C35: Permite actualizar la información de un cliente registrado jurídico existente | H35: id | I35: UUID | J35: Tiene el identificador único del cliente registrado jurídico a modificar y la nueva información | K35: ClienteRegistradoJuridico | L35: Objeto del cliente registrado jurídico con su información actualizada | P35: =HYPERLINK("#'P-ClienteRegistradoJ'!A7",'P-ClienteRegistradoJ'!A7) -> P-CRJ-003 | Q35: ='P-ClienteRegistradoJ'!B7 -> Asegurar que el campo Telefono del cliente registrado jurídico sea único e irrepetible | R35: Generar una excepción indicando que ya existe un cliente registrado con ese mismo Telefono | S35: Detener operación
H36: datos | I36: ClienteRegistradoJuridico | P36: =HYPERLINK("#'P-ClienteRegistradoJ'!A8",'P-ClienteRegistradoJ'!A8) -> P-CRJ-004 | Q36: ='P-ClienteRegistradoJ'!B8 -> Asegurar que el campo Correo del cliente registrado jurídico sea único e irrepetible | R36: Generar una excepción indicando que ya existe un cliente registrado con ese mismo Correo | S36: Detener operación
P37: =HYPERLINK("#'P-ClienteRegistradoJ'!A9",'P-ClienteRegistradoJ'!A9) -> P-CRJ-005 | Q37: ='P-ClienteRegistradoJ'!B9 -> Asegurar que el campo RazonSocial del cliente registrado jurídico sea único e irrepetible | R37: Generar una excepción indicando que ya existe un cliente registrado con esa misma Razon social | S37: Detener operación
P38: =HYPERLINK("#'P-ClienteRegistradoJ'!A11",'P-ClienteRegistradoJ'!A11) -> P-CRJ-007 | Q38: ='P-ClienteRegistradoJ'!B11 -> Asegurar que los datos requeridos sean válidos en tipo de dato, longitud, obligatoriedad y formato | R38: Generar una excepción indicando que el cliente registrado no existe o no puede ser modificado | S38: Detener operación
A39: =HYPERLINK("#'C-ClienteRegistradoJ'!AB4","eliminarClienteRegistradoJuridico") -> eliminarClienteRegistradoJuridico | C39: Permite eliminar un cliente registrado jurídico eliminando la trazabilidad de su historial | H39: id | I39: UUID | J39: Contiene el identificador único del cliente registrado jurídico que se desea eliminar | P39: =HYPERLINK("#'P-ClienteRegistradoJ'!A11",'P-ClienteRegistradoJ'!A11) -> P-CRJ-007 | Q39: ='P-ClienteRegistradoJ'!B11 -> Asegurar que los datos requeridos sean válidos en tipo de dato, longitud, obligatoriedad y formato | R39: Generar una excepción indicando que los datos requeridos son inválidos o están incompletos | S39: Detener operación
P40: =HYPERLINK("#'P-ClienteRegistradoJ'!A12",'P-ClienteRegistradoJ'!A12) -> P-CRJ-008 | Q40: ='P-ClienteRegistradoJ'!B12 -> Asegurar que cliente no este realizando algún proceso o transacción de compra en el momento de la eliminación | R40: Generar una exepción indicando que el cliente se encuentra realizando una transacción importante en el momento, por lo que es imposible eliminarlo instantáneamente | S40: Detener operación

Sheet E-ClienteRegistradoJ
A1: <<<Ir al modelo de dominio | B1: <<<Ir a objeto de dominio | C1: <<<Ir a muestreo del objeto | D1: <<<Ir a caracterización | E1: Ir a las políticas>>>
A2: Objeto de Dominio: | B2: ='Objetos de Dominio'!A17 -> ClienteRegistradoJ
A3: Descripción: | B3: ='Objetos de Dominio'!B17 -> Representa al cliente registrado Jurídico en el sistema con sus datos básicos de identificación y contacto
A4: Actor | B4: Action/Command | D4: Entity/Aggregate/Object domain | E4: Read Model | G4: Business Rule/Policy | I4: External System | J4: Domain Event | K4: Hotspot/questions/Risk
A5: Actor | B5: Acción | C5: Descripción | D5: Objeto de dominio | E5: Información externa | G5: Políticas | I5: Sistema Externo | J5: Evento | K5: Aspectos por solucionar
E6: Información | F6: Descripción | G6: Número | H6: Descripción
A7: Vendedor | B7: Registrar un nuevo cliente registrado jurídico | C7: Permite registrar un nuevo cliente registrado jurídico en el sistema | D7: ClienteRegistradoJuridico | E7: Datos del nuevo cliente registrado jurídico | F7: Contiene la información requerida para registrar un nuevo cliente registrado jurídico en el sistema | G7: ='P-ClienteRegistradoJ'!A5 -> P-CRJ-001 | H7: ='P-ClienteRegistradoJ'!B5 -> Asegurar que el id del cliente registrado jurídico sea único e irrepetible | J7: Cliente registrado jurídico creado
G8: ='P-ClienteRegistradoJ'!A6 -> P-CRJ-002 | H8: ='P-ClienteRegistradoJ'!B6 -> Asegurar que el campo NIT del cliente registrado jurídico sea único e irrepetible
G9: ='P-ClienteRegistradoJ'!A7 -> P-CRJ-003 | H9: ='P-ClienteRegistradoJ'!B7 -> Asegurar que el campo Telefono del cliente registrado jurídico sea único e irrepetible
G10: ='P-ClienteRegistradoJ'!A8 -> P-CRJ-004 | H10: ='P-ClienteRegistradoJ'!B8 -> Asegurar que el campo Correo del cliente registrado jurídico sea único e irrepetible
G11: ='P-ClienteRegistradoJ'!A9 -> P-CRJ-005 | H11: ='P-ClienteRegistradoJ'!B9 -> Asegurar que el campo RazonSocial del cliente registrado jurídico sea único e irrepetible
G12: ='P-ClienteRegistradoJ'!A10 -> P-CRJ-006 | H12: ='P-ClienteRegistradoJ'!B10 -> Garantizar que el sistema debe validar que un mismo cliente registrado no esté asociado a más de un ClienteRegistradoNatural ni a un ClienteRegistradoJuridico
G13: ='P-ClienteRegistradoJ'!A11 -> P-CRJ-007 | H13: ='P-ClienteRegistradoJ'!B11 -> Asegurar que los datos requeridos sean válidos en tipo de dato, longitud, obligatoriedad y formato
A14: Administrador/Vendedor | B14: Consultar clientes registrados jurídicos por filtro | C14: Permite buscar, listar y filtrar los clientes registrados jurídicos según los criterios de búsqueda enviados | D14: ClienteRegistradoJuridico | E14: Filtros de cliente registrado jurídico | F14: Contiene los parámetros o criterios de búsqueda enviados para filtrar la consulta | G14: ='P-ClienteRegistradoJ'!A11 -> P-CRJ-007 | H14: ='P-ClienteRegistradoJ'!B11 -> Asegurar que los datos requeridos sean válidos en tipo de dato, longitud, obligatoriedad y formato | J14: Clientes registrados jurídicos encontrados
A15: Vendedor | B15: Modificar un cliente registrado jurídico | C15: Permite actualizar la información de un cliente registrado jurídico existente | D15: ClienteRegistradoJuridico | E15: Datos del cliente registrado jurídico a modificar | F15: Tiene el identificador único del cliente registrado jurídico a modificar y la nueva información | G15: ='P-ClienteRegistradoJ'!A7 -> P-CRJ-003 | H15: ='P-ClienteRegistradoJ'!B7 -> Asegurar que el campo Telefono del cliente registrado jurídico sea único e irrepetible | J15: Cliente registrado jurídico modificado
G16: ='P-ClienteRegistradoJ'!A8 -> P-CRJ-004 | H16: ='P-ClienteRegistradoJ'!B8 -> Asegurar que el campo Correo del cliente registrado jurídico sea único e irrepetible
G17: ='P-ClienteRegistradoJ'!A9 -> P-CRJ-005 | H17: ='P-ClienteRegistradoJ'!B9 -> Asegurar que el campo RazonSocial del cliente registrado jurídico sea único e irrepetible
G18: ='P-ClienteRegistradoJ'!A11 -> P-CRJ-007 | H18: ='P-ClienteRegistradoJ'!B11 -> Asegurar que los datos requeridos sean válidos en tipo de dato, longitud, obligatoriedad y formato
A19: Vendedor | B19: Eliminar un cliente registrado jurídico | C19: Permite eliminar un cliente registrado jurídico conservando la trazabilidad de su historial | D19: ClienteRegistradoJuridico | E19: Identificador del cliente registrado jurídico a eliminar | F19: Contiene el identificador único del cliente registrado jurídico que se desea eliminar | G19: ='P-ClienteRegistradoJ'!A11 -> P-CRJ-007 | H19: ='P-ClienteRegistradoJ'!B11 -> Asegurar que los datos requeridos sean válidos en tipo de dato, longitud, obligatoriedad y formato | J19: Cliente registrado jurídico eliminado
G20: ='P-ClienteRegistradoJ'!A12 -> P-CRJ-008 | H20: ='P-ClienteRegistradoJ'!B12 -> Asegurar que cliente no este realizando algún proceso o transacción de compra en el momento de la eliminación

Sheet P-ClienteRegistradoJ
A1: <<<Ir al modelo de dominio | B1: <<<Ir a objeto de dominio | C1: <<<Ir a muestreo del objeto | D1: <<<Ir a caracterización | E1: <<<Ir al event storming
A2: Objeto de Dominio: | B2: ='Objetos de Dominio'!A17 -> ClienteRegistradoJ
A3: Descripción: | B3: ='Objetos de Dominio'!B17 -> Representa al cliente registrado Jurídico en el sistema con sus datos básicos de identificación y contacto
A4: Número Política | B4: Descripción Política | C4: Objeto Responsable
A5: P-CRJ-001 | B5: Asegurar que el id del cliente registrado jurídico sea único e irrepetible | C5: ClienteRegistradoJuridico
A6: P-CRJ-002 | B6: Asegurar que el campo NIT del cliente registrado jurídico sea único e irrepetible | C6: ClienteRegistradoJuridico
A7: P-CRJ-003 | B7: Asegurar que el campo Telefono del cliente registrado jurídico sea único e irrepetible | C7: ClienteRegistradoJuridico
A8: P-CRJ-004 | B8: Asegurar que el campo Correo del cliente registrado jurídico sea único e irrepetible | C8: ClienteRegistradoJuridico
A9: P-CRJ-005 | B9: Asegurar que el campo RazonSocial del cliente registrado jurídico sea único e irrepetible | C9: ClienteRegistradoJuridico
A10: P-CRJ-006 | B10: Garantizar que el sistema debe validar que un mismo cliente registrado no esté asociado a más de un ClienteRegistradoNatural ni a un ClienteRegistradoJuridico | C10: ClienteRegistradoJuridico
A11: P-CRJ-007 | B11: Asegurar que los datos requeridos sean válidos en tipo de dato, longitud, obligatoriedad y formato | C11: ClienteRegistradoJuridico
A12: P-CRJ-008 | B12: Asegurar que cliente no este realizando algún proceso o transacción de compra en el momento de la eliminación | C12: ClienteRegistradoJuridico

Sheet M-Ciudad
A1: <<<Ir al modelo de dominio | B1: <<<Ir a objeto de dominio | C1: Ir a la caracterización>>> | D1: Ir al event storming>>> | E1: Ir a las políticas>>>
A2: Nombre: | B2: ='Objetos de Dominio'!A18 -> Ciudad
A3: Descripción: | B3: ='Objetos de Dominio'!B18 -> Representa la ciudad o municipio donde se ubican las sedes del negocio y residen los clientes.
A4: Identificador único de la ciudad | B4: Departamento al que pertenece la ciudad | C4: Nombre oficial de la ciudad o municipio | D4: Combinación única que indica que no puede existir más de una ciudad con el mismo nombre en un mismo departamento
A5: ID | B5: ='Objetos de Dominio'!A13 -> Departamento | C5: Nombre | D5: DepartamentoCiudad
A6: 1 | B6: ='M-Departamento'!C6 -> Antioquia | C6: Rionegro | D6: =_xlfn.CONCAT(B6, " + ", C6) -> Antioquia + Rionegro
A7: 2 | B7: ='M-Departamento'!C7 -> Cundinamarca | C7: La Ceja | D7: =_xlfn.CONCAT(B7, " + ", C7) -> Cundinamarca + La Ceja
A8: 3 | B8: ='M-Departamento'!C8 -> Pichincha | C8: Medellín | D8: =_xlfn.CONCAT(B8, " + ", C8) -> Pichincha + Medellín

Sheet C-Ciudad
A1: <<<Ir al modelo de dominio | B1: <<<Ir a objeto de dominio | C1: <<<Ir a muestreo del objeto | D1: Ir al event storming>>> | E1: Ir a las políticas>>>
A2: Nombre | B2: ='Objetos de Dominio'!A18 -> Ciudad
A3: Descripción | B3: ='Objetos de Dominio'!B18 -> Representa la ciudad o municipio donde se ubican las sedes del negocio y residen los clientes.
A4: Nombre atributo | B4: Descripción atributo | C4: Identificador del objeto de dominio | D4: Tipo de dato | E4: Obligatorio | F4: Longitud mínima (si aplica) | G4: Longitud máxima (si aplica) | H4: Precisión (si aplica) | I4: Redondeo (si aplica) | J4: Rango inicial (si aplica) | K4: Rango final (si aplica) | L4: Formato (si aplica) | M4: Reglas especiales (si aplica) | N4: Dato calculado | O4: Aplica ajuste del dato (si aplica) | P4: Carácter de ajuste (si aplica) | Q4: Quitar espacios en blanco al inicio (si aplica) | R4: Quitar espacios en blanco al fin (si aplica) | S4: Dato sensible (si aplica) | T4: Valor por defecto (si aplica) | U4: Auto generado | V4: consultarCiudadesPorFiltro
A5: ID | B5: ='M-Ciudad'!A4 -> Identificador único de la ciudad | C5: Si | D5: Identificador único universal | E5: Si | F5: - | G5: - | H5: - | I5: - | J5: - | K5: - | L5: - | M5: Debe ser único y no debe repetirse en los distintos id's de las ciudades | N5: No | O5: No | P5: - | Q5: No | R5: No | S5: - | T5: - | U5: Si | V5: Filtro | W5: No Mostrar
A6: Departamento | B6: ='M-Ciudad'!B4 -> Departamento al que pertenece la ciudad | C6: No | D6: Departamento | E6: Si | F6: - | G6: - | H6: - | I6: - | J6: - | K6: - | L6: - | M6: Aplican las reglas del objeto referenciado | N6: No | O6: No | P6: - | Q6: No | R6: No | S6: - | T6: - | U6: No | V6: Filtro | W6: Mostrar
A7: Nombre | B7: ='M-Ciudad'!C4 -> Nombre oficial de la ciudad o municipio | C7: No | D7: Alfanumérico | E7: Si | F7: 2 | G7: 100 | H7: - | I7: - | J7: - | K7: - | L7: - | M7: Se debe asegurar una sanitización del dato, para garantizar que dentro de su contenido no tenga cualquier tipo de intento de ataque | N7: No | O7: No | P7: - | Q7: Si | R7: Si | S7: - | T7: - | U7: No | V7: Filtro | W7: Mostrar
A10: Nombre combinación única | B10: Descripción | C10: Atributos involucrados
A11: ='M-Ciudad'!D5 -> DepartamentoCiudad | B11: ='M-Ciudad'!D4 -> Combinación única que indica que no puede existir más de una ciudad con el mismo nombre en un mismo departamento | C11: Departamento
C12: Nombre
A15: Responsabilidad | C15: Descripción | G15: Entradas | J15: Salida | O15: Políticas (Reglas de Negocio) | Q15: Excepción
G16: Parámetro | H16: Tipo de dato | I16: Descripción | J16: Tipo de Dato | K16: Descripción | O16: Política | P16: Descripción | Q16: Detalle | R16: ¿Qué hago?
A17: consultarCiudadesPorFiltro | C17: Permite buscar, listar y filtrar las ciudades según los criterios de búsqueda enviados | G17: filtro | H17: Ciudad | I17: Contiene los parámetros o criterios de búsqueda enviados para filtrar la consulta | J17: Lista<Ciudad> | K17: Contiene la lista de ciudades que cumplen con las condiciones del filtro enviado | O17: =HYPERLINK("#'P-Ciudad'!A7",'P-Ciudad'!A5) -> P-CIU-001 | P17: ='P-Ciudad'!B5 -> Asegurar que los datos requeridos sean válidos en tipo de dato, longitud, obligatoriedad y formato. | Q17: Generar una excepción indicando que los datos requeridos son inválidos o están incompletos | R17: Detener operación

Sheet E-Ciudad
A1: <<<Ir al modelo de dominio | B1: <<<Ir a objeto de dominio | C1: <<<Ir a muestreo del objeto | D1: <<<Ir a caracterización | E1: Ir a las políticas>>>
A2: Objeto de Dominio: | B2: ='Objetos de Dominio'!A18 -> Ciudad
A3: Descripción: | B3: ='Objetos de Dominio'!B18 -> Representa la ciudad o municipio donde se ubican las sedes del negocio y residen los clientes.
A4: Actor | B4: Action/Command | D4: Entity/Aggregate/Object domain | E4: Read Model | G4: Business Rule/Policy | I4: External System | J4: Domain Event | K4: Hotspot/questions/Risk
A5: Actor | B5: Acción | C5: Descripción | D5: Objeto de dominio | E5: Información externa | G5: Políticas | I5: Sistema Externo | J5: Evento | K5: Aspectos por solucionar
E6: Información | F6: Descripción | G6: Número | H6: Descripción
A7: Administrador/Vendedor | B7: Consultar ciudades por filtro | C7: Permite buscar, listar y filtrar las ciudades según los criterios de búsqueda enviados | D7: Ciudad | E7: Filtros de ciudades | F7: Contiene los parámetros o criterios de búsqueda enviados para filtrar la consulta | G7: =HYPERLINK("#'P-Ciudad'!A7",'P-Ciudad'!A5) -> P-CIU-001 | H7: ='P-Ciudad'!B5 -> Asegurar que los datos requeridos sean válidos en tipo de dato, longitud, obligatoriedad y formato. | J7: Ciudades encontradas

Sheet P-Ciudad
A1: <<<Ir al modelo de dominio | B1: <<<Ir a objeto de dominio | C1: <<<Ir a muestreo del objeto | D1: <<<Ir a caracterización | E1: <<<Ir al event storming
A2: Objeto de Dominio: | B2: ='Objetos de Dominio'!A18 -> Ciudad
A3: Descripción: | B3: ='Objetos de Dominio'!B18 -> Representa la ciudad o municipio donde se ubican las sedes del negocio y residen los clientes.
A4: Número Política | B4: Descripción Política | C4: Objeto Responsable
A5: P-CIU-001 | B5: Asegurar que los datos requeridos sean válidos en tipo de dato, longitud, obligatoriedad y formato. | C5: Ciudad

Sheet M-Sede
A1: <<<Ir al modelo de dominio | B1: <<<Ir a objeto de dominio | C1: Ir a la caracterización>>> | D1: Ir al event storming>>> | E1: Ir a las políticas>>>
A2: Nombre: | B2: ='Objetos de Dominio'!A19 -> Sede
A3: Descripción: | B3: ='Objetos de Dominio'!B19 -> Representa cada local físico del negocio, donde se atienden las compras y se almacena la mercancía.
A4: Identificador único de la sede | B4: Ciudad en la que está ubicada la sede | C4: Nombre con el que se identifica el local físico | D4: Número de NIT legal con el que se identifica la sede | E4: Dirección física donde está ubicada la sede | F4: Variable booleana que define si una sede esta funcionando actualmente o no | G4: Combinación única que indica que no puede existir más de una sede con el mismo nombre | H4: Combinación única que indica que no puede existir más de una sede con el mismo NIT | I4: Combinación única que indica que no puede existir más de una sede con la misma Dirección
A5: ID | B5: ='Objetos de Dominio'!A18 -> Ciudad | C5: Nombre | D5: Nit | E5: Dirección | F5: EsActiva | G5: NombreSedeUnico | H5: NitSedeUnico | I5: DireccionSedeUnica
A6: 1 | B6: ='M-Ciudad'!C6 -> Rionegro | C6: Saraitel San Nicolás | D6: 890.900.608-9 | E6: CC San Nicolás, Local 120 | F6: SI | G6: =C6 -> Saraitel San Nicolás | H6: =D6 -> 890.900.608-9 | I6: =E6 -> CC San Nicolás, Local 120
A7: 2 | B7: ='M-Ciudad'!C6 -> Rionegro | C7: Saraitel San Antonio | D7: 860.005.224-6 | E7: Mall la Placita, Local 112- San Antonio de Pereira | F7: SI | G7: =C7 -> Saraitel San Antonio | H7: =D7 -> 860.005.224-6 | I7: =E7 -> Mall la Placita, Local 112- San Antonio de Pereira
A8: 3 | B8: ='M-Ciudad'!C8 -> Medellín | C8: Saraitel La Ceja | D8: 890.301.884-0 | E8: Cl 51 #38-20, La Ceja del Tambo | F8: NO | G8: =C8 -> Saraitel La Ceja | H8: =D8 -> 890.301.884-0 | I8: =E8 -> Cl 51 #38-20, La Ceja del Tambo

Sheet C-Sede
A1: <<<Ir al modelo de dominio | B1: <<<Ir a objeto de dominio | C1: <<<Ir a muestreo del objeto | D1: Ir al event storming>>> | E1: Ir a las políticas>>>
A2: Nombre | B2: ='Objetos de Dominio'!A19 -> Sede
A3: Descripción | B3: ='Objetos de Dominio'!B19 -> Representa cada local físico del negocio, donde se atienden las compras y se almacena la mercancía.
A4: Nombre atributo | B4: Descripción atributo | C4: Identificador del objeto de dominio | D4: Tipo de dato | E4: Obligatorio | F4: Longitud mínima (si aplica) | G4: Longitud máxima (si aplica) | H4: Precisión (si aplica) | I4: Redondeo (si aplica) | J4: Rango inicial (si aplica) | K4: Rango final (si aplica) | L4: Formato (si aplica) | M4: Reglas especiales (si aplica) | N4: Dato calculado | O4: Aplica ajuste del dato (si aplica) | P4: Carácter de ajuste (si aplica) | Q4: Quitar espacios en blanco al inicio (si aplica) | R4: Quitar espacios en blanco al fin (si aplica) | S4: Dato sensible (si aplica) | T4: Valor por defecto (si aplica) | U4: Auto generado | V4: registrarSede | W4: consultarSedesPorFiltro | Y4: modificarSede
A5: ID | B5: ='M-Sede'!A4 -> Identificador único de la sede | C5: Si | D5: Identificador único universal | E5: Si | F5: - | G5: - | H5: - | I5: - | J5: - | K5: - | L5: - | M5: Debe ser único y no debe repetirse en los distintos id's de las sedes | N5: No | O5: No | P5: - | Q5: No | R5: No | S5: - | T5: - | U5: Si | V5: Requerido | W5: Filtro | X5: No Mostrar | Y5: Requerido | Z5: No Modificable
A6: Ciudad | B6: ='M-Sede'!B4 -> Ciudad en la que está ubicada la sede | C6: No | D6: Ciudad | E6: Si | F6: - | G6: - | H6: - | I6: - | J6: - | K6: - | L6: - | M6: Aplican las reglas del objeto referenciado | N6: No | O6: No | P6: - | Q6: No | R6: No | S6: - | T6: - | U6: No | V6: Requerido | W6: Filtro | X6: Mostrar | Y6: No Requerido | Z6: No Modificable
A7: Nombre | B7: ='M-Sede'!C4 -> Nombre con el que se identifica el local físico | C7: No | D7: Alfanumérico | E7: Si | F7: 2 | G7: 100 | H7: - | I7: - | J7: - | K7: - | L7: - | M7: Se debe asegurar una sanitización del dato, para garantizar que dentro de su contenido no tenga cualquier tipo de intento de ataque | N7: No | O7: No | P7: - | Q7: Si | R7: Si | S7: - | T7: - | U7: No | V7: Requerido | W7: Filtro | X7: Mostrar | Y7: No Requerido | Z7: Modificable
A8: Nit | B8: ='M-Sede'!D4 -> Número de NIT legal con el que se identifica la sede | C8: No | D8: Alfanumérico | E8: Si | F8: 6 | G8: 20 | H8: - | I8: - | J8: - | K8: - | L8: Formato valido de NIT 897468876-9 | M8: Debe ser un NIT válido con dígito de verificación correcto, y debe ser único por sede | N8: No | O8: No | P8: - | Q8: Si | R8: Si | S8: - | T8: - | U8: No | V8: Requerido | W8: Filtro | X8: Mostrar | Y8: No Requerido | Z8: Modificable
A9: Dirección | B9: ='M-Sede'!E4 -> Dirección física donde está ubicada la sede | C9: No | D9: Alfanumérico | E9: Si | F9: 5 | G9: 200 | H9: - | I9: - | J9: - | K9: - | L9: - | M9: Se debe asegurar una sanitización del dato, para garantizar que dentro de su contenido no tenga cualquier tipo de intento de ataque | N9: No | O9: No | P9: - | Q9: Si | R9: Si | S9: - | T9: - | U9: No | V9: Requerido | W9: Filtro | X9: Mostrar | Y9: No Requerido | Z9: Modificable
A10: EsActiva | B10: ='M-Sede'!F4 -> Variable booleana que define si una sede esta funcionando actualmente o no | C10: Si | D10: Lógico | E10: Si | F10: - | G10: - | H10: - | I10: - | J10: - | K10: - | L10: - | M10: Solo admite SI o NO y es ingresado por el administrador; al pasar a NO la sede se inhabilita pero se conserva su historial | N10: No | O10: No | P10: - | Q10: No | R10: No | S10: - | T10: Si | U10: No | V10: Requerido | W10: Filtro | X10: Mostrar | Y10: Requerido | Z10: Modificable
A14: Nombre combinación única | B14: Descripción | C14: Atributos involucrados
A15: ='M-Sede'!G5 -> NombreSedeUnico | B15: ='M-Sede'!G4 -> Combinación única que indica que no puede existir más de una sede con el mismo nombre | C15: Nombre
A16: ='M-Sede'!H5 -> NitSedeUnico | B16: ='M-Sede'!H4 -> Combinación única que indica que no puede existir más de una sede con el mismo NIT | C16: NIT
A17: ='M-Sede'!I5 -> DireccionSedeUnica | B17: ='M-Sede'!I4 -> Combinación única que indica que no puede existir más de una sede con la misma Dirección | C17: Dirección
A21: Responsabilidad | C21: Descripción | G21: Entradas | J21: Salida | O21: Políticas (Reglas de Negocio) | Q21: Excepción
G22: Parámetro | H22: Tipo de dato | I22: Descripción | J22: Tipo de Dato | K22: Descripción | O22: Política | P22: Descripción | Q22: Detalle | R22: ¿Qué hago?
A23: registrarSede | C23: Permite registrar una nueva sede en el sistema | G23: datos | H23: Sede | I23: Contiene la información requerida para registrar la sede | J23: Sede | K23: Objeto de la sede registrada con su identificador ID asignado | O23: =HYPERLINK("#'P-Sede'!A5",'P-Sede'!A5) -> P-SED-001 | P23: ='P-Sede'!B5 -> Asegurar que el id de la sede debe ser único e irrepetible | Q23: Generar un nuevo identificador hasta garantizar que no exista | R23: Continuar operación
O24: =HYPERLINK("#'P-Sede'!A6",'P-Sede'!A6) -> P-SED-002 | P24: ='P-Sede'!B6 -> Asegurar que el campo Nombre de sede debe ser único e irrepetible | Q24: Generar una excepción indicando que ya existe una sede con ese mismo Nombre | R24: Detener operación
O25: =HYPERLINK("#'P-Sede'!A7",'P-Sede'!A7) -> P-SED-003 | P25: ='P-Sede'!B7 -> Asegurar que el campo NIT de sede debe ser único e irrepetible | Q25: Generar una excepción indicando que ya existe una sede con ese mismo NIT | R25: Detener operación
O26: =HYPERLINK("#'P-Sede'!A8",'P-Sede'!A8) -> P-SED-004 | P26: ='P-Sede'!B8 -> Asegurar que el campo Dirección de sede debe ser único e irrepetible | Q26: Generar una excepción indicando que ya existe una sede con ese mismo Dirección | R26: Detener operación
O27: =HYPERLINK("#'P-Sede'!A9",'P-Sede'!A9) -> P-SED-005 | P27: ='P-Sede'!B9 -> Asegurar que los datos requeridos sean válidos en tipo de dato, longitud, obligatoriedad y formato | Q27: Generar una excepción indicando que los datos requeridos son inválidos o están incompletos | R27: Detener operación
A28: consultarSedesPorFiltro | C28: Permite buscar, listar y filtrar las sedes según los criterios de búsqueda enviados | G28: filtro | H28: Sede | I28: Contiene los parámetros o criterios de búsqueda enviados para filtrar la consulta | J28: Lista<Sede> | K28: Contiene la lista de sedes que cumplen con las condiciones del filtro enviado | O28: =HYPERLINK("#'P-Sede'!A9",'P-Sede'!A9) -> P-SED-005 | P28: ='P-Sede'!B9 -> Asegurar que los datos requeridos sean válidos en tipo de dato, longitud, obligatoriedad y formato | Q28: Generar una excepción indicando que los datos requeridos son inválidos o están incompletos | R28: Detener operación
A29: modificarSede | C29: Permite actualizar la información de una sede existente | G29: id | H29: UUID | I29: Tiene el identificador único de la sede a modificar y la nueva información | J29: Sede | K29: Objeto de la sede con su información actualizada | O29: =HYPERLINK("#'P-Sede'!A6",'P-Sede'!A6) -> P-SED-002 | P29: ='P-Sede'!B6 -> Asegurar que el campo Nombre de sede debe ser único e irrepetible | Q29: Generar una excepción indicando que ya existe una sede con ese mismo Nombre | R29: Detener operación
O30: =HYPERLINK("#'P-Sede'!A7",'P-Sede'!A7) -> P-SED-003 | P30: ='P-Sede'!B7 -> Asegurar que el campo NIT de sede debe ser único e irrepetible | Q30: Generar una excepción indicando que ya existe una sede con ese mismo NIT | R30: Detener operación
G31: datos | H31: Sede | O31: =HYPERLINK("#'P-Sede'!A8",'P-Sede'!A8) -> P-SED-004 | P31: ='P-Sede'!B8 -> Asegurar que el campo Dirección de sede debe ser único e irrepetible | Q31: Generar una excepción indicando que ya existe una sede con ese mismo Dirección | R31: Detener operación
O32: =HYPERLINK("#'P-Sede'!A9",'P-Sede'!A9) -> P-SED-005 | P32: ='P-Sede'!B9 -> Asegurar que los datos requeridos sean válidos en tipo de dato, longitud, obligatoriedad y formato | Q32: Generar una excepción indicando que los datos requeridos son inválidos o están incompletos | R32: Detener operación

Sheet E-Sede
A1: <<<Ir al modelo de dominio | B1: <<<Ir a objeto de dominio | C1: <<<Ir a muestreo del objeto | D1: <<<Ir a caracterización | E1: Ir a las políticas>>>
A2: Objeto de Dominio: | B2: ='Objetos de Dominio'!A19 -> Sede
A3: Descripción: | B3: ='Objetos de Dominio'!B19 -> Representa cada local físico del negocio, donde se atienden las compras y se almacena la mercancía.
A4: Actor | B4: Action/Command | D4: Entity/Aggregate/Object domain | E4: Read Model | G4: Business Rule/Policy | I4: External System | J4: Domain Event | K4: Hotspot/questions/Risk
A5: Actor | B5: Acción | C5: Descripción | D5: Objeto de dominio | E5: Información externa | G5: Políticas | I5: Sistema Externo | J5: Evento | K5: Aspectos por solucionar
E6: Información | F6: Descripción | G6: Número | H6: Descripción
A7: Administrador | B7: Registrar una nueva sede | C7: Permite registrar una nueva sede en el sistema | D7: Sede | E7: Datos de la nueva sede | F7: Contiene la información requerida para registrar la sede | G7: =HYPERLINK("#'P-Sede'!A5",'P-Sede'!A5) -> P-SED-001 | H7: ='P-Sede'!B5 -> Asegurar que el id de la sede debe ser único e irrepetible | J7: Sede registrada
G8: =HYPERLINK("#'P-Sede'!A6",'P-Sede'!A6) -> P-SED-002 | H8: ='P-Sede'!B6 -> Asegurar que el campo Nombre de sede debe ser único e irrepetible
G9: =HYPERLINK("#'P-Sede'!A7",'P-Sede'!A7) -> P-SED-003 | H9: ='P-Sede'!B7 -> Asegurar que el campo NIT de sede debe ser único e irrepetible
G10: =HYPERLINK("#'P-Sede'!A8",'P-Sede'!A8) -> P-SED-004 | H10: ='P-Sede'!B8 -> Asegurar que el campo Dirección de sede debe ser único e irrepetible
G11: =HYPERLINK("#'P-Sede'!A9",'P-Sede'!A9) -> P-SED-005 | H11: ='P-Sede'!B9 -> Asegurar que los datos requeridos sean válidos en tipo de dato, longitud, obligatoriedad y formato
A12: Administrador/Vendedor | B12: Consultar sedes por filtro | C12: Permite buscar, listar y filtrar las sedes según los criterios de búsqueda enviados | D12: Sede | E12: Filtros de sedes | F12: Contiene los parámetros o criterios de búsqueda enviados para filtrar la consulta | G12: =HYPERLINK("#'P-Sede'!A9",'P-Sede'!A9) -> P-SED-005 | H12: ='P-Sede'!B9 -> Asegurar que los datos requeridos sean válidos en tipo de dato, longitud, obligatoriedad y formato | J12: Sedes encontradas
A13: Administrador | B13: Modificar una sede | C13: Permite actualizar la información de una sede existente | D13: Sede | E13: Datos de la sede a modificar | F13: Tiene el identificador único de la sede a modificar y la nueva información | G13: =HYPERLINK("#'P-Sede'!A6",'P-Sede'!A6) -> P-SED-002 | H13: ='P-Sede'!B6 -> Asegurar que el campo Nombre de sede debe ser único e irrepetible | J13: Sede modificada
G14: =HYPERLINK("#'P-Sede'!A7",'P-Sede'!A7) -> P-SED-003 | H14: ='P-Sede'!B7 -> Asegurar que el campo NIT de sede debe ser único e irrepetible
G15: =HYPERLINK("#'P-Sede'!A8",'P-Sede'!A8) -> P-SED-004 | H15: ='P-Sede'!B8 -> Asegurar que el campo Dirección de sede debe ser único e irrepetible
G16: =HYPERLINK("#'P-Sede'!A9",'P-Sede'!A9) -> P-SED-005 | H16: ='P-Sede'!B9 -> Asegurar que los datos requeridos sean válidos en tipo de dato, longitud, obligatoriedad y formato

Sheet P-Sede
A1: <<<Ir al modelo de dominio | B1: <<<Ir a objeto de dominio | C1: <<<Ir a muestreo del objeto | D1: <<<Ir a caracterización | E1: <<<Ir al event storming
A2: Objeto de Dominio: | B2: ='Objetos de Dominio'!A19 -> Sede
A3: Descripción: | B3: ='Objetos de Dominio'!B19 -> Representa cada local físico del negocio, donde se atienden las compras y se almacena la mercancía.
A4: Número Política | B4: Descripción Política | C4: Objeto Responsable
A5: P-SED-001 | B5: Asegurar que el id de la sede debe ser único e irrepetible | C5: Sede
A6: P-SED-002 | B6: Asegurar que el campo Nombre de sede debe ser único e irrepetible | C6: Sede
A7: P-SED-003 | B7: Asegurar que el campo NIT de sede debe ser único e irrepetible | C7: Sede
A8: P-SED-004 | B8: Asegurar que el campo Dirección de sede debe ser único e irrepetible | C8: Sede
A9: P-SED-005 | B9: Asegurar que los datos requeridos sean válidos en tipo de dato, longitud, obligatoriedad y formato | C9: Sede

Sheet M-IngresoInventario
A1: <<<Ir al modelo de dominio | B1: <<<Ir a objeto de dominio | C1: Ir a la caracterización>>> | D1: Ir al event storming>>> | E1: Ir a las políticas>>>
A2: Nombre: | B2: ='Objetos de Dominio'!A20 -> IngresoInventario
A3: Descripción: | B3: ='Objetos de Dominio'!B20 -> Representa la factura de la llegada de nueva mercancía a una sede por parte de un proveedor que la creó previamente.
A4: Identificador único del ingreso de inventario | B4: Nombre de la sede que recibe la mercancía | C4: Fecha en que llega la mercancía a la sede | D4: Valor total de la mercancía ingresada | E4: Estado actual de la ingreso de inventario (En proceso, Cancelado y Creado) | F4: Combinación única que indica que no puede existir más de un ingresoInventario en la misma sede a la misma hora de ingreso
A5: ID | B5: Sede | C5: FechaLlegada | D5: Total | E5: Estado | F5: LlegadaInventarioSedeUnico
A6: 1 | B6: ='M-Sede'!C6 -> Saraitel San Nicolás | C6: 04/03/2026 - 7:00 pm | D6: 1000000 | E6: Creado | F6: =_xlfn.CONCAT(B6," + ",C6) -> Saraitel San Nicolás + 04/03/2026 - 7:00 pm
A7: 2 | B7: ='M-Sede'!C7 -> Saraitel San Antonio | C7: 05/02/2026 - 5:00 am | D7: 5000000 | E7: Creado | F7: =_xlfn.CONCAT(B7," + ",C7) -> Saraitel San Antonio + 05/02/2026 - 5:00 am
A8: 3 | B8: ='M-Sede'!C8 -> Saraitel La Ceja | C8: 06/02/2026 - 10:00 am | D8: 2500000 | E8: Cancelado | F8: =_xlfn.CONCAT(B8," + ",C8) -> Saraitel La Ceja + 06/02/2026 - 10:00 am

Sheet C-IngresoInventario
A1: <<<Ir al modelo de dominio | B1: <<<Ir a objeto de dominio | C1: <<<Ir a muestreo del objeto | D1: Ir al event storming>>> | E1: Ir a las políticas>>>
A2: Nombre | B2: ='Objetos de Dominio'!A20 -> IngresoInventario
A3: Descripción | B3: ='Objetos de Dominio'!B20 -> Representa la factura de la llegada de nueva mercancía a una sede por parte de un proveedor que la creó previamente.
A4: Nombre atributo | B4: Descripción atributo | C4: Identificador del objeto de dominio | D4: Tipo de dato | E4: Obligatorio | F4: Longitud mínima (si aplica) | G4: Longitud máxima (si aplica) | H4: Precisión (si aplica) | I4: Redondeo (si aplica) | J4: Rango inicial (si aplica) | K4: Rango final (si aplica) | L4: Formato (si aplica) | M4: Reglas especiales (si aplica) | N4: Dato calculado | O4: Aplica ajuste del dato (si aplica) | P4: Carácter de ajuste (si aplica) | Q4: Quitar espacios en blanco al inicio (si aplica) | R4: Quitar espacios en blanco al fin (si aplica) | S4: Dato sensible (si aplica) | T4: Valor por defecto (si aplica) | U4: Auto generado | V4: registrarIngresoInventario | W4: consultarIngresosInventarioPorFiltro
A5: ID | B5: ='M-IngresoInventario'!A4 -> Identificador único del ingreso de inventario | C5: Si | D5: Identificador único universal | E5: Si | F5: - | G5: - | H5: - | I5: - | J5: - | K5: - | L5: - | M5: Debe ser único y no debe repetirse en los distintos id's de los ingresos de inventario | N5: No | O5: No | P5: - | Q5: No | R5: No | S5: - | T5: - | U5: Si | V5: Requerido | W5: Filtro | X5: No Mostrar
A6: Sede | B6: ='M-IngresoInventario'!B4 -> Nombre de la sede que recibe la mercancía | C6: No | D6: Sede | E6: Si | F6: - | G6: - | H6: - | I6: - | J6: - | K6: - | L6: - | M6: Aplican las reglas del objeto referenciado | N6: No | O6: No | P6: - | Q6: No | R6: No | S6: - | T6: - | U6: No | V6: Requerido | W6: Filtro | X6: Mostrar
A7: FechaLlegada | B7: ='M-IngresoInventario'!C4 -> Fecha en que llega la mercancía a la sede | C7: No | D7: Fecha/Hora | E7: Si | F7: - | G7: - | H7: - | I7: - | J7: - | K7: - | L7: DD-MM-AAAA HH:MM | M7: No puede ser una fecha posterior a la fecha y hora actual del sistema | N7: No | O7: No | P7: - | Q7: No | R7: No | S7: - | T7: - | U7: Si | V7: Requerido | W7: Filtro | X7: Mostrar
A8: Total | B8: ='M-IngresoInventario'!D4 -> Valor total de la mercancía ingresada | C8: No | D8: Numérico Decimal | E8: Si | F8: - | G8: - | H8: 2 | I8: Truncamiento | J8: 0 | K8: - | L8: Formato Contaduria | M8: Es un valor que se calcula a partir de el costoUnitario*cantidad de cada producto de detalleIngreso | N8: Si | O8: No | P8: - | Q8: No | R8: No | S8: - | T8: - | U8: No | V8: Requerido | W8: Filtro | X8: Mostrar
A9: Estado | B9: ='M-IngresoInventario'!E4 -> Estado actual de la ingreso de inventario (En proceso, Cancelado y Creado) | C9: No | D9: Texto | E9: Si | F9: 6 | G9: 20 | H9: - | I9: - | J9: - | K9: - | L9: - | M9: Solo puede tomar los estados definidos para el ingreso de inventario y sus cambios deben realizarse de acuerdo con las transiciones permitidas por el proceso de compra. | N9: No | O9: No | P9: - | Q9: Si | R9: Si | S9: - | T9: Pendiente | U9: Si | V9: Requerido | W9: Filtro | X9: Mostrar
A12: Nombre combinación única | B12: Descripción | C12: Atributos involucrados
A13: ='M-IngresoInventario'!F5 -> LlegadaInventarioSedeUnico | B13: ='M-IngresoInventario'!F4 -> Combinación única que indica que no puede existir más de un ingresoInventario en la misma sede a la misma hora de ingreso | C13: Sede
C14: FechaLlegada
A18: Responsabilidad | C18: Descripción | G18: Entradas | J18: Salida | O18: Políticas (Reglas de Negocio) | Q18: Excepción
G19: Parámetro | H19: Tipo de dato | I19: Descripción | J19: Tipo de Dato | K19: Descripción | O19: Política | P19: Descripción | Q19: Detalle | R19: ¿Qué hago?
A20: registrarIngresoInventario | C20: Permite registrar un nuevo ingreso de inventario en el sistema | G20: datos | H20: IngresoInventario | I20: Contiene la información requerida para registrar el ingreso de inventario | J20: IngresoInventario | K20: Objeto del ingreso de inventario registrado con su identificador ID asignado | O20: =HYPERLINK("#'P-IngresoInventario'!A5",'P-IngresoInventario'!A5) -> P-ING-001 | P20: ='P-IngresoInventario'!B5 -> Asegurar que el id de ingreso de inventario sea único e irrepetible | Q20: Generar un nuevo identificador hasta garantizar que no exista | R20: Continuar operación
O21: =HYPERLINK("#'P-IngresoInventario'!A6",'P-IngresoInventario'!A6) -> P-ING-002 | P21: ='P-IngresoInventario'!B6 -> Asegurar que solo se registren ingresos en una sede activa | Q21: Generar una excepción indicando que la sede no esta activa en el momento | R21: Detener operación
O22: =HYPERLINK("#'P-IngresoInventario'!A7",'P-IngresoInventario'!A7) -> P-ING-003 | P22: ='P-IngresoInventario'!B7 -> Asegurar que el ingreso de inventario a una sede específica no ocurra al mismo tiempo que otro ingreso | Q22: Generar una excepción indicando que en la sede no se puede tener un ingreso de inventario ingresando a una misma sede a la misma hora | R22: Detener operación
O23: =HYPERLINK("#'P-IngresoInventario'!A8",'P-IngresoInventario'!A8) -> P-ING-004 | P23: ='P-IngresoInventario'!B8 -> Asegurar que los datos requeridos sean válidos en tipo de dato, longitud, obligatoriedad y formato | Q23: Generar una excepción indicando que los datos requeridos son inválidos o están incompletos | R23: Detener operación
A24: consultarIngresosInventarioPorFiltro | C24: Permite buscar, listar y filtrar los ingresos de inventario según los criterios de búsqueda enviados | G24: filtro | H24: IngresoInventario | I24: Contiene los parámetros o criterios de búsqueda enviados para filtrar la consulta | J24: Lista<IngresoInventario> | K24: Contiene la lista de ingresos de inventario que cumplen con las condiciones del filtro enviado | O24: =HYPERLINK("#'P-IngresoInventario'!A8",'P-IngresoInventario'!A8) -> P-ING-004 | P24: ='P-IngresoInventario'!B8 -> Asegurar que los datos requeridos sean válidos en tipo de dato, longitud, obligatoriedad y formato | Q24: Generar una excepción indicando que los datos requeridos son inválidos o están incompletos | R24: Detener operación

Sheet E-IngresoInventario
A1: <<<Ir al modelo de dominio | B1: <<<Ir a objeto de dominio | C1: <<<Ir a muestreo del objeto | D1: <<<Ir a caracterización | E1: Ir a las políticas>>>
A2: Objeto de Dominio: | B2: ='Objetos de Dominio'!A20 -> IngresoInventario
A3: Descripción: | B3: ='Objetos de Dominio'!B20 -> Representa la factura de la llegada de nueva mercancía a una sede por parte de un proveedor que la creó previamente.
A4: Actor | B4: Action/Command | D4: Entity/Aggregate/Object domain | E4: Read Model | G4: Business Rule/Policy | I4: External System | J4: Domain Event | K4: Hotspot/questions/Risk
A5: Actor | B5: Acción | C5: Descripción | D5: Objeto de dominio | E5: Información externa | G5: Políticas | I5: Sistema Externo | J5: Evento | K5: Aspectos por solucionar
E6: Información | F6: Descripción | G6: Número | H6: Descripción
A7: Administrador | B7: Registrar un nuevo ingreso de inventario | C7: Permite registrar un nuevo ingreso de inventario en el sistema | D7: IngresoInventario | E7: Datos del nuevo ingreso de inventario | F7: Contiene la información requerida para registrar el ingreso de inventario | G7: =HYPERLINK("#'P-IngresoInventario'!A5",'P-IngresoInventario'!A5) -> P-ING-001 | H7: ='P-IngresoInventario'!B5 -> Asegurar que el id de ingreso de inventario sea único e irrepetible | J7: Ingreso de inventario registrado
G8: =HYPERLINK("#'P-IngresoInventario'!A6",'P-IngresoInventario'!A6) -> P-ING-002 | H8: ='P-IngresoInventario'!B6 -> Asegurar que solo se registren ingresos en una sede activa
G9: =HYPERLINK("#'P-IngresoInventario'!A7",'P-IngresoInventario'!A7) -> P-ING-003 | H9: ='P-IngresoInventario'!B7 -> Asegurar que el ingreso de inventario a una sede específica no ocurra al mismo tiempo que otro ingreso
G10: =HYPERLINK("#'P-IngresoInventario'!A8",'P-IngresoInventario'!A8) -> P-ING-004 | H10: ='P-IngresoInventario'!B8 -> Asegurar que los datos requeridos sean válidos en tipo de dato, longitud, obligatoriedad y formato
